Workbook

Sheet 考え方
B2: 計算クラスと、量クラスを区分する
C3: 例：テレビの買いかえ計算クラス － 消費量クラス（インスタンスはテレビ買い替えn台目）
B5: 設定値は計算クラスに設定
C6: 例：テレビの価格、テレビの性能等
B8: 対策計算では、なるべく「削減率」を通じて削減計算をする
B10: 1 | C10: 関数があればそれを選ぶ
B11: 2 | C11: 削減率の配列があればそれを選ぶ（Consで計算）
B12: 3 | C12: 設定値があればそれを選ぶ（ConsStrategy固定値）
A14: 消費量と対策を一括して計算をする
A15: 消費量は確定している状態で、対策の計算を一括で行う
A16: 分野の追加をする（追加をして、他の入力の追加も対応する）
A19: cons
B20: calc
B21: calcCO2
A22: measures
B23: calc
B24: calcCO2
B25: calcCO2Change
B26: dispDetail | D26: 対策ごとに、詳細について値を得ることができる
A31: PHPとActionscriptの両方に対応
B33: 消費量クラスでASかPHPかの記述を変更可能
B38: PHP
B40: AS
B41: PHP

Sheet readme
A1: Home Energy Diagnosis system language definition sheets
A3: use this sheets to magage parameters and translation
A4: please translate right color cell to left one. | D4: Fill cells of this color | E4: reference
A5: fill this sheet and copy "source code" cells to program code.
A7: sheet name | B7: target | C7: source code to paste
A8: Field | B8: "Field Name" and "Input field name" | C8: not use
A9: Items | B9: fill "Language set" | C9: d6/logic_**/senarofix.js
A10: Measures | B10: title, title short, easyness, subsidy, advice, | C10: d6/logic_**/senaroset.js
A11: Input | B11: title, unit, text, Input type, display value, save data | C11: d6/logic_**/senaroset.js
A12: Language | B12: fill "Language set" | C12: language/lang_**.php
A14: Area | B14: Place/Area, average templature(summer, winter) | C14: d6/logic_**/senaroset.js manual setting
A17: ver 2.1 | B17: create this readme sheet | C17: 43056
B18: Measures:change name hojoGov to subsidy
B19: Input: insert action valuation parameters
B20: Input: insert action valuation questions
B21: Items: add season
B22: Language: countfix_pre_after
A24: Ver3.0 | B24: not use js Language set combined to PHP | C24: 43058
B26: other misspelling | C26: 43064
B27: use Equipment list | C27: 44534

Sheet Field
A1: Field Code | F1: Fill cells of this color
B3: ID | C3: Field name | D3: Input field name | E3: code | F3: reference name | G3: reference input
B4: 0 | C4: 太陽光・契約 | D4: 家庭全般 | E4: TO | F4: 太陽光・契約 | G4: 家庭全般
B5: 1 | C5: 給湯・水道 | D5: 給湯・水道 | E5: HW | F5: 給湯・水道 | G5: 給湯・水道
B6: 2 | C6: 冷暖房 | D6: 冷暖房 | E6: AC | F6: 冷暖房 | G6: 冷暖房
B7: 3 | C7: 調理 | E7: CK | F7: 調理
B8: 4 | C8: 洗濯・衣類乾燥 | D8: 洗濯・乾燥 | E8: DR | F8: 洗濯・衣類乾燥 | G8: 洗濯・乾燥
B9: 5 | C9: 照明 | D9: 照明 | E9: LI | F9: 照明 | G9: 照明
B10: 6 | C10: テレビ | D10: テレビ・オーディオ | E10: TV | F10: テレビ | G10: テレビ・オーディオ
B11: 7 | C11: 冷蔵庫 | D11: 冷蔵庫 | E11: RF | F11: 冷蔵庫 | G11: 冷蔵庫
B12: 8 | C12: 自家用車 | E12: CR | F12: 自家用車
B13: 9 | C13: 待機電力・その他 | E13: OT | F13: 待機電力・その他
C14: 暖房 | D14: 暖房 | E14: HT | F14: 暖房 | G14: 暖房
C15: 冷房 | D15: 冷房 | E15: CO | F15: 冷房 | G15: 冷房
A17: Input Code | C17: range 100 is field ID | E17: ex. | F17: In100
A20: measure Code
C21: code name is "m" + fieldcode + name | E21: ex. | F21: mLIExchange

Sheet クラス
A1: Diagnosis
B2: 全てのクラス実体の保持。計算実行。
B4: Diagnosis | C4: コンストラクタ
B5: setSenario | C5: 初期構造設定 | D5: 消費量計算クラスの実装
D6: 消費量クラスの実装
D7: 消費量クラスの関連構造設定
D8: 対策クラスの実装（addMeasureAllCons）
D9: 入力変数の展開
D10: 質問リストの作成
B13: addMeasureAllCons | C13: 対策クラスの実装 | D13: addMeasureOneConsを複数回呼び出す
B16: addMeasureOneCons | C16: 対策１個の追加
B18: addCons | C18: 分野の追加 | D18: 消費量クラスの実装
D19: 消費量クラスの関連構造設定
D20: addMeasureOneConsを呼び出して対策を追加する
D21: 変数の追加
B23: calcConsAdjust | C23: 消費量計算の整合性 | D23: 補正率の算出
D24: cons::calcAdjustの呼び出し
B26: calcCons | C26: 消費量計算 | D26: 世帯人数・地域設定
D27: 初期計算
D28: 分野間関連計算
D29: 消費量計算の整合性（calcConsAdjust)
D30: 価格計算
B33: calcMeasures | C33: 対策自動計算 | D33: 選択状態の保存
D34: 選択状態のクリア
D35: １つずつ追加しての計算 cons.addReduction()
D36: 選択条件を戻す
B38: calcMeasuresLifestyle | C38: ライフスタイル対策のみ自動計算
B40: calcMeasuresOne | C40: 現状の対策計算 | D40: 現状状態で１回だけ計算をする
B42: measureAdd | C42: 対策選択を追加 | D42: フラグの設定
D43: calcMeasuresOneの実行
B45: measureDelete | C45: 対策選択を削除 | D45: フラグの設定
D46: 積み上げ直しcalcMeasuresの実行
B48: clearSelectedMeasures | C48: 全対策を削除 | D48: フラグをすべて解除
D49: calcMeasuresOneの実行
B51: rankIn100 | C51: 100世帯中順位 | D51: 順位計算
A54: Cons extended Energy
B55: 消費量値の実体、計算指示はこの実体に対して行われるが、計算は計算クラスに渡される。
B56: diagnosisクラスに配列として保持されている
B58: energy | D58: エネルギー種別の消費量
B59: value | D59: 対策計算等で使われる変数の保持
B60: logic | D60: 計算クラスへのリンク
B61: linkMeasure | D61: 対策クラスの配列へのリンク
B63: calc | C63: 消費量計算 | D63: 計算クラスを呼び出す
B65: calc2nd | C65: 他の分野との整合性 | D65: 計算クラスを呼び出す
B67: calcMeasure | C67: 対策の計算 | D67: 計算クラスを呼び出す（削減率の計算と設定）
B69: calcAdjust | C69: 補正実行 | D69: 割引の実行
D70: 各消費量ごとにcalcAdjustStrategyを実行
A72: Cons* extended logicBase
B73: 消費量計算、対策計算の実体
B74: 主にこのクラスの記述をすることで、計算方法を積み上げていく
B76: cons | D76: 消費量の実体
B77: cvalue | D77: 消費量クラスに保存される値の入れ物（cons.valueと同じ）
B79: calc | C79: 消費量計算 | D79: 入力値を参考に、消費量の計算、固定の削減率設定
B81: calc2nd | C81: 他の分野との整合性 | D81: 暖房など他の消費との調整が必要な対策のみ
B83: calcMeasure | C83: 対策の計算 | D83: 削減率の計算
D84: calcMeasureCommonの実行
B86: calcMeasureCommon | C86: 削減率計算 | D86: 削減率を用いた対策効果計算の一括実行
A93: Measure extended Energy
B94: diagnosisクラスに配列として保持されている。
B95: 対策として選択する場合に、個別に関数を実行する。
B96: 対策による効果（CO2、コスト等）を表示する。
B99: calcSave | C99: 削減量の算出 | D99: 現在からの削減量を算出する
B101: addReduction | C101: 選択による計算 | D101: 消費量を書き換えるとともに、関連する分野も削減する

Sheet 消費量クラス
A1: 消費量クラス一覧（ソースコードで設定） | G1: ※addMeasureで変更があったら伝える先 | P1: 消費計算クラス実装AS | R1: AS | S1: 消費クラス定義 | X1: AS { par1:data1, par2:data2…..} PHP ( para1=>data1, para2=>data2…..)
B2: ID | C2: クラス名 | D2: 短縮名 | E2: タイトル | F2: 初期実装数 0は増加できない | G2: 集約クラス1 | H2: 関連クラス2 | I2: 代替使用クラス | J2: 分野CODE | K2: 色 | L2: 簡素レベル | R2: 上記をASにするとActionScript それ以外はPHP | U2: 不要
C3: name | D3: nameCode | E3: title | F3: count | G3: sumClass | H3: refClass | I3: substituteClass | J3: code | K3: color | L3: level
B4: 0 | C4: consTotal | D4: TO | E4: 全体 | F4: 0 | J4: 0 | K4: 0xa9a9a9 | L4: 1 | R4: =IF($R$1="AS","consCalcList['","$consCalcList['")&C4&IF($R$1="AS","'] = new logic.C","'] = new C")&MID(C4,2,20)&"();" -> consCalcList['consTotal'] = new logic.ConsTotal(); | U4: =IF($R$1="AS","defCons['"&C4&"'] = { "&C$3&":'"&C4&"', "&D$3&": '"&D4&"', "&E$3&":'"&E4&"', "&F$3&":"&F4&", "&G$3&":'"&G4&"', "&H$3&":'"&H4&"', "&I$3&":'"&I4&"', "&J$3&":"&J4&", "&K$3&":'"&K4&"' };","$this->defCons['"&C4&"'] = [ '"&C4&"', '"&D4&"', '"&E4&"', "&F4&", '"&G4&"', '"&H4&"', '"&I4&"', "&J4&", '"&K4&"' ];") -> defCons['consTotal'] = { name:'consTotal', nameCode: 'TO', title:'全体', count:0, sumClass:'', refClass:'', substituteClass:'', code:0, color:'0xa9a9a9' };
B5: 1 | C5: consHWsum | D5: HW | E5: 給湯・水道 | F5: 0 | G5: consTotal | J5: 1 | K5: 0xffb700 | L5: 1 | R5: =IF($R$1="AS","consCalcList['","$consCalcList['")&C5&IF($R$1="AS","'] = new logic.C","'] = new C")&MID(C5,2,20)&"();" -> consCalcList['consHWsum'] = new logic.ConsHWsum(); | U5: =IF($R$1="AS","defCons['"&C5&"'] = { "&C$3&":'"&C5&"', "&D$3&": '"&D5&"', "&E$3&":'"&E5&"', "&F$3&":"&F5&", "&G$3&":'"&G5&"', "&H$3&":'"&H5&"', "&I$3&":'"&I5&"', "&J$3&":"&J5&", "&K$3&":'"&K5&"' };","$this->defCons['"&C5&"'] = [ '"&C5&"', '"&D5&"', '"&E5&"', "&F5&", '"&G5&"', '"&H5&"', '"&I5&"', "&J5&", '"&K5&"' ];") -> defCons['consHWsum'] = { name:'consHWsum', nameCode: 'HW', title:'給湯・水道', count:0, sumClass:'consTotal', refClass:'', substituteClass:'', code:1, color:'0xffb700' };
B6: 2 | C6: consHWtub | E6: 浴槽 | F6: 0 | G6: consHWsum | H6: consHWshower | J6: 1 | L6: 2 | R6: =IF($R$1="AS","consCalcList['","$consCalcList['")&C6&IF($R$1="AS","'] = new logic.C","'] = new C")&MID(C6,2,20)&"();" -> consCalcList['consHWtub'] = new logic.ConsHWtub(); | U6: =IF($R$1="AS","defCons['"&C6&"'] = { "&C$3&":'"&C6&"', "&D$3&": '"&D6&"', "&E$3&":'"&E6&"', "&F$3&":"&F6&", "&G$3&":'"&G6&"', "&H$3&":'"&H6&"', "&I$3&":'"&I6&"', "&J$3&":"&J6&", "&K$3&":'"&K6&"' };","$this->defCons['"&C6&"'] = [ '"&C6&"', '"&D6&"', '"&E6&"', "&F6&", '"&G6&"', '"&H6&"', '"&I6&"', "&J6&", '"&K6&"' ];") -> defCons['consHWtub'] = { name:'consHWtub', nameCode: '', title:'浴槽', count:0, sumClass:'consHWsum', refClass:'consHWshower', substituteClass:'', code:1, color:'' };
B7: 3 | C7: consHWshower | E7: シャワー | F7: 0 | G7: consHWsum | J7: 1 | L7: 2 | R7: =IF($R$1="AS","consCalcList['","$consCalcList['")&C7&IF($R$1="AS","'] = new logic.C","'] = new C")&MID(C7,2,20)&"();" -> consCalcList['consHWshower'] = new logic.ConsHWshower(); | U7: =IF($R$1="AS","defCons['"&C7&"'] = { "&C$3&":'"&C7&"', "&D$3&": '"&D7&"', "&E$3&":'"&E7&"', "&F$3&":"&F7&", "&G$3&":'"&G7&"', "&H$3&":'"&H7&"', "&I$3&":'"&I7&"', "&J$3&":"&J7&", "&K$3&":'"&K7&"' };","$this->defCons['"&C7&"'] = [ '"&C7&"', '"&D7&"', '"&E7&"', "&F7&", '"&G7&"', '"&H7&"', '"&I7&"', "&J7&", '"&K7&"' ];") -> defCons['consHWshower'] = { name:'consHWshower', nameCode: '', title:'シャワー', count:0, sumClass:'consHWsum', refClass:'', substituteClass:'', code:1, color:'' };
B8: 15 | C8: consHWdishwash | E8: 食洗 | F8: 0 | G8: consHWsum | J8: 1 | L8: 2 | R8: =IF($R$1="AS","consCalcList['","$consCalcList['")&C8&IF($R$1="AS","'] = new logic.C","'] = new C")&MID(C8,2,20)&"();" -> consCalcList['consHWdishwash'] = new logic.ConsHWdishwash(); | U8: =IF($R$1="AS","defCons['"&C8&"'] = { "&C$3&":'"&C8&"', "&D$3&": '"&D8&"', "&E$3&":'"&E8&"', "&F$3&":"&F8&", "&G$3&":'"&G8&"', "&H$3&":'"&H8&"', "&I$3&":'"&I8&"', "&J$3&":"&J8&", "&K$3&":'"&K8&"' };","$this->defCons['"&C8&"'] = [ '"&C8&"', '"&D8&"', '"&E8&"', "&F8&", '"&G8&"', '"&H8&"', '"&I8&"', "&J8&", '"&K8&"' ];") -> defCons['consHWdishwash'] = { name:'consHWdishwash', nameCode: '', title:'食洗', count:0, sumClass:'consHWsum', refClass:'', substituteClass:'', code:1, color:'' };
B9: 4 | C9: consHWdresser | E9: 洗面 | F9: 0 | G9: consHWsum | J9: 1 | L9: 3 | R9: =IF($R$1="AS","consCalcList['","$consCalcList['")&C9&IF($R$1="AS","'] = new logic.C","'] = new C")&MID(C9,2,20)&"();" -> consCalcList['consHWdresser'] = new logic.ConsHWdresser(); | U9: =IF($R$1="AS","defCons['"&C9&"'] = { "&C$3&":'"&C9&"', "&D$3&": '"&D9&"', "&E$3&":'"&E9&"', "&F$3&":"&F9&", "&G$3&":'"&G9&"', "&H$3&":'"&H9&"', "&I$3&":'"&I9&"', "&J$3&":"&J9&", "&K$3&":'"&K9&"' };","$this->defCons['"&C9&"'] = [ '"&C9&"', '"&D9&"', '"&E9&"', "&F9&", '"&G9&"', '"&H9&"', '"&I9&"', "&J9&", '"&K9&"' ];") -> defCons['consHWdresser'] = { name:'consHWdresser', nameCode: '', title:'洗面', count:0, sumClass:'consHWsum', refClass:'', substituteClass:'', code:1, color:'' };
B10: 5 | C10: consHWtoilet | E10: トイレ | F10: 0 | G10: consHWsum | J10: 1 | L10: 3 | R10: =IF($R$1="AS","consCalcList['","$consCalcList['")&C10&IF($R$1="AS","'] = new logic.C","'] = new C")&MID(C10,2,20)&"();" -> consCalcList['consHWtoilet'] = new logic.ConsHWtoilet(); | U10: =IF($R$1="AS","defCons['"&C10&"'] = { "&C$3&":'"&C10&"', "&D$3&": '"&D10&"', "&E$3&":'"&E10&"', "&F$3&":"&F10&", "&G$3&":'"&G10&"', "&H$3&":'"&H10&"', "&I$3&":'"&I10&"', "&J$3&":"&J10&", "&K$3&":'"&K10&"' };","$this->defCons['"&C10&"'] = [ '"&C10&"', '"&D10&"', '"&E10&"', "&F10&", '"&G10&"', '"&H10&"', '"&I10&"', "&J10&", '"&K10&"' ];") -> defCons['consHWtoilet'] = { name:'consHWtoilet', nameCode: '', title:'トイレ', count:0, sumClass:'consHWsum', refClass:'', substituteClass:'', code:1, color:'' };
B11: 6 | C11: consHTsum | D11: HT | E11: 暖房 | F11: 0 | G11: consTotal | H11: consHW | J11: 2 | K11: 0xff0000 | L11: 1 | M11: ※床温水暖房など | R11: =IF($R$1="AS","consCalcList['","$consCalcList['")&C11&IF($R$1="AS","'] = new logic.C","'] = new C")&MID(C11,2,20)&"();" -> consCalcList['consHTsum'] = new logic.ConsHTsum(); | U11: =IF($R$1="AS","defCons['"&C11&"'] = { "&C$3&":'"&C11&"', "&D$3&": '"&D11&"', "&E$3&":'"&E11&"', "&F$3&":"&F11&", "&G$3&":'"&G11&"', "&H$3&":'"&H11&"', "&I$3&":'"&I11&"', "&J$3&":"&J11&", "&K$3&":'"&K11&"' };","$this->defCons['"&C11&"'] = [ '"&C11&"', '"&D11&"', '"&E11&"', "&F11&", '"&G11&"', '"&H11&"', '"&I11&"', "&J11&", '"&K11&"' ];") -> defCons['consHTsum'] = { name:'consHTsum', nameCode: 'HT', title:'暖房', count:0, sumClass:'consTotal', refClass:'consHW', substituteClass:'', code:2, color:'0xff0000' };
B12: 7 | C12: consCOsum | D12: CO | E12: 冷房除湿 | F12: 0 | G12: consTotal | J12: 2 | K12: 0x0000ff | L12: 1 | R12: =IF($R$1="AS","consCalcList['","$consCalcList['")&C12&IF($R$1="AS","'] = new logic.C","'] = new C")&MID(C12,2,20)&"();" -> consCalcList['consCOsum'] = new logic.ConsCOsum(); | U12: =IF($R$1="AS","defCons['"&C12&"'] = { "&C$3&":'"&C12&"', "&D$3&": '"&D12&"', "&E$3&":'"&E12&"', "&F$3&":"&F12&", "&G$3&":'"&G12&"', "&H$3&":'"&H12&"', "&I$3&":'"&I12&"', "&J$3&":"&J12&", "&K$3&":'"&K12&"' };","$this->defCons['"&C12&"'] = [ '"&C12&"', '"&D12&"', '"&E12&"', "&F12&", '"&G12&"', '"&H12&"', '"&I12&"', "&J12&", '"&K12&"' ];") -> defCons['consCOsum'] = { name:'consCOsum', nameCode: 'CO', title:'冷房除湿', count:0, sumClass:'consTotal', refClass:'', substituteClass:'', code:2, color:'0x0000ff' };
B13: 8 | C13: consAC | E13: 個別冷暖房 | F13: 3 | J13: 2 | L13: 3 | R13: =IF($R$1="AS","consCalcList['","$consCalcList['")&C13&IF($R$1="AS","'] = new logic.C","'] = new C")&MID(C13,2,20)&"();" -> consCalcList['consAC'] = new logic.ConsAC(); | U13: =IF($R$1="AS","defCons['"&C13&"'] = { "&C$3&":'"&C13&"', "&D$3&": '"&D13&"', "&E$3&":'"&E13&"', "&F$3&":"&F13&", "&G$3&":'"&G13&"', "&H$3&":'"&H13&"', "&I$3&":'"&I13&"', "&J$3&":"&J13&", "&K$3&":'"&K13&"' };","$this->defCons['"&C13&"'] = [ '"&C13&"', '"&D13&"', '"&E13&"', "&F13&", '"&G13&"', '"&H13&"', '"&I13&"', "&J13&", '"&K13&"' ];") -> defCons['consAC'] = { name:'consAC', nameCode: '', title:'個別冷暖房', count:3, sumClass:'', refClass:'', substituteClass:'', code:2, color:'' };
B14: 9 | C14: consACheat | E14: 個別暖房 | F14: 3 | G14: consHTsum | H14: consAC | J14: 2 | L14: 2 | R14: =IF($R$1="AS","consCalcList['","$consCalcList['")&C14&IF($R$1="AS","'] = new logic.C","'] = new C")&MID(C14,2,20)&"();" -> consCalcList['consACheat'] = new logic.ConsACheat(); | U14: =IF($R$1="AS","defCons['"&C14&"'] = { "&C$3&":'"&C14&"', "&D$3&": '"&D14&"', "&E$3&":'"&E14&"', "&F$3&":"&F14&", "&G$3&":'"&G14&"', "&H$3&":'"&H14&"', "&I$3&":'"&I14&"', "&J$3&":"&J14&", "&K$3&":'"&K14&"' };","$this->defCons['"&C14&"'] = [ '"&C14&"', '"&D14&"', '"&E14&"', "&F14&", '"&G14&"', '"&H14&"', '"&I14&"', "&J14&", '"&K14&"' ];") -> defCons['consACheat'] = { name:'consACheat', nameCode: '', title:'個別暖房', count:3, sumClass:'consHTsum', refClass:'consAC', substituteClass:'', code:2, color:'' };
B15: 10 | C15: consACcool | E15: 個別冷房 | F15: 3 | G15: consCOsum | H15: consAC | J15: 2 | L15: 2 | R15: =IF($R$1="AS","consCalcList['","$consCalcList['")&C15&IF($R$1="AS","'] = new logic.C","'] = new C")&MID(C15,2,20)&"();" -> consCalcList['consACcool'] = new logic.ConsACcool(); | U15: =IF($R$1="AS","defCons['"&C15&"'] = { "&C$3&":'"&C15&"', "&D$3&": '"&D15&"', "&E$3&":'"&E15&"', "&F$3&":"&F15&", "&G$3&":'"&G15&"', "&H$3&":'"&H15&"', "&I$3&":'"&I15&"', "&J$3&":"&J15&", "&K$3&":'"&K15&"' };","$this->defCons['"&C15&"'] = [ '"&C15&"', '"&D15&"', '"&E15&"', "&F15&", '"&G15&"', '"&H15&"', '"&I15&"', "&J15&", '"&K15&"' ];") -> defCons['consACcool'] = { name:'consACcool', nameCode: '', title:'個別冷房', count:3, sumClass:'consCOsum', refClass:'consAC', substituteClass:'', code:2, color:'' };
B16: 11 | C16: consRFsum | D16: RF | E16: 冷蔵庫 | F16: 0 | G16: consTotal | I16: consSum | J16: 3 | K16: 0x80ff80 | L16: 1 | R16: =IF($R$1="AS","consCalcList['","$consCalcList['")&C16&IF($R$1="AS","'] = new logic.C","'] = new C")&MID(C16,2,20)&"();" -> consCalcList['consRFsum'] = new logic.ConsRFsum(); | U16: =IF($R$1="AS","defCons['"&C16&"'] = { "&C$3&":'"&C16&"', "&D$3&": '"&D16&"', "&E$3&":'"&E16&"', "&F$3&":"&F16&", "&G$3&":'"&G16&"', "&H$3&":'"&H16&"', "&I$3&":'"&I16&"', "&J$3&":"&J16&", "&K$3&":'"&K16&"' };","$this->defCons['"&C16&"'] = [ '"&C16&"', '"&D16&"', '"&E16&"', "&F16&", '"&G16&"', '"&H16&"', '"&I16&"', "&J16&", '"&K16&"' ];") -> defCons['consRFsum'] = { name:'consRFsum', nameCode: 'RF', title:'冷蔵庫', count:0, sumClass:'consTotal', refClass:'', substituteClass:'consSum', code:3, color:'0x80ff80' };
B17: 12 | C17: consRF | E17: 冷蔵庫 | F17: 2 | G17: consRFsum | J17: 3 | L17: 2 | R17: =IF($R$1="AS","consCalcList['","$consCalcList['")&C17&IF($R$1="AS","'] = new logic.C","'] = new C")&MID(C17,2,20)&"();" -> consCalcList['consRF'] = new logic.ConsRF(); | U17: =IF($R$1="AS","defCons['"&C17&"'] = { "&C$3&":'"&C17&"', "&D$3&": '"&D17&"', "&E$3&":'"&E17&"', "&F$3&":"&F17&", "&G$3&":'"&G17&"', "&H$3&":'"&H17&"', "&I$3&":'"&I17&"', "&J$3&":"&J17&", "&K$3&":'"&K17&"' };","$this->defCons['"&C17&"'] = [ '"&C17&"', '"&D17&"', '"&E17&"', "&F17&", '"&G17&"', '"&H17&"', '"&I17&"', "&J17&", '"&K17&"' ];") -> defCons['consRF'] = { name:'consRF', nameCode: '', title:'冷蔵庫', count:2, sumClass:'consRFsum', refClass:'', substituteClass:'', code:3, color:'' };
B18: 13 | C18: consCKsum | D18: CK | E18: 調理 | F18: 0 | G18: consTotal | I18: consSum | J18: 4 | K18: 0xffe4b5 | L18: 1 | R18: =IF($R$1="AS","consCalcList['","$consCalcList['")&C18&IF($R$1="AS","'] = new logic.C","'] = new C")&MID(C18,2,20)&"();" -> consCalcList['consCKsum'] = new logic.ConsCKsum(); | U18: =IF($R$1="AS","defCons['"&C18&"'] = { "&C$3&":'"&C18&"', "&D$3&": '"&D18&"', "&E$3&":'"&E18&"', "&F$3&":"&F18&", "&G$3&":'"&G18&"', "&H$3&":'"&H18&"', "&I$3&":'"&I18&"', "&J$3&":"&J18&", "&K$3&":'"&K18&"' };","$this->defCons['"&C18&"'] = [ '"&C18&"', '"&D18&"', '"&E18&"', "&F18&", '"&G18&"', '"&H18&"', '"&I18&"', "&J18&", '"&K18&"' ];") -> defCons['consCKsum'] = { name:'consCKsum', nameCode: 'CK', title:'調理', count:0, sumClass:'consTotal', refClass:'', substituteClass:'consSum', code:4, color:'0xffe4b5' };
B19: 14 | C19: consCKcook | E19: 調理 | F19: 0 | G19: consCKsum | J19: 4 | L19: 3 | R19: =IF($R$1="AS","consCalcList['","$consCalcList['")&C19&IF($R$1="AS","'] = new logic.C","'] = new C")&MID(C19,2,20)&"();" -> consCalcList['consCKcook'] = new logic.ConsCKcook(); | U19: =IF($R$1="AS","defCons['"&C19&"'] = { "&C$3&":'"&C19&"', "&D$3&": '"&D19&"', "&E$3&":'"&E19&"', "&F$3&":"&F19&", "&G$3&":'"&G19&"', "&H$3&":'"&H19&"', "&I$3&":'"&I19&"', "&J$3&":"&J19&", "&K$3&":'"&K19&"' };","$this->defCons['"&C19&"'] = [ '"&C19&"', '"&D19&"', '"&E19&"', "&F19&", '"&G19&"', '"&H19&"', '"&I19&"', "&J19&", '"&K19&"' ];") -> defCons['consCKcook'] = { name:'consCKcook', nameCode: '', title:'調理', count:0, sumClass:'consCKsum', refClass:'', substituteClass:'', code:4, color:'' };
B20: 16 | C20: consCKplug | E20: 待機 | F20: 0 | G20: consCKsum | J20: 4 | L20: 3 | R20: =IF($R$1="AS","consCalcList['","$consCalcList['")&C20&IF($R$1="AS","'] = new logic.C","'] = new C")&MID(C20,2,20)&"();" -> consCalcList['consCKplug'] = new logic.ConsCKplug(); | U20: =IF($R$1="AS","defCons['"&C20&"'] = { "&C$3&":'"&C20&"', "&D$3&": '"&D20&"', "&E$3&":'"&E20&"', "&F$3&":"&F20&", "&G$3&":'"&G20&"', "&H$3&":'"&H20&"', "&I$3&":'"&I20&"', "&J$3&":"&J20&", "&K$3&":'"&K20&"' };","$this->defCons['"&C20&"'] = [ '"&C20&"', '"&D20&"', '"&E20&"', "&F20&", '"&G20&"', '"&H20&"', '"&I20&"', "&J20&", '"&K20&"' ];") -> defCons['consCKplug'] = { name:'consCKplug', nameCode: '', title:'待機', count:0, sumClass:'consCKsum', refClass:'', substituteClass:'', code:4, color:'' };
B21: 17 | C21: consCKpot | E21: ポット | F21: 0 | G21: consCKsum | J21: 4 | L21: 3 | R21: =IF($R$1="AS","consCalcList['","$consCalcList['")&C21&IF($R$1="AS","'] = new logic.C","'] = new C")&MID(C21,2,20)&"();" -> consCalcList['consCKpot'] = new logic.ConsCKpot(); | U21: =IF($R$1="AS","defCons['"&C21&"'] = { "&C$3&":'"&C21&"', "&D$3&": '"&D21&"', "&E$3&":'"&E21&"', "&F$3&":"&F21&", "&G$3&":'"&G21&"', "&H$3&":'"&H21&"', "&I$3&":'"&I21&"', "&J$3&":"&J21&", "&K$3&":'"&K21&"' };","$this->defCons['"&C21&"'] = [ '"&C21&"', '"&D21&"', '"&E21&"', "&F21&", '"&G21&"', '"&H21&"', '"&I21&"', "&J21&", '"&K21&"' ];") -> defCons['consCKpot'] = { name:'consCKpot', nameCode: '', title:'ポット', count:0, sumClass:'consCKsum', refClass:'', substituteClass:'', code:4, color:'' };
B22: 18 | C22: consCKrice | E22: 炊飯ジャー | F22: 0 | G22: consCKsum | J22: 4 | L22: 3 | R22: =IF($R$1="AS","consCalcList['","$consCalcList['")&C22&IF($R$1="AS","'] = new logic.C","'] = new C")&MID(C22,2,20)&"();" -> consCalcList['consCKrice'] = new logic.ConsCKrice(); | U22: =IF($R$1="AS","defCons['"&C22&"'] = { "&C$3&":'"&C22&"', "&D$3&": '"&D22&"', "&E$3&":'"&E22&"', "&F$3&":"&F22&", "&G$3&":'"&G22&"', "&H$3&":'"&H22&"', "&I$3&":'"&I22&"', "&J$3&":"&J22&", "&K$3&":'"&K22&"' };","$this->defCons['"&C22&"'] = [ '"&C22&"', '"&D22&"', '"&E22&"', "&F22&", '"&G22&"', '"&H22&"', '"&I22&"', "&J22&", '"&K22&"' ];") -> defCons['consCKrice'] = { name:'consCKrice', nameCode: '', title:'炊飯ジャー', count:0, sumClass:'consCKsum', refClass:'', substituteClass:'', code:4, color:'' };
B23: 19 | C23: consDRsum | D23: DR | E23: 洗濯乾燥 | F23: 0 | G23: consTotal | J23: 5 | K23: 0x00ffff | L23: 1 | R23: =IF($R$1="AS","consCalcList['","$consCalcList['")&C23&IF($R$1="AS","'] = new logic.C","'] = new C")&MID(C23,2,20)&"();" -> consCalcList['consDRsum'] = new logic.ConsDRsum(); | U23: =IF($R$1="AS","defCons['"&C23&"'] = { "&C$3&":'"&C23&"', "&D$3&": '"&D23&"', "&E$3&":'"&E23&"', "&F$3&":"&F23&", "&G$3&":'"&G23&"', "&H$3&":'"&H23&"', "&I$3&":'"&I23&"', "&J$3&":"&J23&", "&K$3&":'"&K23&"' };","$this->defCons['"&C23&"'] = [ '"&C23&"', '"&D23&"', '"&E23&"', "&F23&", '"&G23&"', '"&H23&"', '"&I23&"', "&J23&", '"&K23&"' ];") -> defCons['consDRsum'] = { name:'consDRsum', nameCode: 'DR', title:'洗濯乾燥', count:0, sumClass:'consTotal', refClass:'', substituteClass:'', code:5, color:'0x00ffff' };
B24: 20 | C24: consDRwash | E24: 洗濯 | F24: 0 | G24: consDRsum | J24: 5 | L24: 3 | R24: =IF($R$1="AS","consCalcList['","$consCalcList['")&C24&IF($R$1="AS","'] = new logic.C","'] = new C")&MID(C24,2,20)&"();" -> consCalcList['consDRwash'] = new logic.ConsDRwash(); | U24: =IF($R$1="AS","defCons['"&C24&"'] = { "&C$3&":'"&C24&"', "&D$3&": '"&D24&"', "&E$3&":'"&E24&"', "&F$3&":"&F24&", "&G$3&":'"&G24&"', "&H$3&":'"&H24&"', "&I$3&":'"&I24&"', "&J$3&":"&J24&", "&K$3&":'"&K24&"' };","$this->defCons['"&C24&"'] = [ '"&C24&"', '"&D24&"', '"&E24&"', "&F24&", '"&G24&"', '"&H24&"', '"&I24&"', "&J24&", '"&K24&"' ];") -> defCons['consDRwash'] = { name:'consDRwash', nameCode: '', title:'洗濯', count:0, sumClass:'consDRsum', refClass:'', substituteClass:'', code:5, color:'' };
B25: 21 | C25: consDRdry | E25: 乾燥 | F25: 0 | G25: consDRsum | J25: 5 | L25: 3 | R25: =IF($R$1="AS","consCalcList['","$consCalcList['")&C25&IF($R$1="AS","'] = new logic.C","'] = new C")&MID(C25,2,20)&"();" -> consCalcList['consDRdry'] = new logic.ConsDRdry(); | U25: =IF($R$1="AS","defCons['"&C25&"'] = { "&C$3&":'"&C25&"', "&D$3&": '"&D25&"', "&E$3&":'"&E25&"', "&F$3&":"&F25&", "&G$3&":'"&G25&"', "&H$3&":'"&H25&"', "&I$3&":'"&I25&"', "&J$3&":"&J25&", "&K$3&":'"&K25&"' };","$this->defCons['"&C25&"'] = [ '"&C25&"', '"&D25&"', '"&E25&"', "&F25&", '"&G25&"', '"&H25&"', '"&I25&"', "&J25&", '"&K25&"' ];") -> defCons['consDRdry'] = { name:'consDRdry', nameCode: '', title:'乾燥', count:0, sumClass:'consDRsum', refClass:'', substituteClass:'', code:5, color:'' };
B26: 22 | C26: consLIsum | D26: LI | E26: 照明 | F26: 0 | G26: consTotal | I26: consSum | J26: 6 | K26: 0xffff00 | L26: 1 | R26: =IF($R$1="AS","consCalcList['","$consCalcList['")&C26&IF($R$1="AS","'] = new logic.C","'] = new C")&MID(C26,2,20)&"();" -> consCalcList['consLIsum'] = new logic.ConsLIsum(); | U26: =IF($R$1="AS","defCons['"&C26&"'] = { "&C$3&":'"&C26&"', "&D$3&": '"&D26&"', "&E$3&":'"&E26&"', "&F$3&":"&F26&", "&G$3&":'"&G26&"', "&H$3&":'"&H26&"', "&I$3&":'"&I26&"', "&J$3&":"&J26&", "&K$3&":'"&K26&"' };","$this->defCons['"&C26&"'] = [ '"&C26&"', '"&D26&"', '"&E26&"', "&F26&", '"&G26&"', '"&H26&"', '"&I26&"', "&J26&", '"&K26&"' ];") -> defCons['consLIsum'] = { name:'consLIsum', nameCode: 'LI', title:'照明', count:0, sumClass:'consTotal', refClass:'', substituteClass:'consSum', code:6, color:'0xffff00' };
B27: 23 | C27: consLI | E27: 照明 | F27: 3 | G27: consLIsum | J27: 6 | L27: 2 | R27: =IF($R$1="AS","consCalcList['","$consCalcList['")&C27&IF($R$1="AS","'] = new logic.C","'] = new C")&MID(C27,2,20)&"();" -> consCalcList['consLI'] = new logic.ConsLI(); | U27: =IF($R$1="AS","defCons['"&C27&"'] = { "&C$3&":'"&C27&"', "&D$3&": '"&D27&"', "&E$3&":'"&E27&"', "&F$3&":"&F27&", "&G$3&":'"&G27&"', "&H$3&":'"&H27&"', "&I$3&":'"&I27&"', "&J$3&":"&J27&", "&K$3&":'"&K27&"' };","$this->defCons['"&C27&"'] = [ '"&C27&"', '"&D27&"', '"&E27&"', "&F27&", '"&G27&"', '"&H27&"', '"&I27&"', "&J27&", '"&K27&"' ];") -> defCons['consLI'] = { name:'consLI', nameCode: '', title:'照明', count:3, sumClass:'consLIsum', refClass:'', substituteClass:'', code:6, color:'' };
B28: 24 | C28: consTVsum | D28: TV | E28: テレビ | F28: 0 | G28: consTotal | I28: consSum | J28: 7 | K28: 0x00ff00 | L28: 1 | R28: =IF($R$1="AS","consCalcList['","$consCalcList['")&C28&IF($R$1="AS","'] = new logic.C","'] = new C")&MID(C28,2,20)&"();" -> consCalcList['consTVsum'] = new logic.ConsTVsum(); | U28: =IF($R$1="AS","defCons['"&C28&"'] = { "&C$3&":'"&C28&"', "&D$3&": '"&D28&"', "&E$3&":'"&E28&"', "&F$3&":"&F28&", "&G$3&":'"&G28&"', "&H$3&":'"&H28&"', "&I$3&":'"&I28&"', "&J$3&":"&J28&", "&K$3&":'"&K28&"' };","$this->defCons['"&C28&"'] = [ '"&C28&"', '"&D28&"', '"&E28&"', "&F28&", '"&G28&"', '"&H28&"', '"&I28&"', "&J28&", '"&K28&"' ];") -> defCons['consTVsum'] = { name:'consTVsum', nameCode: 'TV', title:'テレビ', count:0, sumClass:'consTotal', refClass:'', substituteClass:'consSum', code:7, color:'0x00ff00' };
B29: 25 | C29: consTV | E29: テレビ | F29: 3 | G29: consTVsum | J29: 7 | L29: 3 | R29: =IF($R$1="AS","consCalcList['","$consCalcList['")&C29&IF($R$1="AS","'] = new logic.C","'] = new C")&MID(C29,2,20)&"();" -> consCalcList['consTV'] = new logic.ConsTV(); | U29: =IF($R$1="AS","defCons['"&C29&"'] = { "&C$3&":'"&C29&"', "&D$3&": '"&D29&"', "&E$3&":'"&E29&"', "&F$3&":"&F29&", "&G$3&":'"&G29&"', "&H$3&":'"&H29&"', "&I$3&":'"&I29&"', "&J$3&":"&J29&", "&K$3&":'"&K29&"' };","$this->defCons['"&C29&"'] = [ '"&C29&"', '"&D29&"', '"&E29&"', "&F29&", '"&G29&"', '"&H29&"', '"&I29&"', "&J29&", '"&K29&"' ];") -> defCons['consTV'] = { name:'consTV', nameCode: '', title:'テレビ', count:3, sumClass:'consTVsum', refClass:'', substituteClass:'', code:7, color:'' };
B30: 26 | C30: consCRsum | D30: CR | E30: 交通 | F30: 0 | G30: consTotal | J30: 8 | K30: 0xee82ee | L30: 1 | R30: =IF($R$1="AS","consCalcList['","$consCalcList['")&C30&IF($R$1="AS","'] = new logic.C","'] = new C")&MID(C30,2,20)&"();" -> consCalcList['consCRsum'] = new logic.ConsCRsum(); | U30: =IF($R$1="AS","defCons['"&C30&"'] = { "&C$3&":'"&C30&"', "&D$3&": '"&D30&"', "&E$3&":'"&E30&"', "&F$3&":"&F30&", "&G$3&":'"&G30&"', "&H$3&":'"&H30&"', "&I$3&":'"&I30&"', "&J$3&":"&J30&", "&K$3&":'"&K30&"' };","$this->defCons['"&C30&"'] = [ '"&C30&"', '"&D30&"', '"&E30&"', "&F30&", '"&G30&"', '"&H30&"', '"&I30&"', "&J30&", '"&K30&"' ];") -> defCons['consCRsum'] = { name:'consCRsum', nameCode: 'CR', title:'交通', count:0, sumClass:'consTotal', refClass:'', substituteClass:'', code:8, color:'0xee82ee' };
B31: 27 | C31: consCR | E31: 車 | F31: 3 | G31: consCRsum | H31: consCRtrip | J31: 8 | L31: 3 | R31: =IF($R$1="AS","consCalcList['","$consCalcList['")&C31&IF($R$1="AS","'] = new logic.C","'] = new C")&MID(C31,2,20)&"();" -> consCalcList['consCR'] = new logic.ConsCR(); | U31: =IF($R$1="AS","defCons['"&C31&"'] = { "&C$3&":'"&C31&"', "&D$3&": '"&D31&"', "&E$3&":'"&E31&"', "&F$3&":"&F31&", "&G$3&":'"&G31&"', "&H$3&":'"&H31&"', "&I$3&":'"&I31&"', "&J$3&":"&J31&", "&K$3&":'"&K31&"' };","$this->defCons['"&C31&"'] = [ '"&C31&"', '"&D31&"', '"&E31&"', "&F31&", '"&G31&"', '"&H31&"', '"&I31&"', "&J31&", '"&K31&"' ];") -> defCons['consCR'] = { name:'consCR', nameCode: '', title:'車', count:3, sumClass:'consCRsum', refClass:'consCRtrip', substituteClass:'', code:8, color:'' };
B32: 28 | C32: consCRtrip | E32: 交通 | F32: 5 | G32: consCRsum | H32: consCR | J32: 8 | L32: 2 | R32: =IF($R$1="AS","consCalcList['","$consCalcList['")&C32&IF($R$1="AS","'] = new logic.C","'] = new C")&MID(C32,2,20)&"();" -> consCalcList['consCRtrip'] = new logic.ConsCRtrip(); | U32: =IF($R$1="AS","defCons['"&C32&"'] = { "&C$3&":'"&C32&"', "&D$3&": '"&D32&"', "&E$3&":'"&E32&"', "&F$3&":"&F32&", "&G$3&":'"&G32&"', "&H$3&":'"&H32&"', "&I$3&":'"&I32&"', "&J$3&":"&J32&", "&K$3&":'"&K32&"' };","$this->defCons['"&C32&"'] = [ '"&C32&"', '"&D32&"', '"&E32&"', "&F32&", '"&G32&"', '"&H32&"', '"&I32&"', "&J32&", '"&K32&"' ];") -> defCons['consCRtrip'] = { name:'consCRtrip', nameCode: '', title:'交通', count:5, sumClass:'consCRsum', refClass:'consCR', substituteClass:'', code:8, color:'' };
B33: 29 | C33: consOTsum | D33: OT | E33: 待機・その他 | F33: 0 | G33: consTotal | I33: consSum | J33: 9 | K33: 0xd2691e | L33: 1 | M33: ※積み上げのみ | R33: =IF($R$1="AS","consCalcList['","$consCalcList['")&C33&IF($R$1="AS","'] = new logic.C","'] = new C")&MID(C33,2,20)&"();" -> consCalcList['consOTsum'] = new logic.ConsOTsum(); | U33: =IF($R$1="AS","defCons['"&C33&"'] = { "&C$3&":'"&C33&"', "&D$3&": '"&D33&"', "&E$3&":'"&E33&"', "&F$3&":"&F33&", "&G$3&":'"&G33&"', "&H$3&":'"&H33&"', "&I$3&":'"&I33&"', "&J$3&":"&J33&", "&K$3&":'"&K33&"' };","$this->defCons['"&C33&"'] = [ '"&C33&"', '"&D33&"', '"&E33&"', "&F33&", '"&G33&"', '"&H33&"', '"&I33&"', "&J33&", '"&K33&"' ];") -> defCons['consOTsum'] = { name:'consOTsum', nameCode: 'OT', title:'待機・その他', count:0, sumClass:'consTotal', refClass:'', substituteClass:'consSum', code:9, color:'0xd2691e' };
B34: 30 | C34: consOT | E34: 待機・その他 | F34: 3 | G34: consOTsum | J34: 9 | L34: 3 | R34: =IF($R$1="AS","consCalcList['","$consCalcList['")&C34&IF($R$1="AS","'] = new logic.C","'] = new C")&MID(C34,2,20)&"();" -> consCalcList['consOT'] = new logic.ConsOT(); | U34: =IF($R$1="AS","defCons['"&C34&"'] = { "&C$3&":'"&C34&"', "&D$3&": '"&D34&"', "&E$3&":'"&E34&"', "&F$3&":"&F34&", "&G$3&":'"&G34&"', "&H$3&":'"&H34&"', "&I$3&":'"&I34&"', "&J$3&":"&J34&", "&K$3&":'"&K34&"' };","$this->defCons['"&C34&"'] = [ '"&C34&"', '"&D34&"', '"&E34&"', "&F34&", '"&G34&"', '"&H34&"', '"&I34&"', "&J34&", '"&K34&"' ];") -> defCons['consOT'] = { name:'consOT', nameCode: '', title:'待機・その他', count:3, sumClass:'consOTsum', refClass:'', substituteClass:'', code:9, color:'' };
C37: 暖房が、各部屋の合計にならない場合には、部屋を1つ追加して「その他差分」を設定しておく。
C38: 各機器まで落とすことができるかどうか

Sheet Iems
A1: set in D6/senariofix.js | C1: language set | D1: refernce
A2: =CLEAN(B2&IF(C2="","",""""&C2&""";"))
A3: =CLEAN(B3&IF(C3="","",""""&C3&""";")) -> D6.consAC.title = "部屋空調"; | B3: D6.consAC.title = | C3: 部屋空調 | D3: room air conditioning
A4: =CLEAN(B4&IF(C4="","",""""&C4&""";")) -> D6.consAC.countCall = "部屋目"; | B4: D6.consAC.countCall = | C4: 部屋目 | D4: room
A5: =CLEAN(B5&IF(C5="","",""""&C5&""";"))
A6: =CLEAN(B6&IF(C6="","",""""&C6&""";")) -> D6.consACcool.title = "部屋冷房"; | B6: D6.consACcool.title = | C6: 部屋冷房 | D6: room air conditioning
A7: =CLEAN(B7&IF(C7="","",""""&C7&""";")) -> D6.consACcool.addable = "冷暖房する部屋"; | B7: D6.consACcool.addable = | C7: 冷暖房する部屋 | D7: room air conditioning
A8: =CLEAN(B8&IF(C8="","",""""&C8&""";")) -> D6.consACcool.countCall = "部屋目"; | B8: D6.consACcool.countCall = | C8: 部屋目 | D8: room #
A9: =CLEAN(B9&IF(C9="","",""""&C9&""";")) -> D6.consACcool.inputGuide = "部屋ごとの冷房の使い方について"; | B9: D6.consACcool.inputGuide = | C9: 部屋ごとの冷房の使い方について | D9: how to use air conditioning for each room
A10: =CLEAN(B10&IF(C10="","",""""&C10&""";"))
A11: =CLEAN(B11&IF(C11="","",""""&C11&""";")) -> D6.consACheat.title = "部屋暖房"; | B11: D6.consACheat.title = | C11: 部屋暖房 | D11: room heating
A12: =CLEAN(B12&IF(C12="","",""""&C12&""";")) -> D6.consACheat.addable = "冷暖房する部屋"; | B12: D6.consACheat.addable = | C12: 冷暖房する部屋 | D12: room air conditioning
A13: =CLEAN(B13&IF(C13="","",""""&C13&""";")) -> D6.consACheat.countCall = "部屋目"; | B13: D6.consACheat.countCall = | C13: 部屋目 | D13: room #
A14: =CLEAN(B14&IF(C14="","",""""&C14&""";")) -> D6.consACheat.inputGuide = "部屋ごとの暖房の使い方について"; | B14: D6.consACheat.inputGuide = | C14: 部屋ごとの暖房の使い方について | D14: how to use each room heating
A15: =CLEAN(B15&IF(C15="","",""""&C15&""";"))
A16: =CLEAN(B16&IF(C16="","",""""&C16&""";")) -> D6.consCKcook.title = "調理"; | B16: D6.consCKcook.title = | C16: 調理 | D16: Cooking
A17: =CLEAN(B17&IF(C17="","",""""&C17&""";")) -> D6.consCKcook.inputGuide = "コンロを中心とした調理の使い方について"; | B17: D6.consCKcook.inputGuide = | C17: コンロを中心とした調理の使い方について | D17: How to use cooking to focus on the stove
A18: =CLEAN(B18&IF(C18="","",""""&C18&""";"))
A19: =CLEAN(B19&IF(C19="","",""""&C19&""";")) -> D6.consCKpot.title = "保温"; | B19: D6.consCKpot.title = | C19: 保温 | D19: adiabatic
A20: =CLEAN(B20&IF(C20="","",""""&C20&""";")) -> D6.consCKpot.inputGuide = "保温器具の使い方について"; | B20: D6.consCKpot.inputGuide = | C20: 保温器具の使い方について | D20: How to use insulation
A21: =CLEAN(B21&IF(C21="","",""""&C21&""";"))
A22: =CLEAN(B22&IF(C22="","",""""&C22&""";")) -> D6.consCKrice.title = "炊飯"; | B22: D6.consCKrice.title = | C22: 炊飯 | D22: rice cook
A23: =CLEAN(B23&IF(C23="","",""""&C23&""";")) -> D6.consCKrice.inputGuide = "炊飯の使い方について"; | B23: D6.consCKrice.inputGuide = | C23: 炊飯の使い方について | D23: how to use a rice cooker
A24: =CLEAN(B24&IF(C24="","",""""&C24&""";"))
A25: =CLEAN(B25&IF(C25="","",""""&C25&""";")) -> D6.consCKsum.title = "調理"; | B25: D6.consCKsum.title = | C25: 調理 | D25: Cooking
A26: =CLEAN(B26&IF(C26="","",""""&C26&""";")) -> D6.consCKsum.inputGuide = "調理関連の使い方について"; | B26: D6.consCKsum.inputGuide = | C26: 調理関連の使い方について | D26: How to use cooking related
A27: =CLEAN(B27&IF(C27="","",""""&C27&""";"))
A28: =CLEAN(B28&IF(C28="","",""""&C28&""";")) -> D6.consCOsum.title = "冷房"; | B28: D6.consCOsum.title = | C28: 冷房 | D28: cool
A29: =CLEAN(B29&IF(C29="","",""""&C29&""";")) -> D6.consCOsum.inputGuide = "家全体での冷房の使い方について"; | B29: D6.consCOsum.inputGuide = | C29: 家全体での冷房の使い方について | D29: how to use air conditioning in the whole house
A30: =CLEAN(B30&IF(C30="","",""""&C30&""";"))
A31: =CLEAN(B31&IF(C31="","",""""&C31&""";")) -> D6.consCR.title = "車両"; | B31: D6.consCR.title = | C31: 車両 | D31: vehicle
A32: =CLEAN(B32&IF(C32="","",""""&C32&""";")) -> D6.consCR.addable = "車両"; | B32: D6.consCR.addable = | C32: 車両 | D32: vehicle
A33: =CLEAN(B33&IF(C33="","",""""&C33&""";")) -> D6.consCR.countCall = "台目"; | B33: D6.consCR.countCall = | C33: 台目 | D33: car #
A34: =CLEAN(B34&IF(C34="","",""""&C34&""";")) -> D6.consCR.inputGuide = "保有する車ごとの性能・使い方について"; | B34: D6.consCR.inputGuide = | C34: 保有する車ごとの性能・使い方について | D34: on the performance and use of each car will be held
A35: =CLEAN(B35&IF(C35="","",""""&C35&""";"))
A36: =CLEAN(B36&IF(C36="","",""""&C36&""";")) -> D6.consCRsum.title = "車"; | B36: D6.consCRsum.title = | C36: 車 | D36: vehicle
A37: =CLEAN(B37&IF(C37="","",""""&C37&""";")) -> D6.consCRsum.inputGuide = "車・バイクの使い方について"; | B37: D6.consCRsum.inputGuide = | C37: 車・バイクの使い方について | D37: How to use cars, bicycles
A38: =CLEAN(B38&IF(C38="","",""""&C38&""";"))
A39: =CLEAN(B39&IF(C39="","",""""&C39&""";")) -> D6.consCRtrip.title = "移動"; | B39: D6.consCRtrip.title = | C39: 移動 | D39: movement
A40: =CLEAN(B40&IF(C40="","",""""&C40&""";")) -> D6.consCRtrip.countCall = "ヶ所目"; | B40: D6.consCRtrip.countCall = | C40: ヶ所目 | D40: destination #
A41: =CLEAN(B41&IF(C41="","",""""&C41&""";")) -> D6.consCRtrip.addable = "移動先"; | B41: D6.consCRtrip.addable = | C41: 移動先 | D41: destination
A42: =CLEAN(B42&IF(C42="","",""""&C42&""";")) -> D6.consCRtrip.inputGuide = "移動先ごとの車等の使い方について"; | B42: D6.consCRtrip.inputGuide = | C42: 移動先ごとの車等の使い方について | D42: how to use cars and other destinations
A43: =CLEAN(B43&IF(C43="","",""""&C43&""";"))
A44: =CLEAN(B44&IF(C44="","",""""&C44&""";")) -> D6.consDRsum.title = "掃除洗濯"; | B44: D6.consDRsum.title = | C44: 掃除洗濯 | D44: laundry washing
A45: =CLEAN(B45&IF(C45="","",""""&C45&""";")) -> D6.consDRsum.inputGuide = "掃除機、洗濯機や衣類乾燥機の使い方について"; | B45: D6.consDRsum.inputGuide = | C45: 掃除機、洗濯機や衣類乾燥機の使い方について | D45: Clean the vacuum cleaner, how to use the washing machine and clothes dryer
A46: =CLEAN(B46&IF(C46="","",""""&C46&""";"))
A47: =CLEAN(B47&IF(C47="","",""""&C47&""";")) -> D6.consEnergy.title = "全般エネルギー設定"; | B47: D6.consEnergy.title = | C47: 全般エネルギー設定 | D47: General Energy Set
A48: =CLEAN(B48&IF(C48="","",""""&C48&""";")) -> D6.consEnergy.inputGuide = "家全体でのエネルギーの使い方や、1ヶ月あたりの光熱費について"; | B48: D6.consEnergy.inputGuide = | C48: 家全体でのエネルギーの使い方や、1ヶ月あたりの光熱費について | D48: the use of the whole house and the energy, monthly electricity bills
A49: =CLEAN(B49&IF(C49="","",""""&C49&""";"))
A50: =CLEAN(B50&IF(C50="","",""""&C50&""";")) -> D6.consHTcold.title = "寒冷地"; | B50: D6.consHTcold.title = | C50: 寒冷地 | D50: In the cold climate
A51: =CLEAN(B51&IF(C51="","",""""&C51&""";")) -> D6.consHTcold.inputGuide = "寒冷地での暖房の使い方について"; | B51: D6.consHTcold.inputGuide = | C51: 寒冷地での暖房の使い方について | D51: How to use heating in cold weather
A52: =CLEAN(B52&IF(C52="","",""""&C52&""";"))
A53: =CLEAN(B53&IF(C53="","",""""&C53&""";")) -> D6.consHTsum.title = "暖房"; | B53: D6.consHTsum.title = | C53: 暖房 | D53: heating
A54: =CLEAN(B54&IF(C54="","",""""&C54&""";")) -> D6.consHTsum.inputGuide = "家全体での暖房の使い方について"; | B54: D6.consHTsum.inputGuide = | C54: 家全体での暖房の使い方について | D54: how to use the whole house heating
A55: =CLEAN(B55&IF(C55="","",""""&C55&""";"))
A56: =CLEAN(B56&IF(C56="","",""""&C56&""";")) -> D6.consHWdishwash.title = "食器洗い"; | B56: D6.consHWdishwash.title = | C56: 食器洗い | D56: Wash
A57: =CLEAN(B57&IF(C57="","",""""&C57&""";")) -> D6.consHWdishwash.inputGuide = "食器洗いの使い方について"; | B57: D6.consHWdishwash.inputGuide = | C57: 食器洗いの使い方について | D57: How to use the dishwasher
A58: =CLEAN(B58&IF(C58="","",""""&C58&""";"))
A59: =CLEAN(B59&IF(C59="","",""""&C59&""";")) -> D6.consHWdresser.title = "洗面"; | B59: D6.consHWdresser.title = | C59: 洗面 | D59: wash
A60: =CLEAN(B60&IF(C60="","",""""&C60&""";")) -> D6.consHWdresser.inputGuide = "洗面でのお湯の使い方について"; | B60: D6.consHWdresser.inputGuide = | C60: 洗面でのお湯の使い方について | D60: How to wash hot water in the basin
A61: =CLEAN(B61&IF(C61="","",""""&C61&""";"))
A62: =CLEAN(B62&IF(C62="","",""""&C62&""";")) -> D6.consHWshower.title = "シャワー"; | B62: D6.consHWshower.title = | C62: シャワー | D62: shower
A63: =CLEAN(B63&IF(C63="","",""""&C63&""";")) -> D6.consHWshower.inputGuide = "シャワーの使い方について"; | B63: D6.consHWshower.inputGuide = | C63: シャワーの使い方について | D63: how to use shower
A64: =CLEAN(B64&IF(C64="","",""""&C64&""";"))
A65: =CLEAN(B65&IF(C65="","",""""&C65&""";")) -> D6.consHWsum.title = "給湯"; | B65: D6.consHWsum.title = | C65: 給湯 | D65: hot water supply
A66: =CLEAN(B66&IF(C66="","",""""&C66&""";")) -> D6.consHWsum.inputGuide = "給湯全般の使い方について"; | B66: D6.consHWsum.inputGuide = | C66: 給湯全般の使い方について | D66: how to use hot water supply in general
A67: =CLEAN(B67&IF(C67="","",""""&C67&""";"))
A68: =CLEAN(B68&IF(C68="","",""""&C68&""";")) -> D6.consHWtoilet.title = "トイレ"; | B68: D6.consHWtoilet.title = | C68: トイレ | D68: toilet
A69: =CLEAN(B69&IF(C69="","",""""&C69&""";")) -> D6.consHWtoilet.inputGuide = "トイレの水や保温の使い方について"; | B69: D6.consHWtoilet.inputGuide = | C69: トイレの水や保温の使い方について | D69: How to use toilet water and heat insulation
A70: =CLEAN(B70&IF(C70="","",""""&C70&""";"))
A71: =CLEAN(B71&IF(C71="","",""""&C71&""";")) -> D6.consHWtub.title = "浴槽"; | B71: D6.consHWtub.title = | C71: 浴槽 | D71: Bath
A72: =CLEAN(B72&IF(C72="","",""""&C72&""";")) -> D6.consHWtub.inputGuide = "浴槽のお湯の使い方について"; | B72: D6.consHWtub.inputGuide = | C72: 浴槽のお湯の使い方について | D72: how to use hot tub
A73: =CLEAN(B73&IF(C73="","",""""&C73&""";"))
A74: =CLEAN(B74&IF(C74="","",""""&C74&""";")) -> D6.consLI.title = "照明"; | B74: D6.consLI.title = | C74: 照明 | D74: light
A75: =CLEAN(B75&IF(C75="","",""""&C75&""";")) -> D6.consLI.addable = "照明する部屋"; | B75: D6.consLI.addable = | C75: 照明する部屋 | D75: room lighting
A76: =CLEAN(B76&IF(C76="","",""""&C76&""";")) -> D6.consLI.countCall = "部屋目"; | B76: D6.consLI.countCall = | C76: 部屋目 | D76: room #
A77: =CLEAN(B77&IF(C77="","",""""&C77&""";")) -> D6.consLI.inputGuide = "個別部屋の照明の使い方について"; | B77: D6.consLI.inputGuide = | C77: 個別部屋の照明の使い方について | D77: how to use a single room lighting
A78: =CLEAN(B78&IF(C78="","",""""&C78&""";"))
A79: =CLEAN(B79&IF(C79="","",""""&C79&""";")) -> D6.consLIsum.title = "照明"; | B79: D6.consLIsum.title = | C79: 照明 | D79: light
A80: =CLEAN(B80&IF(C80="","",""""&C80&""";")) -> D6.consLIsum.inputGuide = "家全体での照明の使い方について"; | B80: D6.consLIsum.inputGuide = | C80: 家全体での照明の使い方について | D80: how to use the whole house lighting
A81: =CLEAN(B81&IF(C81="","",""""&C81&""";"))
A82: =CLEAN(B82&IF(C82="","",""""&C82&""";")) -> D6.consRF.title = "冷蔵庫"; | B82: D6.consRF.title = | C82: 冷蔵庫 | D82: refrigerator
A83: =CLEAN(B83&IF(C83="","",""""&C83&""";")) -> D6.consRF.addable = "冷蔵庫"; | B83: D6.consRF.addable = | C83: 冷蔵庫 | D83: refrigerator
A84: =CLEAN(B84&IF(C84="","",""""&C84&""";")) -> D6.consRF.countCall = "台目"; | B84: D6.consRF.countCall = | C84: 台目 | D84: #
A85: =CLEAN(B85&IF(C85="","",""""&C85&""";")) -> D6.consRF.inputGuide = "個別の冷蔵庫の使い方について"; | B85: D6.consRF.inputGuide = | C85: 個別の冷蔵庫の使い方について | D85: How to use personal refrigerator
A86: =CLEAN(B86&IF(C86="","",""""&C86&""";"))
A87: =CLEAN(B87&IF(C87="","",""""&C87&""";")) -> D6.consRFsum.title = "冷蔵庫"; | B87: D6.consRFsum.title = | C87: 冷蔵庫 | D87: refrigerator
A88: =CLEAN(B88&IF(C88="","",""""&C88&""";")) -> D6.consRFsum.inputGuide = "家全体での冷蔵庫の使い方について"; | B88: D6.consRFsum.inputGuide = | C88: 家全体での冷蔵庫の使い方について | D88: use the refrigerator in the whole house
A89: =CLEAN(B89&IF(C89="","",""""&C89&""";"))
A90: =CLEAN(B90&IF(C90="","",""""&C90&""";")) -> D6.consSeason.inputGuide = "季節ごとの1ヶ月あたりの光熱費について。おおよその値でご記入ください。"; | B90: D6.consSeason.inputGuide = | C90: 季節ごとの1ヶ月あたりの光熱費について。おおよその値でご記入ください。 | D90: For monthly water and electricity charges per season. Please fill in the approximate value.
A91: =CLEAN(B91&IF(C91="","",""""&C91&""";"))
A92: =CLEAN(B92&IF(C92="","",""""&C92&""";")) -> D6.consTotal.title = "全体"; | B92: D6.consTotal.title = | C92: 全体 | D92: whole
A93: =CLEAN(B93&IF(C93="","",""""&C93&""";")) -> D6.consTotal.inputGuide = "地域や家の基本情報について"; | B93: D6.consTotal.inputGuide = | C93: 地域や家の基本情報について | D93: Basic information about the area and house
A94: =CLEAN(B94&IF(C94="","",""""&C94&""";"))
A95: =CLEAN(B95&IF(C95="","",""""&C95&""";")) -> D6.consTV.title = "テレビ"; | B95: D6.consTV.title = | C95: テレビ | D95: TV
A96: =CLEAN(B96&IF(C96="","",""""&C96&""";")) -> D6.consTV.addable = "テレビ"; | B96: D6.consTV.addable = | C96: テレビ | D96: TV
A97: =CLEAN(B97&IF(C97="","",""""&C97&""";")) -> D6.consTV.countCall = "台目"; | B97: D6.consTV.countCall = | C97: 台目 | D97: #
A98: =CLEAN(B98&IF(C98="","",""""&C98&""";")) -> D6.consTV.inputGuide = "個別のテレビの使い方について"; | B98: D6.consTV.inputGuide = | C98: 個別のテレビの使い方について | D98: How to use personalized TV
A99: =CLEAN(B99&IF(C99="","",""""&C99&""";"))
A100: =CLEAN(B100&IF(C100="","",""""&C100&""";")) -> D6.consTVsum.title = "テレビ"; | B100: D6.consTVsum.title = | C100: テレビ | D100: TV
...

Sheet Measures
A1: measures definition | D1: Fill cells of this color | X1: for program source code | AD1: 5
B2: mid | C2: name | D2: title | F2: refCons | G2: titleShort | I2: easyness | K2: level | L2: figNum | M2: lifeTime | N2: price | O2: roanShow | P2: standardType | Q2: subsidy | S2: advice | U2: lifestyle | V2: season | AB2: program code in php( not use) | AD2: joyfull
B3: measure ID | C3: code | D3: measure titile(if you want not to show start with # ) | E3: reference(not used) | F3: target consumption | G3: short title | H3: reference | I3: easyness（5easy,1difficult,-1:not show) | J3: refernce | K3: Level(0:always,5:detail only) | L3: picture ID | M3: lifetime(year) | N3: price | O3: use loan | P3: compare to standard type | Q3: subsidy | R3: reference | S3: advice message | T3: reference | U3: lifestylle | V3: season(winter,spring,summer) | Z3: program code in senarioset.js | AB3: $defMeasures = []; | AD3: joyfull advice
B4: 1 | C4: mTOsolar | D4: 太陽光発電を設置する | E4: 太陽光発電を設置する | F4: consTotal | G4: 太陽光発電 | H4: 太陽光発電 | I4: 0.5 | J4: 0.5 | L4: 25 | M4: 20 | N4: 350000 | S4: 発電で余った電気は、FIT制度により電力会社に買い取ってもらうことができ、2025年10月以降に設置した場合は最初の4年間が1kWhあたり24円、5年目から10年目までが8.3円で買取がされます。パネルを設置するだけで発電がされ、モーターなど稼働する部分がないために寿命が長く、維持管理も比較的少なくて済みます。交流に変換をする「コンディショナー」と呼ばれる装置は10年程度ごとに交換が必要になります。<br> また、太陽光発電装置を導入すると、電気を売る様子が表示される装置が設置されます。電気をどれだけ発電できたのか、家庭でどれだけ消費したのかが表示され、機種によっては時間帯別に表示されるものもあります。販売できた金額も表示され、より多く販売するために自然と電気の使用量が減る効果も出てきます。 | T4: 発電で余った電気は、FIT制度により電力会社に買い取ってもらうことができ、2020年度は1kWhあたり21円になります。パネルを設置するだけで発電がされ、モーターなど稼働する部分がないために寿命が長く、維持管理も比較的少なくて済みます。交流に変換をする「コンディショナー」と呼ばれる装置は10年程度ごとに交換が必要になります。<br> また、太陽光発電装置を導入すると、電気を売る様子が表示される装置が設置されます。電気をどれだけ発電できたのか、家庭でどれだけ消費したのかが表示され、機種によっては時間帯別に表示されるものもあります。販売できた金額も表示され、より多く販売するために自然と電気の使用量が減る効果も出てきます。 | V4: wss | Z4: ="D6.scenario.defMeasures['"&C4&"'] = { "&B$2&":"""&B4&""", "&C$2&":"""&C4&""", "&D$2&":"""&CLEAN(SUBSTITUTE(D4,"""","'"))&""", "&I$2&":"""&I4&""", "&F$2&":"""&F4&""", "&G$2&":"""&CLEAN(SUBSTITUTE(G4,"""","'"))&""", "&K$2&":"""&K4&""", "&L$2&":"""&L4&""", "&M$2&":"""&M4&""", "&N$2&":"""&N4&""", "&O$2&":"""&O4&""", "&P$2&":"""&P4&""", "&Q$2&":"""&Q4&""", "&S$2&":"""&CLEAN(SUBSTITUTE(S4,"""","'"))&""", "&U$2&":"""&U4&""", "&V$2&":"""&V4&"""};" -> D6.scenario.defMeasures['mTOsolar'] = { mid:"1", name:"mTOsolar", title:"太陽光発電を設置する", easyness:"0.5", refCons:"consTotal", titleShort:"太陽光発電", level:"", figNum:"25", lifeTime:"20", price:"350000", roanShow:"", standardType:"", subsidy :"", advice:"発電で余った電気は、FIT制度により電力会社に買い取ってもらうことができ、2025年10月以降に設置した場合は最初の4年間が1kWhあたり24円、5年目から10年目までが8.3円で買取がされます。パネルを設置するだけで発電がされ、モーターなど稼働する部分がないために寿命が長く、維持管理も比較的少なくて済みます。交流に変換をする「コンディショナー」と呼ばれる装置は10年程度ごとに交換が必要になります。<br> また、太陽光発電装置を導入すると、電気を売る様子が表示される装置が設置されます。電気をどれだけ発電できたのか、家庭でどれだけ消費したのかが表示され、機種によっては時間帯別に表示されるものもあります。販売できた金額も表示され、より多く販売するために自然と電気の使用量が減る効果も出てきます。", lifestyle:"", season:"wss"}; | AB4: ="$defMeasures['"&C4&"'] = [ '"&B$2&"'=>"""&B4&""", '"&D$2&"'=>"""&CLEAN(SUBSTITUTE(D4,"""","'"))&""", '"&L$2&"'=>"""&L4&""", '"&S$2&"'=>"""&CLEAN(SUBSTITUTE(S4,"""","'"))&"""];" -> $defMeasures['mTOsolar'] = [ 'mid'=>"1", 'title'=>"太陽光発電を設置する", 'figNum'=>"25", 'advice'=>"発電で余った電気は、FIT制度により電力会社に買い取ってもらうことができ、2025年10月以降に設置した場合は最初の4年間が1kWhあたり24円、5年目から10年目までが8.3円で買取がされます。パネルを設置するだけで発電がされ、モーターなど稼働する部分がないために寿命が長く、維持管理も比較的少なくて済みます。交流に変換をする「コンディショナー」と呼ばれる装置は10年程度ごとに交換が必要になります。<br> また、太陽光発電装置を導入すると、電気を売る様子が表示される装置が設置されます。電気をどれだけ発電できたのか、家庭でどれだけ消費したのかが表示され、機種によっては時間帯別に表示されるものもあります。販売できた金額も表示され、より多く販売するために自然と電気の使用量が減る効果も出てきます。"]; | AD4: いくら省エネしても、エネルギーを使わずに生活できるわけはなく、省エネを進めるほど苦しくなるものです。そんな中、自分で「発電する」ことができれば、いともかんたんにゼロが達成できます。いままで電気代を払っていたものが、電気を生産して売れるというのも楽しいですし、それでいて環境にいいことができているわけです。貯金をするよりも利子がつく計算となり、太陽がふりそそぐ屋根をもっていたら、これを逃す手はありません。
B5: 2 | C5: mTOhems | D5: HEMS装置を設置する | E5: HEMS装置を設置する | F5: consTotal | G5: HEMS装置 | H5: HEMS装置 | I5: 1 | J5: 1 | L5: 3 | M5: 20 | N5: 200000 | S5: HEMS(Home Energy Management Sysytem：ヘムス)とは、家庭で使っている電気を時間ごとに細かく把握したり、エアコンなどの家電製品を、省エネのために自動制御したりできるシステムです。電気の使い方などの特徴をチェックすると、どんなことをすれば省エネにつながるか、ポイントが見えてきます。表示されるグラフをもとに、いつ電気の消費が多いのか、何が原因なのか、考えてみてください。 | T5: HEMS(Home Energy Management Sysytem)とは、家庭で使っている電気を時間ごとに細かく把握したり、エアコンなどの家電製品を、省エネのために自動制御したりできるシステムです。電気の使い方などの特徴をチェックすると、どんなことをすれば省エネにつながるか、ポイントが見えてきます。表示されるグラフをもとに、いつ電気の消費が多いのか、何が原因なのか、考えてみてください。 | V5: wss | Z5: ="D6.scenario.defMeasures['"&C5&"'] = { "&B$2&":"""&B5&""", "&C$2&":"""&C5&""", "&D$2&":"""&CLEAN(SUBSTITUTE(D5,"""","'"))&""", "&I$2&":"""&I5&""", "&F$2&":"""&F5&""", "&G$2&":"""&CLEAN(SUBSTITUTE(G5,"""","'"))&""", "&K$2&":"""&K5&""", "&L$2&":"""&L5&""", "&M$2&":"""&M5&""", "&N$2&":"""&N5&""", "&O$2&":"""&O5&""", "&P$2&":"""&P5&""", "&Q$2&":"""&Q5&""", "&S$2&":"""&CLEAN(SUBSTITUTE(S5,"""","'"))&""", "&U$2&":"""&U5&""", "&V$2&":"""&V5&"""};" -> D6.scenario.defMeasures['mTOhems'] = { mid:"2", name:"mTOhems", title:"HEMS装置を設置する", easyness:"1", refCons:"consTotal", titleShort:"HEMS装置", level:"", figNum:"3", lifeTime:"20", price:"200000", roanShow:"", standardType:"", subsidy :"", advice:"HEMS(Home Energy Management Sysytem：ヘムス)とは、家庭で使っている電気を時間ごとに細かく把握したり、エアコンなどの家電製品を、省エネのために自動制御したりできるシステムです。電気の使い方などの特徴をチェックすると、どんなことをすれば省エネにつながるか、ポイントが見えてきます。表示されるグラフをもとに、いつ電気の消費が多いのか、何が原因なのか、考えてみてください。", lifestyle:"", season:"wss"}; | AB5: ="$defMeasures['"&C5&"'] = [ '"&B$2&"'=>"""&B5&""", '"&D$2&"'=>"""&CLEAN(SUBSTITUTE(D5,"""","'"))&""", '"&L$2&"'=>"""&L5&""", '"&S$2&"'=>"""&CLEAN(SUBSTITUTE(S5,"""","'"))&"""];" -> $defMeasures['mTOhems'] = [ 'mid'=>"2", 'title'=>"HEMS装置を設置する", 'figNum'=>"3", 'advice'=>"HEMS(Home Energy Management Sysytem：ヘムス)とは、家庭で使っている電気を時間ごとに細かく把握したり、エアコンなどの家電製品を、省エネのために自動制御したりできるシステムです。電気の使い方などの特徴をチェックすると、どんなことをすれば省エネにつながるか、ポイントが見えてきます。表示されるグラフをもとに、いつ電気の消費が多いのか、何が原因なのか、考えてみてください。"]; | AD5: 家庭の消費状況を見えるだけではなく、家電製品を操作することができるのは大きなポイントです。つけっぱなしだったところを、消しに行くのは面倒ですが、設定によっては自動的に消してくれます。賢い召使がいるような感じでしょうか。
B6: 3 | C6: mTOsolarSmall | D6: ベランダに太陽光パネルを置く | E6: ベランダに太陽光パネルを置く | F6: consTotal | G6: ベランダ太陽光 | H6: ベランダ太陽光 | I6: 2 | J6: 2 | L6: 25 | M6: 10 | N6: 50000 | S6: 太陽光発電パネルを屋根に設置するのではなく、小型のものをベランダなどに置くことで、一部の照明などの用途に使うことができます。既成品として販売されていることもありますが、自分で部品を購入して作ることもできます。太陽光パネル（20～200W）、充放電コントローラー、車用バッテリー、インバーターを組み合わせることで動作し、インターネット通販やホームセンターなどで調達できます。<br> 晴れた日にはふとんを干すような感覚で、日光にあててバッテリーを充電させ、充電された分で活用することができます。曇りの日などは、電気を使うことができない場合があります。 | T6: 太陽光といっても屋根に設置するのではなく、持ち運びできる小型のパネルをベランダなどに置くもので、照明などちょっとした用途に使うことができます。既成品として販売されていることもありますが、自分で作ることもでき、材料は、インターネット通販とホームセンターで調達できます。<br> 晴れた日にはふとんを干すような感覚で、日光にあててバッテリーを充電させ、充電された分で活用することができます。曇りの日などは、電気を使うことができない場合があります。 | V6: wss | Z6: ="D6.scenario.defMeasures['"&C6&"'] = { "&B$2&":"""&B6&""", "&C$2&":"""&C6&""", "&D$2&":"""&CLEAN(SUBSTITUTE(D6,"""","'"))&""", "&I$2&":"""&I6&""", "&F$2&":"""&F6&""", "&G$2&":"""&CLEAN(SUBSTITUTE(G6,"""","'"))&""", "&K$2&":"""&K6&""", "&L$2&":"""&L6&""", "&M$2&":"""&M6&""", "&N$2&":"""&N6&""", "&O$2&":"""&O6&""", "&P$2&":"""&P6&""", "&Q$2&":"""&Q6&""", "&S$2&":"""&CLEAN(SUBSTITUTE(S6,"""","'"))&""", "&U$2&":"""&U6&""", "&V$2&":"""&V6&"""};" -> D6.scenario.defMeasures['mTOsolarSmall'] = { mid:"3", name:"mTOsolarSmall", title:"ベランダに太陽光パネルを置く", easyness:"2", refCons:"consTotal", titleShort:"ベランダ太陽光", level:"", figNum:"25", lifeTime:"10", price:"50000", roanShow:"", standardType:"", subsidy :"", advice:"太陽光発電パネルを屋根に設置するのではなく、小型のものをベランダなどに置くことで、一部の照明などの用途に使うことができます。既成品として販売されていることもありますが、自分で部品を購入して作ることもできます。太陽光パネル（20～200W）、充放電コントローラー、車用バッテリー、インバーターを組み合わせることで動作し、インターネット通販やホームセンターなどで調達できます。<br> 晴れた日にはふとんを干すような感覚で、日光にあててバッテリーを充電させ、充電された分で活用することができます。曇りの日などは、電気を使うことができない場合があります。", lifestyle:"", season:"wss"}; | AB6: ="$defMeasures['"&C6&"'] = [ '"&B$2&"'=>"""&B6&""", '"&D$2&"'=>"""&CLEAN(SUBSTITUTE(D6,"""","'"))&""", '"&L$2&"'=>"""&L6&""", '"&S$2&"'=>"""&CLEAN(SUBSTITUTE(S6,"""","'"))&"""];" -> $defMeasures['mTOsolarSmall'] = [ 'mid'=>"3", 'title'=>"ベランダに太陽光パネルを置く", 'figNum'=>"25", 'advice'=>"太陽光発電パネルを屋根に設置するのではなく、小型のものをベランダなどに置くことで、一部の照明などの用途に使うことができます。既成品として販売されていることもありますが、自分で部品を購入して作ることもできます。太陽光パネル（20～200W）、充放電コントローラー、車用バッテリー、インバーターを組み合わせることで動作し、インターネット通販やホームセンターなどで調達できます。<br> 晴れた日にはふとんを干すような感覚で、日光にあててバッテリーを充電させ、充電された分で活用することができます。曇りの日などは、電気を使うことができない場合があります。"]; | AD6: なんといっても、自分で発電を組み立てることができるのは楽しみです。大型の家電製品は消費電力が大きいので動きませんが、ちょっとした照明くらいなら利用可能です。晴れた日の太陽の恵みをすぐに実感
B7: 6 | C7: mTOzeh | D7: ZEHに建て替える | E7: ZEHに建て替える | F7: consTotal | G7: ZEH | H7: ZEH | I7: 0.5 | J7: 0.5 | L7: 25 | M7: 30 | N7: 22000000 | P7: 省エネ基準住宅 | S7: 断熱性能を高めて省エネ機器設備を導入した上で、太陽光発電を設置すると、家庭のエネルギー消費を実質まかなうことができます。ネット・ゼロ・エネルギー・ハウス（ZEH：ゼッチ）と呼ばれ、すでに大手ハウスメーカーでは新築の標準になっており、2030年頃にはすべての新築住宅でこのレベルを達成することが求められます。エネルギー面でメリットがあるだけでなく、冬は暖かく、夏は涼しく、快適に過ごすことができ、健康面でもメリットがあることがわかっています。 | T7: 発電で余った電気は、FIT制度により電力会社に買い取ってもらうことができ、2020年度は1kWhあたり21円になります。パネルを設置するだけで発電がされ、モーターなど稼働する部分がないために寿命が長く、維持管理も比較的少なくて済みます。交流に変換をする「コンディショナー」と呼ばれる装置は10年程度ごとに交換が必要になります。<br> また、太陽光発電装置を導入すると、電気を売る様子が表示される装置が設置されます。電気をどれだけ発電できたのか、家庭でどれだけ消費したのかが表示され、機種によっては時間帯別に表示されるものもあります。販売できた金額も表示され、より多く販売するために自然と電気の使用量が減る効果も出てきます。 | V7: wss | Z7: ="D6.scenario.defMeasures['"&C7&"'] = { "&B$2&":"""&B7&""", "&C$2&":"""&C7&""", "&D$2&":"""&CLEAN(SUBSTITUTE(D7,"""","'"))&""", "&I$2&":"""&I7&""", "&F$2&":"""&F7&""", "&G$2&":"""&CLEAN(SUBSTITUTE(G7,"""","'"))&""", "&K$2&":"""&K7&""", "&L$2&":"""&L7&""", "&M$2&":"""&M7&""", "&N$2&":"""&N7&""", "&O$2&":"""&O7&""", "&P$2&":"""&P7&""", "&Q$2&":"""&Q7&""", "&S$2&":"""&CLEAN(SUBSTITUTE(S7,"""","'"))&""", "&U$2&":"""&U7&""", "&V$2&":"""&V7&"""};" -> D6.scenario.defMeasures['mTOzeh'] = { mid:"6", name:"mTOzeh", title:"ZEHに建て替える", easyness:"0.5", refCons:"consTotal", titleShort:"ZEH", level:"", figNum:"25", lifeTime:"30", price:"22000000", roanShow:"", standardType:"省エネ基準住宅", subsidy :"", advice:"断熱性能を高めて省エネ機器設備を導入した上で、太陽光発電を設置すると、家庭のエネルギー消費を実質まかなうことができます。ネット・ゼロ・エネルギー・ハウス（ZEH：ゼッチ）と呼ばれ、すでに大手ハウスメーカーでは新築の標準になっており、2030年頃にはすべての新築住宅でこのレベルを達成することが求められます。エネルギー面でメリットがあるだけでなく、冬は暖かく、夏は涼しく、快適に過ごすことができ、健康面でもメリットがあることがわかっています。", lifestyle:"", season:"wss"}; | AB7: ="$defMeasures['"&C7&"'] = [ '"&B$2&"'=>"""&B7&""", '"&D$2&"'=>"""&CLEAN(SUBSTITUTE(D7,"""","'"))&""", '"&L$2&"'=>"""&L7&""", '"&S$2&"'=>"""&CLEAN(SUBSTITUTE(S7,"""","'"))&"""];" -> $defMeasures['mTOzeh'] = [ 'mid'=>"6", 'title'=>"ZEHに建て替える", 'figNum'=>"25", 'advice'=>"断熱性能を高めて省エネ機器設備を導入した上で、太陽光発電を設置すると、家庭のエネルギー消費を実質まかなうことができます。ネット・ゼロ・エネルギー・ハウス（ZEH：ゼッチ）と呼ばれ、すでに大手ハウスメーカーでは新築の標準になっており、2030年頃にはすべての新築住宅でこのレベルを達成することが求められます。エネルギー面でメリットがあるだけでなく、冬は暖かく、夏は涼しく、快適に過ごすことができ、健康面でもメリットがあることがわかっています。"]; | AD7: いくら省エネしても、エネルギーを使わずに生活できるわけはなく、省エネを進めるほど苦しくなるものです。そんな中、自分で「発電する」ことができれば、いともかんたんにゼロが達成できます。いままで電気代を払っていたものが、電気を生産して売れるというのも楽しいですし、それでいて環境にいいことができているわけです。貯金をするよりも利子がつく計算となり、太陽がふりそそぐ屋根をもっていたら、これを逃す手はありません。
B8: 7 | C8: mTObattery | D8: 家庭用蓄電池を設置する | F8: consTotal | G8: 家庭用蓄電池 | I8: 0.5 | J8: 2 | L8: 25 | M8: 10 | N8: 1000000 | S8: 太陽光発電装置で発電がされた電気のうち、使い切れない分を蓄電しておくことで、家庭の電気をより多くまかなうことができます。蓄電池がなくても余った電気を売電することができますが、通常は購入する電気代のほうが高く、その分お得になります。また非常時には蓄電された電気を使って、家電製品を動かすこともにも活用できます。 | V8: wss | Z8: ="D6.scenario.defMeasures['"&C8&"'] = { "&B$2&":"""&B8&""", "&C$2&":"""&C8&""", "&D$2&":"""&CLEAN(SUBSTITUTE(D8,"""","'"))&""", "&I$2&":"""&I8&""", "&F$2&":"""&F8&""", "&G$2&":"""&CLEAN(SUBSTITUTE(G8,"""","'"))&""", "&K$2&":"""&K8&""", "&L$2&":"""&L8&""", "&M$2&":"""&M8&""", "&N$2&":"""&N8&""", "&O$2&":"""&O8&""", "&P$2&":"""&P8&""", "&Q$2&":"""&Q8&""", "&S$2&":"""&CLEAN(SUBSTITUTE(S8,"""","'"))&""", "&U$2&":"""&U8&""", "&V$2&":"""&V8&"""};" -> D6.scenario.defMeasures['mTObattery'] = { mid:"7", name:"mTObattery", title:"家庭用蓄電池を設置する", easyness:"0.5", refCons:"consTotal", titleShort:"家庭用蓄電池", level:"", figNum:"25", lifeTime:"10", price:"1000000", roanShow:"", standardType:"", subsidy :"", advice:"太陽光発電装置で発電がされた電気のうち、使い切れない分を蓄電しておくことで、家庭の電気をより多くまかなうことができます。蓄電池がなくても余った電気を売電することができますが、通常は購入する電気代のほうが高く、その分お得になります。また非常時には蓄電された電気を使って、家電製品を動かすこともにも活用できます。", lifestyle:"", season:"wss"}; | AB8: ="$defMeasures['"&C8&"'] = [ '"&B$2&"'=>"""&B8&""", '"&D$2&"'=>"""&CLEAN(SUBSTITUTE(D8,"""","'"))&""", '"&L$2&"'=>"""&L8&""", '"&S$2&"'=>"""&CLEAN(SUBSTITUTE(S8,"""","'"))&"""];" -> $defMeasures['mTObattery'] = [ 'mid'=>"7", 'title'=>"家庭用蓄電池を設置する", 'figNum'=>"25", 'advice'=>"太陽光発電装置で発電がされた電気のうち、使い切れない分を蓄電しておくことで、家庭の電気をより多くまかなうことができます。蓄電池がなくても余った電気を売電することができますが、通常は購入する電気代のほうが高く、その分お得になります。また非常時には蓄電された電気を使って、家電製品を動かすこともにも活用できます。"]; | AD8: いくら省エネしても、エネルギーを使わずに生活できるわけはなく、省エネを進めるほど苦しくなるものです。そんな中、自分で「発電する」ことができれば、いともかんたんにゼロが達成できます。いままで電気代を払っていたものが、電気を生産して売れるというのも楽しいですし、それでいて環境にいいことができているわけです。貯金をするよりも利子がつく計算となり、太陽がふりそそぐ屋根をもっていたら、これを逃す手はありません。
B9: 8 | C9: mTOv2h | D9: 電気自動車を家庭用蓄電池として活用する | F9: consTotal | G9: V2H | I9: 0.5 | J9: 2 | L9: 21 | M9: 6 | N9: 1000000 | S9: 太陽光発電装置で発電がされた電気のうち、使い切れない分を蓄電しておくことで、家庭の電気をより多くまかなうことができます。蓄電池がなくても余った電気を売電することができますが、通常は購入する電気代のほうが高く、その分お得になります。また非常時には蓄電された電気を使って、家電製品を動かすこともにも活用できます。電気自動車の容量は大きく、連携する装置を購入することで家庭用の蓄電池としても活用することができます。 | V9: wss | Z9: ="D6.scenario.defMeasures['"&C9&"'] = { "&B$2&":"""&B9&""", "&C$2&":"""&C9&""", "&D$2&":"""&CLEAN(SUBSTITUTE(D9,"""","'"))&""", "&I$2&":"""&I9&""", "&F$2&":"""&F9&""", "&G$2&":"""&CLEAN(SUBSTITUTE(G9,"""","'"))&""", "&K$2&":"""&K9&""", "&L$2&":"""&L9&""", "&M$2&":"""&M9&""", "&N$2&":"""&N9&""", "&O$2&":"""&O9&""", "&P$2&":"""&P9&""", "&Q$2&":"""&Q9&""", "&S$2&":"""&CLEAN(SUBSTITUTE(S9,"""","'"))&""", "&U$2&":"""&U9&""", "&V$2&":"""&V9&"""};" -> D6.scenario.defMeasures['mTOv2h'] = { mid:"8", name:"mTOv2h", title:"電気自動車を家庭用蓄電池として活用する", easyness:"0.5", refCons:"consTotal", titleShort:"V2H", level:"", figNum:"21", lifeTime:"6", price:"1000000", roanShow:"", standardType:"", subsidy :"", advice:"太陽光発電装置で発電がされた電気のうち、使い切れない分を蓄電しておくことで、家庭の電気をより多くまかなうことができます。蓄電池がなくても余った電気を売電することができますが、通常は購入する電気代のほうが高く、その分お得になります。また非常時には蓄電された電気を使って、家電製品を動かすこともにも活用できます。電気自動車の容量は大きく、連携する装置を購入することで家庭用の蓄電池としても活用することができます。", lifestyle:"", season:"wss"}; | AB9: ="$defMeasures['"&C9&"'] = [ '"&B$2&"'=>"""&B9&""", '"&D$2&"'=>"""&CLEAN(SUBSTITUTE(D9,"""","'"))&""", '"&L$2&"'=>"""&L9&""", '"&S$2&"'=>"""&CLEAN(SUBSTITUTE(S9,"""","'"))&"""];" -> $defMeasures['mTOv2h'] = [ 'mid'=>"8", 'title'=>"電気自動車を家庭用蓄電池として活用する", 'figNum'=>"21", 'advice'=>"太陽光発電装置で発電がされた電気のうち、使い切れない分を蓄電しておくことで、家庭の電気をより多くまかなうことができます。蓄電池がなくても余った電気を売電することができますが、通常は購入する電気代のほうが高く、その分お得になります。また非常時には蓄電された電気を使って、家電製品を動かすこともにも活用できます。電気自動車の容量は大きく、連携する装置を購入することで家庭用の蓄電池としても活用することができます。"]; | AD9: いくら省エネしても、エネルギーを使わずに生活できるわけはなく、省エネを進めるほど苦しくなるものです。そんな中、自分で「発電する」ことができれば、いともかんたんにゼロが達成できます。いままで電気代を払っていたものが、電気を生産して売れるというのも楽しいですし、それでいて環境にいいことができているわけです。貯金をするよりも利子がつく計算となり、太陽がふりそそぐ屋根をもっていたら、これを逃す手はありません。
B10: 10 | C10: mTOzeroelectricity | D10: CO2排出係数が0の電気を選ぶ | F10: consTotal | G10: 脱炭素電力を選ぶ | I10: 2 | L10: 25 | S10: 電力契約をいろいろな会社から選ぶことができます。一般的な電気ではなく、水力や太陽光発電、風力発電など、CO2排出係数がゼロとなる脱炭素電力のメニューも選べるようになっています。電力会社を変えることで、単価が安くなる場合もあります。 | V10: wss | Z10: ="D6.scenario.defMeasures['"&C10&"'] = { "&B$2&":"""&B10&""", "&C$2&":"""&C10&""", "&D$2&":"""&CLEAN(SUBSTITUTE(D10,"""","'"))&""", "&I$2&":"""&I10&""", "&F$2&":"""&F10&""", "&G$2&":"""&CLEAN(SUBSTITUTE(G10,"""","'"))&""", "&K$2&":"""&K10&""", "&L$2&":"""&L10&""", "&M$2&":"""&M10&""", "&N$2&":"""&N10&""", "&O$2&":"""&O10&""", "&P$2&":"""&P10&""", "&Q$2&":"""&Q10&""", "&S$2&":"""&CLEAN(SUBSTITUTE(S10,"""","'"))&""", "&U$2&":"""&U10&""", "&V$2&":"""&V10&"""};" -> D6.scenario.defMeasures['mTOzeroelectricity'] = { mid:"10", name:"mTOzeroelectricity", title:"CO2排出係数が0の電気を選ぶ", easyness:"2", refCons:"consTotal", titleShort:"脱炭素電力を選ぶ", level:"", figNum:"25", lifeTime:"", price:"", roanShow:"", standardType:"", subsidy :"", advice:"電力契約をいろいろな会社から選ぶことができます。一般的な電気ではなく、水力や太陽光発電、風力発電など、CO2排出係数がゼロとなる脱炭素電力のメニューも選べるようになっています。電力会社を変えることで、単価が安くなる場合もあります。", lifestyle:"", season:"wss"}; | AB10: ="$defMeasures['"&C10&"'] = [ '"&B$2&"'=>"""&B10&""", '"&D$2&"'=>"""&CLEAN(SUBSTITUTE(D10,"""","'"))&""", '"&L$2&"'=>"""&L10&""", '"&S$2&"'=>"""&CLEAN(SUBSTITUTE(S10,"""","'"))&"""];" -> $defMeasures['mTOzeroelectricity'] = [ 'mid'=>"10", 'title'=>"CO2排出係数が0の電気を選ぶ", 'figNum'=>"25", 'advice'=>"電力契約をいろいろな会社から選ぶことができます。一般的な電気ではなく、水力や太陽光発電、風力発電など、CO2排出係数がゼロとなる脱炭素電力のメニューも選べるようになっています。電力会社を変えることで、単価が安くなる場合もあります。"]; | AD10: いくら省エネしても、エネルギーを使わずに生活できるわけはなく、省エネを進めるほど苦しくなるものです。そんな中、自分で「発電する」ことができれば、いともかんたんにゼロが達成できます。いままで電気代を払っていたものが、電気を生産して売れるというのも楽しいですし、それでいて環境にいいことができているわけです。貯金をするよりも利子がつく計算となり、太陽がふりそそぐ屋根をもっていたら、これを逃す手はありません。
B11: 101 | C11: mHWecocute | D11: 給湯器をエコキュートに買い換える | E11: 給湯器をエコキュートに買い換える | F11: consHWsum | G11: エコキュート | H11: エコキュート | I11: 2 | J11: 2 | L11: 8 | M11: 10 | N11: 400000 | O11: 1 | P11: 電気温水器 | Q11: 子育てグリーン住宅支援事業の対象で、他の断熱工事や機器導入を行って補助額が5万円以上になると補助されます。 | S11: エコキュート(R)（自然冷媒ヒートポンプ給湯器）は、エアコンの室外機のような装置がついており、外気の熱を利用してお湯を沸かすため、電気温水器より3倍以上効率がよくなります。貯湯槽にためたお湯を使い切るような、家族人数が多く、毎日欠かさずお風呂に入る家庭にはお勧めです。<br> また、ふだんのお湯の使い方を考慮して控えめに沸かす設定をすると、さらに省エネにつながります。 | T11: エコキュート(R)（自然冷媒ヒートポンプ給湯器）は、エアコンの室外機のような装置がついており、外気の熱を利用してお湯を沸かすため、電気温水器より3倍以上効率がよくなります。貯湯槽にためたお湯を使い切るような、家族人数が多く、毎日欠かさずお風呂に入る家庭にはお勧めです。<br> また、ふだんのお湯の使い方を考慮して控えめに沸かす設定をすると、さらに省エネにつながります。 | V11: wss | Z11: ="D6.scenario.defMeasures['"&C11&"'] = { "&B$2&":"""&B11&""", "&C$2&":"""&C11&""", "&D$2&":"""&CLEAN(SUBSTITUTE(D11,"""","'"))&""", "&I$2&":"""&I11&""", "&F$2&":"""&F11&""", "&G$2&":"""&CLEAN(SUBSTITUTE(G11,"""","'"))&""", "&K$2&":"""&K11&""", "&L$2&":"""&L11&""", "&M$2&":"""&M11&""", "&N$2&":"""&N11&""", "&O$2&":"""&O11&""", "&P$2&":"""&P11&""", "&Q$2&":"""&Q11&""", "&S$2&":"""&CLEAN(SUBSTITUTE(S11,"""","'"))&""", "&U$2&":"""&U11&""", "&V$2&":"""&V11&"""};" -> D6.scenario.defMeasures['mHWecocute'] = { mid:"101", name:"mHWecocute", title:"給湯器をエコキュートに買い換える", easyness:"2", refCons:"consHWsum", titleShort:"エコキュート", level:"", figNum:"8", lifeTime:"10", price:"400000", roanShow:"1", standardType:"電気温水器", subsidy :"子育てグリーン住宅支援事業の対象で、他の断熱工事や機器導入を行って補助額が5万円以上になると補助されます。", advice:"エコキュート(R)（自然冷媒ヒートポンプ給湯器）は、エアコンの室外機のような装置がついており、外気の熱を利用してお湯を沸かすため、電気温水器より3倍以上効率がよくなります。貯湯槽にためたお湯を使い切るような、家族人数が多く、毎日欠かさずお風呂に入る家庭にはお勧めです。<br> また、ふだんのお湯の使い方を考慮して控えめに沸かす設定をすると、さらに省エネにつながります。", lifestyle:"", season:"wss"}; | AB11: ="$defMeasures['"&C11&"'] = [ '"&B$2&"'=>"""&B11&""", '"&D$2&"'=>"""&CLEAN(SUBSTITUTE(D11,"""","'"))&""", '"&L$2&"'=>"""&L11&""", '"&S$2&"'=>"""&CLEAN(SUBSTITUTE(S11,"""","'"))&"""];" -> $defMeasures['mHWecocute'] = [ 'mid'=>"101", 'title'=>"給湯器をエコキュートに買い換える", 'figNum'=>"8", 'advice'=>"エコキュート(R)（自然冷媒ヒートポンプ給湯器）は、エアコンの室外機のような装置がついており、外気の熱を利用してお湯を沸かすため、電気温水器より3倍以上効率がよくなります。貯湯槽にためたお湯を使い切るような、家族人数が多く、毎日欠かさずお風呂に入る家庭にはお勧めです。<br> また、ふだんのお湯の使い方を考慮して控えめに沸かす設定をすると、さらに省エネにつながります。"]; | AD11: 外気の熱を使ってお湯をわかすために、電気の消費は大幅に減ります。ただ貯湯槽の大きさが限られているので、大量にお湯を使う家庭や、盆や正月で人数が急に増えた場合には、湯切れを起こすこともあります。湯切れを起こさないようにと、限られたお湯を大切に使うことも、省エネの基本的な視点です。
B12: 102 | C12: mHWecojoze | D12: 給湯器をエコジョーズ（潜熱回収型ガス給湯器）に買い換える | E12: 給湯器をエコジョーズ（潜熱回収型）に買い換える | F12: consHWsum | G12: エコジョーズ | H12: エコジョーズ | I12: 2 | J12: 2 | L12: 10 | M12: 10 | N12: 200000 | P12: 既存型 | Q12: 子育てグリーン住宅支援事業の対象で、他の断熱工事や機器導入を行って補助額が5万円以上になると補助されます。 | S12: エコジョーズ(R)（潜熱回収型）は、水蒸気として逃げていた熱も回収する仕組みのため、既存のガス給湯器に比べて効率が1割以上向上しています。既存のガス給湯器とほぼ同じ形で置き換えが可能です。熱を回収する際に発生する水を流すドレンがついており、マンションなど排水口が近くにない場合には、工事が必要となる場合があります。ガス会社によってはエコジョーズ料金により、ガス代が割り引かれる場合もあります。 | T12: エコジョーズ(R)（潜熱回収型）は、水蒸気として逃げていた熱も回収する仕組みのため、既存のガス給湯器に比べて効率が1割以上向上しています。既存のガス給湯器とほぼ同じ形ですが、熱回収をするために少し大型になっており、また熱を回収する際に発生する水を流すドレンもついています。ガス会社によってはエコジョーズ料金により、ガス代が割り引かれる場合もあります。 | V12: wss | Z12: ="D6.scenario.defMeasures['"&C12&"'] = { "&B$2&":"""&B12&""", "&C$2&":"""&C12&""", "&D$2&":"""&CLEAN(SUBSTITUTE(D12,"""","'"))&""", "&I$2&":"""&I12&""", "&F$2&":"""&F12&""", "&G$2&":"""&CLEAN(SUBSTITUTE(G12,"""","'"))&""", "&K$2&":"""&K12&""", "&L$2&":"""&L12&""", "&M$2&":"""&M12&""", "&N$2&":"""&N12&""", "&O$2&":"""&O12&""", "&P$2&":"""&P12&""", "&Q$2&":"""&Q12&""", "&S$2&":"""&CLEAN(SUBSTITUTE(S12,"""","'"))&""", "&U$2&":"""&U12&""", "&V$2&":"""&V12&"""};" -> D6.scenario.defMeasures['mHWecojoze'] = { mid:"102", name:"mHWecojoze", title:"給湯器をエコジョーズ（潜熱回収型ガス給湯器）に買い換える", easyness:"2", refCons:"consHWsum", titleShort:"エコジョーズ", level:"", figNum:"10", lifeTime:"10", price:"200000", roanShow:"", standardType:"既存型", subsidy :"子育てグリーン住宅支援事業の対象で、他の断熱工事や機器導入を行って補助額が5万円以上になると補助されます。", advice:"エコジョーズ(R)（潜熱回収型）は、水蒸気として逃げていた熱も回収する仕組みのため、既存のガス給湯器に比べて効率が1割以上向上しています。既存のガス給湯器とほぼ同じ形で置き換えが可能です。熱を回収する際に発生する水を流すドレンがついており、マンションなど排水口が近くにない場合には、工事が必要となる場合があります。ガス会社によってはエコジョーズ料金により、ガス代が割り引かれる場合もあります。", lifestyle:"", season:"wss"}; | AB12: ="$defMeasures['"&C12&"'] = [ '"&B$2&"'=>"""&B12&""", '"&D$2&"'=>"""&CLEAN(SUBSTITUTE(D12,"""","'"))&""", '"&L$2&"'=>"""&L12&""", '"&S$2&"'=>"""&CLEAN(SUBSTITUTE(S12,"""","'"))&"""];" -> $defMeasures['mHWecojoze'] = [ 'mid'=>"102", 'title'=>"給湯器をエコジョーズ（潜熱回収型ガス給湯器）に買い換える", 'figNum'=>"10", 'advice'=>"エコジョーズ(R)（潜熱回収型）は、水蒸気として逃げていた熱も回収する仕組みのため、既存のガス給湯器に比べて効率が1割以上向上しています。既存のガス給湯器とほぼ同じ形で置き換えが可能です。熱を回収する際に発生する水を流すドレンがついており、マンションなど排水口が近くにない場合には、工事が必要となる場合があります。ガス会社によってはエコジョーズ料金により、ガス代が割り引かれる場合もあります。"]; | AD12: エコジョーズなど新しい給湯器は、省エネ性能が高いだけでなく、細かい制御ができるように改良されているため、お湯の温度変化も小さく、快適です。ガス代としても、給湯にかかる分が1割程度減りますので、金銭的にもお得になります。
B13: 103 | C13: mHWecofeel | D13: 給湯器をエコフィール（潜熱回収型灯油給湯器）に買い換える | E13: 給湯器をエコフィール（潜熱回収型）に買い換える | F13: consHWsum | G13: エコフィール | H13: エコフィール | I13: 1 | J13: 1 | L13: 10 | M13: 10 | N13: 250000 | P13: 既存型 | Q13: 子育てグリーン住宅支援事業の対象で、他の断熱工事や機器導入を行って補助額が5万円以上になると補助されます。 | S13: エコフィール(R)（潜熱回収型）は、水蒸気として逃げていた熱も回収する仕組みのため、効率が1割以上向上しています。既存の灯油ボイラーとほぼ同じ形で、交換ができます。灯油ではなくガスのタイプは「エコジョース」といいます。 | T13: エコフィール(R)（潜熱回収型）は、水蒸気として逃げていた熱も回収する仕組みのため、効率が1割以上向上しています。既存の灯油ボイラーとほぼ同じ形ですが、熱回収をするために少し大型になっており、また熱を回収する際に発生する水を流すドレンもついています。灯油ではなくガスのタイプは「エコジョース」といいます。 | V13: wss | Z13: ="D6.scenario.defMeasures['"&C13&"'] = { "&B$2&":"""&B13&""", "&C$2&":"""&C13&""", "&D$2&":"""&CLEAN(SUBSTITUTE(D13,"""","'"))&""", "&I$2&":"""&I13&""", "&F$2&":"""&F13&""", "&G$2&":"""&CLEAN(SUBSTITUTE(G13,"""","'"))&""", "&K$2&":"""&K13&""", "&L$2&":"""&L13&""", "&M$2&":"""&M13&""", "&N$2&":"""&N13&""", "&O$2&":"""&O13&""", "&P$2&":"""&P13&""", "&Q$2&":"""&Q13&""", "&S$2&":"""&CLEAN(SUBSTITUTE(S13,"""","'"))&""", "&U$2&":"""&U13&""", "&V$2&":"""&V13&"""};" -> D6.scenario.defMeasures['mHWecofeel'] = { mid:"103", name:"mHWecofeel", title:"給湯器をエコフィール（潜熱回収型灯油給湯器）に買い換える", easyness:"1", refCons:"consHWsum", titleShort:"エコフィール", level:"", figNum:"10", lifeTime:"10", price:"250000", roanShow:"", standardType:"既存型", subsidy :"子育てグリーン住宅支援事業の対象で、他の断熱工事や機器導入を行って補助額が5万円以上になると補助されます。", advice:"エコフィール(R)（潜熱回収型）は、水蒸気として逃げていた熱も回収する仕組みのため、効率が1割以上向上しています。既存の灯油ボイラーとほぼ同じ形で、交換ができます。灯油ではなくガスのタイプは「エコジョース」といいます。", lifestyle:"", season:"wss"}; | AB13: ="$defMeasures['"&C13&"'] = [ '"&B$2&"'=>"""&B13&""", '"&D$2&"'=>"""&CLEAN(SUBSTITUTE(D13,"""","'"))&""", '"&L$2&"'=>"""&L13&""", '"&S$2&"'=>"""&CLEAN(SUBSTITUTE(S13,"""","'"))&"""];" -> $defMeasures['mHWecofeel'] = [ 'mid'=>"103", 'title'=>"給湯器をエコフィール（潜熱回収型灯油給湯器）に買い換える", 'figNum'=>"10", 'advice'=>"エコフィール(R)（潜熱回収型）は、水蒸気として逃げていた熱も回収する仕組みのため、効率が1割以上向上しています。既存の灯油ボイラーとほぼ同じ形で、交換ができます。灯油ではなくガスのタイプは「エコジョース」といいます。"]; | AD13: 灯油を燃料とする高効率給湯としては、エコフィールが唯一です。従来型のボイラーとくらべて、熱のロスを3分の1以下にしています。おおよそ1割減るので、灯油代を比較してみると、成果がみえてくるかもしれません。
B14: 104 | C14: mHWenefarmSOFC | D14: 給湯器をSOFCタイプのエネファーム（燃料電池）に買い換える | E14: 給湯器をエネファーム（燃料電池）に買い換える | F14: consHWsum | G14: エネファームSOFC | H14: エネファーム | I14: 0.5 | J14: 0.5 | K14: 5 | L14: 10 | M14: 10 | N14: 1100000 | O14: 1 | P14: エコジョーズ | S14: エネファーム(R)は、燃料電池で発電をしながらお湯をわかす効率がよい装置です。家庭で消費する電気の分だけ発電を行い、発生した余熱をお湯としてためて利用することができます。電気やお湯をたくさん使う家庭で、大きな省エネ効果が期待できます。SOFCタイプは、さらに発電効率が高くなってり、お湯の発生量が少ないため、比較的お湯を使わない家庭でも効果がでます。発電を行うため、停電時にも一定の電気を取り出すことが可能となっています。 | T14: エネファーム(R)は、燃料電池で発電をしながらお湯をわかす効率がよい装置です。家庭で消費する電気の分だけ発電を行い、発生した余熱をお湯としてためて利用することができます。電気やお湯をたくさん使う家庭で、大きな省エネ効果が期待できます。SOFCタイプは、さらに発電効率が高くなってり、お湯の発生量が少ないため、比較的お湯を使わない家庭でも効果がでます。発電を行うため、停電時にも一定の電気を取り出すことが可能となっています。 | V14: wss | Z14: ="D6.scenario.defMeasures['"&C14&"'] = { "&B$2&":"""&B14&""", "&C$2&":"""&C14&""", "&D$2&":"""&CLEAN(SUBSTITUTE(D14,"""","'"))&""", "&I$2&":"""&I14&""", "&F$2&":"""&F14&""", "&G$2&":"""&CLEAN(SUBSTITUTE(G14,"""","'"))&""", "&K$2&":"""&K14&""", "&L$2&":"""&L14&""", "&M$2&":"""&M14&""", "&N$2&":"""&N14&""", "&O$2&":"""&O14&""", "&P$2&":"""&P14&""", "&Q$2&":"""&Q14&""", "&S$2&":"""&CLEAN(SUBSTITUTE(S14,"""","'"))&""", "&U$2&":"""&U14&""", "&V$2&":"""&V14&"""};" -> D6.scenario.defMeasures['mHWenefarmSOFC'] = { mid:"104", name:"mHWenefarmSOFC", title:"給湯器をSOFCタイプのエネファーム（燃料電池）に買い換える", easyness:"0.5", refCons:"consHWsum", titleShort:"エネファームSOFC", level:"5", figNum:"10", lifeTime:"10", price:"1100000", roanShow:"1", standardType:"エコジョーズ", subsidy :"", advice:"エネファーム(R)は、燃料電池で発電をしながらお湯をわかす効率がよい装置です。家庭で消費する電気の分だけ発電を行い、発生した余熱をお湯としてためて利用することができます。電気やお湯をたくさん使う家庭で、大きな省エネ効果が期待できます。SOFCタイプは、さらに発電効率が高くなってり、お湯の発生量が少ないため、比較的お湯を使わない家庭でも効果がでます。発電を行うため、停電時にも一定の電気を取り出すことが可能となっています。", lifestyle:"", season:"wss"}; | AB14: ="$defMeasures['"&C14&"'] = [ '"&B$2&"'=>"""&B14&""", '"&D$2&"'=>"""&CLEAN(SUBSTITUTE(D14,"""","'"))&""", '"&L$2&"'=>"""&L14&""", '"&S$2&"'=>"""&CLEAN(SUBSTITUTE(S14,"""","'"))&"""];" -> $defMeasures['mHWenefarmSOFC'] = [ 'mid'=>"104", 'title'=>"給湯器をSOFCタイプのエネファーム（燃料電池）に買い換える", 'figNum'=>"10", 'advice'=>"エネファーム(R)は、燃料電池で発電をしながらお湯をわかす効率がよい装置です。家庭で消費する電気の分だけ発電を行い、発生した余熱をお湯としてためて利用することができます。電気やお湯をたくさん使う家庭で、大きな省エネ効果が期待できます。SOFCタイプは、さらに発電効率が高くなってり、お湯の発生量が少ないため、比較的お湯を使わない家庭でも効果がでます。発電を行うため、停電時にも一定の電気を取り出すことが可能となっています。"]; | AD14: 夢の技術とされた燃料電池が、実用的に広まりつつあります。停電時にも、発電して電気を生み出し使えるというのは、大きなメリットです。
B15: 105 | C15: mHWenefarm | D15: 給湯器をエネファーム（燃料電池）に買い換える | E15: 給湯器をエネファーム（燃料電池）に買い換える | F15: consHWsum | G15: エネファーム | H15: エネファーム | I15: 0.5 | J15: 0.5 | K15: 5 | L15: 10 | M15: 10 | N15: 900000 | O15: 1 | P15: エコジョーズ | S15: エネファーム(R)は、燃料電池で発電をしながらお湯をわかす効率がよい装置です。家庭で消費する電気の分だけ発電を行い、発生した余熱をお湯としてためて利用することができます。電気やお湯をたくさん使う家庭で、大きな省エネ効果が期待できます。 | T15: エネファーム(R)は、燃料電池で発電をしながらお湯をわかす効率がよい装置です。家庭で消費する電気の分だけ発電を行い、発生した余熱をお湯としてためて利用することができます。電気やお湯をたくさん使う家庭で、大きな省エネ効果が期待できます。SOFCタイプは、さらに発電効率が高くなってり、お湯の発生量が少ないため、比較的お湯を使わない家庭でも効果がでます。発電を行うため、停電時にも一定の電気を取り出すことが可能となっています。 | V15: wss | Z15: ="D6.scenario.defMeasures['"&C15&"'] = { "&B$2&":"""&B15&""", "&C$2&":"""&C15&""", "&D$2&":"""&CLEAN(SUBSTITUTE(D15,"""","'"))&""", "&I$2&":"""&I15&""", "&F$2&":"""&F15&""", "&G$2&":"""&CLEAN(SUBSTITUTE(G15,"""","'"))&""", "&K$2&":"""&K15&""", "&L$2&":"""&L15&""", "&M$2&":"""&M15&""", "&N$2&":"""&N15&""", "&O$2&":"""&O15&""", "&P$2&":"""&P15&""", "&Q$2&":"""&Q15&""", "&S$2&":"""&CLEAN(SUBSTITUTE(S15,"""","'"))&""", "&U$2&":"""&U15&""", "&V$2&":"""&V15&"""};" -> D6.scenario.defMeasures['mHWenefarm'] = { mid:"105", name:"mHWenefarm", title:"給湯器をエネファーム（燃料電池）に買い換える", easyness:"0.5", refCons:"consHWsum", titleShort:"エネファーム", level:"5", figNum:"10", lifeTime:"10", price:"900000", roanShow:"1", standardType:"エコジョーズ", subsidy :"", advice:"エネファーム(R)は、燃料電池で発電をしながらお湯をわかす効率がよい装置です。家庭で消費する電気の分だけ発電を行い、発生した余熱をお湯としてためて利用することができます。電気やお湯をたくさん使う家庭で、大きな省エネ効果が期待できます。", lifestyle:"", season:"wss"}; | AB15: ="$defMeasures['"&C15&"'] = [ '"&B$2&"'=>"""&B15&""", '"&D$2&"'=>"""&CLEAN(SUBSTITUTE(D15,"""","'"))&""", '"&L$2&"'=>"""&L15&""", '"&S$2&"'=>"""&CLEAN(SUBSTITUTE(S15,"""","'"))&"""];" -> $defMeasures['mHWenefarm'] = [ 'mid'=>"105", 'title'=>"給湯器をエネファーム（燃料電池）に買い換える", 'figNum'=>"10", 'advice'=>"エネファーム(R)は、燃料電池で発電をしながらお湯をわかす効率がよい装置です。家庭で消費する電気の分だけ発電を行い、発生した余熱をお湯としてためて利用することができます。電気やお湯をたくさん使う家庭で、大きな省エネ効果が期待できます。"]; | AD15: 夢の技術とされた燃料電池が、実用的に広まりつつあります。停電時にも、発電して電気を生み出し使えるというのは、大きなメリットです。
B16: 106 | C16: mHWsolarHeater | D16: 太陽熱温水器（自然循環式）を設置して利用する | E16: 太陽熱温水器（自然循環式）を設置して利用する | F16: consHWsum | G16: 太陽熱温水器 | H16: 太陽熱温水器 | I16: 1 | J16: 1 | L16: 9 | M16: 10 | N16: 400000 | S16: 暖かい時期の晴れた日なら、太陽の熱で沸かしたお湯だけでお風呂に入ることができます。冬でも加温することで利用することができ、お湯のエネルギー消費を大幅に減らせます。比較的簡単なしくみでお湯をわかすことができ、有効な温暖化対策として、世界中で利用が拡大しています。 | T16: 暖かい時期の晴れた日なら、太陽の熱で沸かしたお湯だけでお風呂に入ることができます。冬でも加温することで利用することができ、お湯のエネルギー消費を大幅に減らせます。比較的簡単なしくみでお湯をわかすことができ、有効な温暖化対策として、世界中で利用が拡大しています。 | V16: wss | Z16: ="D6.scenario.defMeasures['"&C16&"'] = { "&B$2&":"""&B16&""", "&C$2&":"""&C16&""", "&D$2&":"""&CLEAN(SUBSTITUTE(D16,"""","'"))&""", "&I$2&":"""&I16&""", "&F$2&":"""&F16&""", "&G$2&":"""&CLEAN(SUBSTITUTE(G16,"""","'"))&""", "&K$2&":"""&K16&""", "&L$2&":"""&L16&""", "&M$2&":"""&M16&""", "&N$2&":"""&N16&""", "&O$2&":"""&O16&""", "&P$2&":"""&P16&""", "&Q$2&":"""&Q16&""", "&S$2&":"""&CLEAN(SUBSTITUTE(S16,"""","'"))&""", "&U$2&":"""&U16&""", "&V$2&":"""&V16&"""};" -> D6.scenario.defMeasures['mHWsolarHeater'] = { mid:"106", name:"mHWsolarHeater", title:"太陽熱温水器（自然循環式）を設置して利用する", easyness:"1", refCons:"consHWsum", titleShort:"太陽熱温水器", level:"", figNum:"9", lifeTime:"10", price:"400000", roanShow:"", standardType:"", subsidy :"", advice:"暖かい時期の晴れた日なら、太陽の熱で沸かしたお湯だけでお風呂に入ることができます。冬でも加温することで利用することができ、お湯のエネルギー消費を大幅に減らせます。比較的簡単なしくみでお湯をわかすことができ、有効な温暖化対策として、世界中で利用が拡大しています。", lifestyle:"", season:"wss"}; | AB16: ="$defMeasures['"&C16&"'] = [ '"&B$2&"'=>"""&B16&""", '"&D$2&"'=>"""&CLEAN(SUBSTITUTE(D16,"""","'"))&""", '"&L$2&"'=>"""&L16&""", '"&S$2&"'=>"""&CLEAN(SUBSTITUTE(S16,"""","'"))&"""];" -> $defMeasures['mHWsolarHeater'] = [ 'mid'=>"106", 'title'=>"太陽熱温水器（自然循環式）を設置して利用する", 'figNum'=>"9", 'advice'=>"暖かい時期の晴れた日なら、太陽の熱で沸かしたお湯だけでお風呂に入ることができます。冬でも加温することで利用することができ、お湯のエネルギー消費を大幅に減らせます。比較的簡単なしくみでお湯をわかすことができ、有効な温暖化対策として、世界中で利用が拡大しています。"]; | AD16: 夏は熱湯が出るほどになる一方、冬場や曇の日には、温度が低めといった、太陽の恵みを実感できる装置です。「今日はおてんと様が照らなかったから、しかたないね」といった、自然を感じる生活が可能です。
B17: 107 | C17: mHWsolarSystem | D17: ソーラーシステム（強制循環式）を設置して利用する | E17: ソーラーシステム（強制循環式）を設置して利用する | F17: consHWsum | G17: ソーラーシステム | H17: ソーラーシステム | I17: 1 | J17: 1 | L17: 9 | M17: 10 | N17: 600000 | Q17: 子育てグリーン住宅支援事業の対象で、他の断熱工事や機器導入を行って補助額が5万円以上になると補助されます。 | S17: 貯湯タンクを地上に置いて利用する太陽熱温水器です。屋根にタンクがないので、負荷がかかりません。暖かい時期の晴れた日なら、太陽の熱で沸かしたお湯だけでお風呂に入ることができます。冬でも加温することで利用することができ、お湯のエネルギー消費を大幅に減らせます。比較的簡単なしくみでお湯をわかすことができ、有効な温暖化対策として、世界中で利用が拡大しています。 | T17: 貯湯タンクを地上に置いて利用する太陽熱温水器です。屋根にタンクがないので、負荷がかかりません。暖かい時期の晴れた日なら、太陽の熱で沸かしたお湯だけでお風呂に入ることができます。冬でも加温することで利用することができ、お湯のエネルギー消費を大幅に減らせます。比較的簡単なしくみでお湯をわかすことができ、有効な温暖化対策として、世界中で利用が拡大しています。 | V17: wss | Z17: ="D6.scenario.defMeasures['"&C17&"'] = { "&B$2&":"""&B17&""", "&C$2&":"""&C17&""", "&D$2&":"""&CLEAN(SUBSTITUTE(D17,"""","'"))&""", "&I$2&":"""&I17&""", "&F$2&":"""&F17&""", "&G$2&":"""&CLEAN(SUBSTITUTE(G17,"""","'"))&""", "&K$2&":"""&K17&""", "&L$2&":"""&L17&""", "&M$2&":"""&M17&""", "&N$2&":"""&N17&""", "&O$2&":"""&O17&""", "&P$2&":"""&P17&""", "&Q$2&":"""&Q17&""", "&S$2&":"""&CLEAN(SUBSTITUTE(S17,"""","'"))&""", "&U$2&":"""&U17&""", "&V$2&":"""&V17&"""};" -> D6.scenario.defMeasures['mHWsolarSystem'] = { mid:"107", name:"mHWsolarSystem", title:"ソーラーシステム（強制循環式）を設置して利用する", easyness:"1", refCons:"consHWsum", titleShort:"ソーラーシステム", level:"", figNum:"9", lifeTime:"10", price:"600000", roanShow:"", standardType:"", subsidy :"子育てグリーン住宅支援事業の対象で、他の断熱工事や機器導入を行って補助額が5万円以上になると補助されます。", advice:"貯湯タンクを地上に置いて利用する太陽熱温水器です。屋根にタンクがないので、負荷がかかりません。暖かい時期の晴れた日なら、太陽の熱で沸かしたお湯だけでお風呂に入ることができます。冬でも加温することで利用することができ、お湯のエネルギー消費を大幅に減らせます。比較的簡単なしくみでお湯をわかすことができ、有効な温暖化対策として、世界中で利用が拡大しています。", lifestyle:"", season:"wss"}; | AB17: ="$defMeasures['"&C17&"'] = [ '"&B$2&"'=>"""&B17&""", '"&D$2&"'=>"""&CLEAN(SUBSTITUTE(D17,"""","'"))&""", '"&L$2&"'=>"""&L17&""", '"&S$2&"'=>"""&CLEAN(SUBSTITUTE(S17,"""","'"))&"""];" -> $defMeasures['mHWsolarSystem'] = [ 'mid'=>"107", 'title'=>"ソーラーシステム（強制循環式）を設置して利用する", 'figNum'=>"9", 'advice'=>"貯湯タンクを地上に置いて利用する太陽熱温水器です。屋根にタンクがないので、負荷がかかりません。暖かい時期の晴れた日なら、太陽の熱で沸かしたお湯だけでお風呂に入ることができます。冬でも加温することで利用することができ、お湯のエネルギー消費を大幅に減らせます。比較的簡単なしくみでお湯をわかすことができ、有効な温暖化対策として、世界中で利用が拡大しています。"]; | AD17: 屋根で温めたお湯を、電気温水器のような貯湯槽にためるのですから、便利極まりありません。夏場はお湯が使いたいほうだいですが、本当は冬に使いたいほうだいならいいのですけれどもね。
B18: 108 | C18: mHWshowerHead | D18: 節水シャワーヘッドを取り付けて利用する | E18: 節水シャワーヘッドを取り付けて利用する | F18: consHWshower | G18: 節水シャワーヘッド | H18: 節水シャワーヘッド | I18: 5 | J18: 5 | L18: 11 | M18: 10 | N18: 3000 | S18: シャワーの持ち手（ヘッド）の部分を取り替えることができるようになっています。お湯が出る穴を小さくしてあり、勢いよくお湯が出てくるほか、手元で止水できるものもあり、3割程度お湯の利用を減らすことができます。ホームセンターや家電量販店などで購入できます。 | T18: シャワーの持ち手（ヘッド）の部分を取り替えることができるようになっています。お湯が出る穴を小さくしてあり、勢いよくお湯が出てくるほか、手元で止水できるものもあり、3割程度お湯の利用を減らすことができます。ホームセンターや家電量販店などで購入できます。 | U18: 1 | V18: wss | Z18: ="D6.scenario.defMeasures['"&C18&"'] = { "&B$2&":"""&B18&""", "&C$2&":"""&C18&""", "&D$2&":"""&CLEAN(SUBSTITUTE(D18,"""","'"))&""", "&I$2&":"""&I18&""", "&F$2&":"""&F18&""", "&G$2&":"""&CLEAN(SUBSTITUTE(G18,"""","'"))&""", "&K$2&":"""&K18&""", "&L$2&":"""&L18&""", "&M$2&":"""&M18&""", "&N$2&":"""&N18&""", "&O$2&":"""&O18&""", "&P$2&":"""&P18&""", "&Q$2&":"""&Q18&""", "&S$2&":"""&CLEAN(SUBSTITUTE(S18,"""","'"))&""", "&U$2&":"""&U18&""", "&V$2&":"""&V18&"""};" -> D6.scenario.defMeasures['mHWshowerHead'] = { mid:"108", name:"mHWshowerHead", title:"節水シャワーヘッドを取り付けて利用する", easyness:"5", refCons:"consHWshower", titleShort:"節水シャワーヘッド", level:"", figNum:"11", lifeTime:"10", price:"3000", roanShow:"", standardType:"", subsidy :"", advice:"シャワーの持ち手（ヘッド）の部分を取り替えることができるようになっています。お湯が出る穴を小さくしてあり、勢いよくお湯が出てくるほか、手元で止水できるものもあり、3割程度お湯の利用を減らすことができます。ホームセンターや家電量販店などで購入できます。", lifestyle:"1", season:"wss"}; | AB18: ="$defMeasures['"&C18&"'] = [ '"&B$2&"'=>"""&B18&""", '"&D$2&"'=>"""&CLEAN(SUBSTITUTE(D18,"""","'"))&""", '"&L$2&"'=>"""&L18&""", '"&S$2&"'=>"""&CLEAN(SUBSTITUTE(S18,"""","'"))&"""];" -> $defMeasures['mHWshowerHead'] = [ 'mid'=>"108", 'title'=>"節水シャワーヘッドを取り付けて利用する", 'figNum'=>"11", 'advice'=>"シャワーの持ち手（ヘッド）の部分を取り替えることができるようになっています。お湯が出る穴を小さくしてあり、勢いよくお湯が出てくるほか、手元で止水できるものもあり、3割程度お湯の利用を減らすことができます。ホームセンターや家電量販店などで購入できます。"]; | AD18: 化学調味料の販売を増やすために、穴を大きくしたという伝説が伝わっていますが、まさにそれを応用した省エネ手法です。勢いがあるので、快適さはかわりません。<br> シャワーのお湯は、お湯を流しつづけるために大量のエネルギーが必要で、およそテレビ300台のエネルギーに相当します。節水シャワーヘッドなら、3分の1削減ですから、100台分のテレビを消した効果がでてきます。
B19: 109 | C19: mHWshowerTime | D19: シャワーの利用を1人1日1分短くする | E19: シャワーの利用を1人1日1分短くする | F19: consHWshower | G19: シャワー1人1分短縮 | H19: シャワー1人1分短縮 | I19: 4 | J19: 4 | L19: 11 | S19: シャワーのエネルギー消費はとても大きく、お湯を出している状態で、テレビ300台分のエネルギーが消費されます。少し止めるだけでも大きな削減になります。身体を洗っているときには止めるなど、利用時間を減らすよう気を付けましょう。 | T19: シャワーのエネルギー消費はとても大きく、お湯を出している状態で、テレビ300台分のエネルギーが消費されます。少し止めるだけでも大きな削減になります。身体を洗っているときには止めるなど、利用時間を減らすよう気を付けましょう。 | U19: 1 | V19: wss | Z19: ="D6.scenario.defMeasures['"&C19&"'] = { "&B$2&":"""&B19&""", "&C$2&":"""&C19&""", "&D$2&":"""&CLEAN(SUBSTITUTE(D19,"""","'"))&""", "&I$2&":"""&I19&""", "&F$2&":"""&F19&""", "&G$2&":"""&CLEAN(SUBSTITUTE(G19,"""","'"))&""", "&K$2&":"""&K19&""", "&L$2&":"""&L19&""", "&M$2&":"""&M19&""", "&N$2&":"""&N19&""", "&O$2&":"""&O19&""", "&P$2&":"""&P19&""", "&Q$2&":"""&Q19&""", "&S$2&":"""&CLEAN(SUBSTITUTE(S19,"""","'"))&""", "&U$2&":"""&U19&""", "&V$2&":"""&V19&"""};" -> D6.scenario.defMeasures['mHWshowerTime'] = { mid:"109", name:"mHWshowerTime", title:"シャワーの利用を1人1日1分短くする", easyness:"4", refCons:"consHWshower", titleShort:"シャワー1人1分短縮", level:"", figNum:"11", lifeTime:"", price:"", roanShow:"", standardType:"", subsidy :"", advice:"シャワーのエネルギー消費はとても大きく、お湯を出している状態で、テレビ300台分のエネルギーが消費されます。少し止めるだけでも大きな削減になります。身体を洗っているときには止めるなど、利用時間を減らすよう気を付けましょう。", lifestyle:"1", season:"wss"}; | AB19: ="$defMeasures['"&C19&"'] = [ '"&B$2&"'=>"""&B19&""", '"&D$2&"'=>"""&CLEAN(SUBSTITUTE(D19,"""","'"))&""", '"&L$2&"'=>"""&L19&""", '"&S$2&"'=>"""&CLEAN(SUBSTITUTE(S19,"""","'"))&"""];" -> $defMeasures['mHWshowerTime'] = [ 'mid'=>"109", 'title'=>"シャワーの利用を1人1日1分短くする", 'figNum'=>"11", 'advice'=>"シャワーのエネルギー消費はとても大きく、お湯を出している状態で、テレビ300台分のエネルギーが消費されます。少し止めるだけでも大きな削減になります。身体を洗っているときには止めるなど、利用時間を減らすよう気を付けましょう。"]; | AD19: シャワーを何分使っているかなんて、ちゃんと計測した人はいないかもしれません。プライバシーに大きく関わることですが、一度測ってみてはいかがでしょうか。<br> シャワーで使うお湯がどれだけなのかは、浴槽が空の状態で栓をして、浴槽のなかでふだんどおりシャワーで洗ってみるとわかります。少し汚いですが、何センチお湯がたまったでしょうか。
B20: 110 | C20: mHWshowerTime30 | D20: シャワーの利用時間を3割短くする | E20: シャワーの利用時間を3割短くする | F20: consHWshower | G20: シャワー3割短縮 | H20: シャワー3割短縮 | I20: 3 | J20: 3 | L20: 11 | S20: シャワーのエネルギー消費はとても大きく、お湯を出している状態で、テレビ300台分のエネルギーが消費されます。少し止めるだけでも大きな削減になります。身体を洗っているときには止めるなど、利用時間を減らすよう気を付けましょう。 | T20: シャワーのエネルギー消費はとても大きく、お湯を出している状態で、テレビ300台分のエネルギーが消費されます。少し止めるだけでも大きな削減になります。身体を洗っているときには止めるなど、利用時間を減らすよう気を付けましょう。 | U20: 1 | V20: wss | Z20: ="D6.scenario.defMeasures['"&C20&"'] = { "&B$2&":"""&B20&""", "&C$2&":"""&C20&""", "&D$2&":"""&CLEAN(SUBSTITUTE(D20,"""","'"))&""", "&I$2&":"""&I20&""", "&F$2&":"""&F20&""", "&G$2&":"""&CLEAN(SUBSTITUTE(G20,"""","'"))&""", "&K$2&":"""&K20&""", "&L$2&":"""&L20&""", "&M$2&":"""&M20&""", "&N$2&":"""&N20&""", "&O$2&":"""&O20&""", "&P$2&":"""&P20&""", "&Q$2&":"""&Q20&""", "&S$2&":"""&CLEAN(SUBSTITUTE(S20,"""","'"))&""", "&U$2&":"""&U20&""", "&V$2&":"""&V20&"""};" -> D6.scenario.defMeasures['mHWshowerTime30'] = { mid:"110", name:"mHWshowerTime30", title:"シャワーの利用時間を3割短くする", easyness:"3", refCons:"consHWshower", titleShort:"シャワー3割短縮", level:"", figNum:"11", lifeTime:"", price:"", roanShow:"", standardType:"", subsidy :"", advice:"シャワーのエネルギー消費はとても大きく、お湯を出している状態で、テレビ300台分のエネルギーが消費されます。少し止めるだけでも大きな削減になります。身体を洗っているときには止めるなど、利用時間を減らすよう気を付けましょう。", lifestyle:"1", season:"wss"}; | AB20: ="$defMeasures['"&C20&"'] = [ '"&B$2&"'=>"""&B20&""", '"&D$2&"'=>"""&CLEAN(SUBSTITUTE(D20,"""","'"))&""", '"&L$2&"'=>"""&L20&""", '"&S$2&"'=>"""&CLEAN(SUBSTITUTE(S20,"""","'"))&"""];" -> $defMeasures['mHWshowerTime30'] = [ 'mid'=>"110", 'title'=>"シャワーの利用時間を3割短くする", 'figNum'=>"11", 'advice'=>"シャワーのエネルギー消費はとても大きく、お湯を出している状態で、テレビ300台分のエネルギーが消費されます。少し止めるだけでも大きな削減になります。身体を洗っているときには止めるなど、利用時間を減らすよう気を付けましょう。"]; | AD20: シャワーを何分使っているかなんて、ちゃんと計測した人はいないかもしれません。プライバシーに大きく関わることですが、一度測ってみてはいかがでしょうか。<br> シャワーで使うお湯がどれだけなのかは、浴槽が空の状態で栓をして、浴槽のなかでふだんどおりシャワーで洗ってみるとわかります。少し汚いですが、何センチお湯がたまったでしょうか。
B21: 111 | C21: mHWkeep | D21: 風呂に家族が続けて入り追い焚きをしない | E21: 風呂に家族が続けて入り追い焚きをしない | F21: consHWtub | G21: 風呂の保温をしない | H21: 風呂の保温をしない | I21: 3 | J21: 3 | L21: 12 | S21: 追い焚きでは、風呂のお湯をいちど外に出し、給湯器まで送る必要があります。この間に冷えてしまい、余分なエネルギーがかかります。追い焚き機能を使わずに、続けてはいることが大きな削減になります。また浴槽に蓋をすることでも、冷めにくくすることもできます。 | T21: 追い焚きでは、風呂のお湯をいちど外に出し、給湯器まで送る必要があります。この間に冷えてしまい、余分なエネルギーがかかります。追い焚き機能を使わずに、続けてはいることが大きな削減になります。また浴槽に蓋をすることでも、冷めにくくすることもできます。 | U21: 1 | V21: wss | Z21: ="D6.scenario.defMeasures['"&C21&"'] = { "&B$2&":"""&B21&""", "&C$2&":"""&C21&""", "&D$2&":"""&CLEAN(SUBSTITUTE(D21,"""","'"))&""", "&I$2&":"""&I21&""", "&F$2&":"""&F21&""", "&G$2&":"""&CLEAN(SUBSTITUTE(G21,"""","'"))&""", "&K$2&":"""&K21&""", "&L$2&":"""&L21&""", "&M$2&":"""&M21&""", "&N$2&":"""&N21&""", "&O$2&":"""&O21&""", "&P$2&":"""&P21&""", "&Q$2&":"""&Q21&""", "&S$2&":"""&CLEAN(SUBSTITUTE(S21,"""","'"))&""", "&U$2&":"""&U21&""", "&V$2&":"""&V21&"""};" -> D6.scenario.defMeasures['mHWkeep'] = { mid:"111", name:"mHWkeep", title:"風呂に家族が続けて入り追い焚きをしない", easyness:"3", refCons:"consHWtub", titleShort:"風呂の保温をしない", level:"", figNum:"12", lifeTime:"", price:"", roanShow:"", standardType:"", subsidy :"", advice:"追い焚きでは、風呂のお湯をいちど外に出し、給湯器まで送る必要があります。この間に冷えてしまい、余分なエネルギーがかかります。追い焚き機能を使わずに、続けてはいることが大きな削減になります。また浴槽に蓋をすることでも、冷めにくくすることもできます。", lifestyle:"1", season:"wss"}; | AB21: ="$defMeasures['"&C21&"'] = [ '"&B$2&"'=>"""&B21&""", '"&D$2&"'=>"""&CLEAN(SUBSTITUTE(D21,"""","'"))&""", '"&L$2&"'=>"""&L21&""", '"&S$2&"'=>"""&CLEAN(SUBSTITUTE(S21,"""","'"))&"""];" -> $defMeasures['mHWkeep'] = [ 'mid'=>"111", 'title'=>"風呂に家族が続けて入り追い焚きをしない", 'figNum'=>"12", 'advice'=>"追い焚きでは、風呂のお湯をいちど外に出し、給湯器まで送る必要があります。この間に冷えてしまい、余分なエネルギーがかかります。追い焚き機能を使わずに、続けてはいることが大きな削減になります。また浴槽に蓋をすることでも、冷めにくくすることもできます。"]; | AD21: 夫婦仲良くいっしょに入っている家庭もあるようです。
B22: 112 | C22: mHWsaveMode | D22: エコキュートを「節約モード」に設定する | E22: エコキュートを「節約モード」に設定する | F22: consHWsum | G22: 給湯節約モード | H22: 給湯節約モード | I22: 3 | J22: 3 | L22: 8 | S22: エコキュートは夜間に沸かす湯量の設定ができるようになっています。お湯切れがないように余裕に沸かすと、保温時のロスが大きくなります。通常の使い方をする日で、特に湯切れなどない場合には、節約モードに設定することで、省エネになります。 | T22: エコキュートは夜間に沸かす湯量の設定ができるようになっています。お湯切れがないように余裕に沸かすと、保温時のロスが大きくなります。通常の使い方をする日で、特に湯切れなどない場合には、節約モードに設定することで、省エネになります。 | U22: 1 | V22: wss | Z22: ="D6.scenario.defMeasures['"&C22&"'] = { "&B$2&":"""&B22&""", "&C$2&":"""&C22&""", "&D$2&":"""&CLEAN(SUBSTITUTE(D22,"""","'"))&""", "&I$2&":"""&I22&""", "&F$2&":"""&F22&""", "&G$2&":"""&CLEAN(SUBSTITUTE(G22,"""","'"))&""", "&K$2&":"""&K22&""", "&L$2&":"""&L22&""", "&M$2&":"""&M22&""", "&N$2&":"""&N22&""", "&O$2&":"""&O22&""", "&P$2&":"""&P22&""", "&Q$2&":"""&Q22&""", "&S$2&":"""&CLEAN(SUBSTITUTE(S22,"""","'"))&""", "&U$2&":"""&U22&""", "&V$2&":"""&V22&"""};" -> D6.scenario.defMeasures['mHWsaveMode'] = { mid:"112", name:"mHWsaveMode", title:"エコキュートを「節約モード」に設定する", easyness:"3", refCons:"consHWsum", titleShort:"給湯節約モード", level:"", figNum:"8", lifeTime:"", price:"", roanShow:"", standardType:"", subsidy :"", advice:"エコキュートは夜間に沸かす湯量の設定ができるようになっています。お湯切れがないように余裕に沸かすと、保温時のロスが大きくなります。通常の使い方をする日で、特に湯切れなどない場合には、節約モードに設定することで、省エネになります。", lifestyle:"1", season:"wss"}; | AB22: ="$defMeasures['"&C22&"'] = [ '"&B$2&"'=>"""&B22&""", '"&D$2&"'=>"""&CLEAN(SUBSTITUTE(D22,"""","'"))&""", '"&L$2&"'=>"""&L22&""", '"&S$2&"'=>"""&CLEAN(SUBSTITUTE(S22,"""","'"))&"""];" -> $defMeasures['mHWsaveMode'] = [ 'mid'=>"112", 'title'=>"エコキュートを「節約モード」に設定する", 'figNum'=>"8", 'advice'=>"エコキュートは夜間に沸かす湯量の設定ができるようになっています。お湯切れがないように余裕に沸かすと、保温時のロスが大きくなります。通常の使い方をする日で、特に湯切れなどない場合には、節約モードに設定することで、省エネになります。"]; | AD22: ふだん湯切れしないなら、少し節約側に設定してみてください。好きな方は、次の日にどれだけお湯を使うかを予測して、設定してみることもできます。
B23: 113 | C23: mHWstopAutoKeep | D23: 自動保温を続けるのでなく、次の人が入る直前に沸かし直す | E23: 自動保温を続けるのでなく、次の人が入る直前に沸かし直す | F23: consHWtub | G23: 自動保温をしない | H23: 自動保温をしない | I23: 3 | J23: 3 | L23: 12 | S23: 自動保温では、頻繁に風呂のお湯を屋外の給湯器まで送り出して温めるため、配管部分の熱の無駄が大きくなります。続けて入ることで保温しなくてもすみますが、時間があいて冷めてしまう場合には自動保温をせず、後から入る直前に温め直すことで省エネになります。 | T23: 自動保温では、頻繁に風呂のお湯を屋外の給湯器まで送り出して温めるため、配管部分の熱の無駄が大きくなります。続けて入ることで保温しなくてもすみますが、時間があいて冷めてしまう場合には自動保温をせず、後から入る直前に温め直すことで省エネになります。 | U23: 1 | V23: wss | Z23: ="D6.scenario.defMeasures['"&C23&"'] = { "&B$2&":"""&B23&""", "&C$2&":"""&C23&""", "&D$2&":"""&CLEAN(SUBSTITUTE(D23,"""","'"))&""", "&I$2&":"""&I23&""", "&F$2&":"""&F23&""", "&G$2&":"""&CLEAN(SUBSTITUTE(G23,"""","'"))&""", "&K$2&":"""&K23&""", "&L$2&":"""&L23&""", "&M$2&":"""&M23&""", "&N$2&":"""&N23&""", "&O$2&":"""&O23&""", "&P$2&":"""&P23&""", "&Q$2&":"""&Q23&""", "&S$2&":"""&CLEAN(SUBSTITUTE(S23,"""","'"))&""", "&U$2&":"""&U23&""", "&V$2&":"""&V23&"""};" -> D6.scenario.defMeasures['mHWstopAutoKeep'] = { mid:"113", name:"mHWstopAutoKeep", title:"自動保温を続けるのでなく、次の人が入る直前に沸かし直す", easyness:"3", refCons:"consHWtub", titleShort:"自動保温をしない", level:"", figNum:"12", lifeTime:"", price:"", roanShow:"", standardType:"", subsidy :"", advice:"自動保温では、頻繁に風呂のお湯を屋外の給湯器まで送り出して温めるため、配管部分の熱の無駄が大きくなります。続けて入ることで保温しなくてもすみますが、時間があいて冷めてしまう場合には自動保温をせず、後から入る直前に温め直すことで省エネになります。", lifestyle:"1", season:"wss"}; | AB23: ="$defMeasures['"&C23&"'] = [ '"&B$2&"'=>"""&B23&""", '"&D$2&"'=>"""&CLEAN(SUBSTITUTE(D23,"""","'"))&""", '"&L$2&"'=>"""&L23&""", '"&S$2&"'=>"""&CLEAN(SUBSTITUTE(S23,"""","'"))&"""];" -> $defMeasures['mHWstopAutoKeep'] = [ 'mid'=>"113", 'title'=>"自動保温を続けるのでなく、次の人が入る直前に沸かし直す", 'figNum'=>"12", 'advice'=>"自動保温では、頻繁に風呂のお湯を屋外の給湯器まで送り出して温めるため、配管部分の熱の無駄が大きくなります。続けて入ることで保温しなくてもすみますが、時間があいて冷めてしまう場合には自動保温をせず、後から入る直前に温め直すことで省エネになります。"]; | AD23: 高い温度を維持し続けようとすると、常にエネルギーがかかります。いったん休んでから、必要なときに温めるほうが省エネです。これは人間でも同じかもしれませんね。給湯器さんの立場にたって、考えてみましょう。
B24: 114 | C24: mHWinsulation | D24: 断熱型の浴槽にリフォームする | E24: 断熱型の浴槽にリフォームする | F24: consHWtub | G24: 断熱浴槽 | H24: 断熱浴槽 | I24: 1 | J24: 1 | L24: 12 | M24: 10 | N24: 600000 | P24: 普及型 | Q24: 子育てグリーン住宅支援事業の対象で、他の断熱工事や機器導入を行って補助額が5万円以上になると補助されます。 | S24: 浴槽が発泡スチロールなどの断熱材で覆われており、お湯が冷めにくくなっているタイプが増えています。浴槽のリフォーム工事が必要になりますが、冷めにくい分、追い焚きをしなくてすみます。あわせて、浴室もユニットバスにすると、浴室全体からの熱も逃げにくくなります。 | T24: 浴槽が発泡スチロールなどの断熱材で覆われており、お湯が冷めにくくなっているタイプが増えています。浴槽のリフォーム工事が必要になりますが、冷めにくい分、追い焚きをしなくてすみます。あわせて、浴室もユニットバスにすると、浴室全体からの熱も逃げにくくなります。 | V24: wss | Z24: ="D6.scenario.defMeasures['"&C24&"'] = { "&B$2&":"""&B24&""", "&C$2&":"""&C24&""", "&D$2&":"""&CLEAN(SUBSTITUTE(D24,"""","'"))&""", "&I$2&":"""&I24&""", "&F$2&":"""&F24&""", "&G$2&":"""&CLEAN(SUBSTITUTE(G24,"""","'"))&""", "&K$2&":"""&K24&""", "&L$2&":"""&L24&""", "&M$2&":"""&M24&""", "&N$2&":"""&N24&""", "&O$2&":"""&O24&""", "&P$2&":"""&P24&""", "&Q$2&":"""&Q24&""", "&S$2&":"""&CLEAN(SUBSTITUTE(S24,"""","'"))&""", "&U$2&":"""&U24&""", "&V$2&":"""&V24&"""};" -> D6.scenario.defMeasures['mHWinsulation'] = { mid:"114", name:"mHWinsulation", title:"断熱型の浴槽にリフォームする", easyness:"1", refCons:"consHWtub", titleShort:"断熱浴槽", level:"", figNum:"12", lifeTime:"10", price:"600000", roanShow:"", standardType:"普及型", subsidy :"子育てグリーン住宅支援事業の対象で、他の断熱工事や機器導入を行って補助額が5万円以上になると補助されます。", advice:"浴槽が発泡スチロールなどの断熱材で覆われており、お湯が冷めにくくなっているタイプが増えています。浴槽のリフォーム工事が必要になりますが、冷めにくい分、追い焚きをしなくてすみます。あわせて、浴室もユニットバスにすると、浴室全体からの熱も逃げにくくなります。", lifestyle:"", season:"wss"}; | AB24: ="$defMeasures['"&C24&"'] = [ '"&B$2&"'=>"""&B24&""", '"&D$2&"'=>"""&CLEAN(SUBSTITUTE(D24,"""","'"))&""", '"&L$2&"'=>"""&L24&""", '"&S$2&"'=>"""&CLEAN(SUBSTITUTE(S24,"""","'"))&"""];" -> $defMeasures['mHWinsulation'] = [ 'mid'=>"114", 'title'=>"断熱型の浴槽にリフォームする", 'figNum'=>"12", 'advice'=>"浴槽が発泡スチロールなどの断熱材で覆われており、お湯が冷めにくくなっているタイプが増えています。浴槽のリフォーム工事が必要になりますが、冷めにくい分、追い焚きをしなくてすみます。あわせて、浴室もユニットバスにすると、浴室全体からの熱も逃げにくくなります。"]; | AD24: これがない時代は、浴槽の底から冷たくなってくるのが感じられました。浴槽の裏側に断熱材をつけただけなので、取り立てて画期的な技術ではないはずですが、とても快適です。
B25: 115 | C25: mHWonlyShower | D25: 夏場はシャワーだけですませて浴槽にお湯を張らない | E25: 夏場はシャワーだけですませて浴槽にお湯を張らない | F25: consHWtub | G25: 夏に浴槽のお湯をためない | H25: 夏に浴槽のお湯をためない | I25: 3 | J25: 3 | L25: 11 | S25: 浴槽のお湯の量は、シャワーを使っている時間に換算すると10～20分に相当します。自動湯張りをせずに、浴槽のお湯だけを使って体を洗う使い方ではかえってエネルギー消費が増える場合もありますが、シャワーを併用している場合には浴槽の分が削減になります。 | T25: 浴槽のお湯の量は、シャワーを使っている時間に換算すると10～20分に相当します。自動湯張りをせずに、浴槽のお湯だけを使って体を洗う使い方ではかえってエネルギー消費が増える場合もありますが、シャワーを併用している場合には浴槽の分が削減になります。 | U25: 1 | V25: wss | Z25: ="D6.scenario.defMeasures['"&C25&"'] = { "&B$2&":"""&B25&""", "&C$2&":"""&C25&""", "&D$2&":"""&CLEAN(SUBSTITUTE(D25,"""","'"))&""", "&I$2&":"""&I25&""", "&F$2&":"""&F25&""", "&G$2&":"""&CLEAN(SUBSTITUTE(G25,"""","'"))&""", "&K$2&":"""&K25&""", "&L$2&":"""&L25&""", "&M$2&":"""&M25&""", "&N$2&":"""&N25&""", "&O$2&":"""&O25&""", "&P$2&":"""&P25&""", "&Q$2&":"""&Q25&""", "&S$2&":"""&CLEAN(SUBSTITUTE(S25,"""","'"))&""", "&U$2&":"""&U25&""", "&V$2&":"""&V25&"""};" -> D6.scenario.defMeasures['mHWonlyShower'] = { mid:"115", name:"mHWonlyShower", title:"夏場はシャワーだけですませて浴槽にお湯を張らない", easyness:"3", refCons:"consHWtub", titleShort:"夏に浴槽のお湯をためない", level:"", figNum:"11", lifeTime:"", price:"", roanShow:"", standardType:"", subsidy :"", advice:"浴槽のお湯の量は、シャワーを使っている時間に換算すると10～20分に相当します。自動湯張りをせずに、浴槽のお湯だけを使って体を洗う使い方ではかえってエネルギー消費が増える場合もありますが、シャワーを併用している場合には浴槽の分が削減になります。", lifestyle:"1", season:"wss"}; | AB25: ="$defMeasures['"&C25&"'] = [ '"&B$2&"'=>"""&B25&""", '"&D$2&"'=>"""&CLEAN(SUBSTITUTE(D25,"""","'"))&""", '"&L$2&"'=>"""&L25&""", '"&S$2&"'=>"""&CLEAN(SUBSTITUTE(S25,"""","'"))&"""];" -> $defMeasures['mHWonlyShower'] = [ 'mid'=>"115", 'title'=>"夏場はシャワーだけですませて浴槽にお湯を張らない", 'figNum'=>"11", 'advice'=>"浴槽のお湯の量は、シャワーを使っている時間に換算すると10～20分に相当します。自動湯張りをせずに、浴槽のお湯だけを使って体を洗う使い方ではかえってエネルギー消費が増える場合もありますが、シャワーを併用している場合には浴槽の分が削減になります。"]; | AD25: 夏は浴槽につかると暑くなるので、シャワーだけという家庭も多いです。ちなみに、シャワーと浴槽とどっちがお湯の消費が少ないのか聞かれることがありますが、浴槽をためながらシャワーを使う家庭なら、浴槽の分がそのまま削減になります。ただ、シャワーも20分近く使っていると、浴槽1杯分になるので、使う時間には注意が必要です。<br>さあ夏ができるのなら、春秋だってできそうですね。春秋ができたら、冬だってできるのではないでしょうか。（実際にそんな家庭もあります）
B26: 116 | C26: mHWdishTank | D26: 食器洗いでお湯を流しっぱなしにしない | E26: 食器洗いでお湯を流しっぱなしにしない | F26: consHWdishwash | G26: 食器流し洗い | H26: 食器流し洗い | I26: 2 | J26: 2 | L26: 13 | S26: 洗剤で洗っているときにはお湯を止めるなど、なるべくお湯を出す時間を短く工夫してください。油汚れは古布等で先にふき取っておくと、すすぎも早く済みます。 | T26: 洗剤で洗っているときにはお湯を止めるなど、なるべくお湯を出す時間を短く工夫してください。油汚れは古布等で先にふき取っておくと、すすぎも早く済みます。 | U26: 1 | V26: wss | Z26: ="D6.scenario.defMeasures['"&C26&"'] = { "&B$2&":"""&B26&""", "&C$2&":"""&C26&""", "&D$2&":"""&CLEAN(SUBSTITUTE(D26,"""","'"))&""", "&I$2&":"""&I26&""", "&F$2&":"""&F26&""", "&G$2&":"""&CLEAN(SUBSTITUTE(G26,"""","'"))&""", "&K$2&":"""&K26&""", "&L$2&":"""&L26&""", "&M$2&":"""&M26&""", "&N$2&":"""&N26&""", "&O$2&":"""&O26&""", "&P$2&":"""&P26&""", "&Q$2&":"""&Q26&""", "&S$2&":"""&CLEAN(SUBSTITUTE(S26,"""","'"))&""", "&U$2&":"""&U26&""", "&V$2&":"""&V26&"""};" -> D6.scenario.defMeasures['mHWdishTank'] = { mid:"116", name:"mHWdishTank", title:"食器洗いでお湯を流しっぱなしにしない", easyness:"2", refCons:"consHWdishwash", titleShort:"食器流し洗い", level:"", figNum:"13", lifeTime:"", price:"", roanShow:"", standardType:"", subsidy :"", advice:"洗剤で洗っているときにはお湯を止めるなど、なるべくお湯を出す時間を短く工夫してください。油汚れは古布等で先にふき取っておくと、すすぎも早く済みます。", lifestyle:"1", season:"wss"}; | AB26: ="$defMeasures['"&C26&"'] = [ '"&B$2&"'=>"""&B26&""", '"&D$2&"'=>"""&CLEAN(SUBSTITUTE(D26,"""","'"))&""", '"&L$2&"'=>"""&L26&""", '"&S$2&"'=>"""&CLEAN(SUBSTITUTE(S26,"""","'"))&"""];" -> $defMeasures['mHWdishTank'] = [ 'mid'=>"116", 'title'=>"食器洗いでお湯を流しっぱなしにしない", 'figNum'=>"13", 'advice'=>"洗剤で洗っているときにはお湯を止めるなど、なるべくお湯を出す時間を短く工夫してください。油汚れは古布等で先にふき取っておくと、すすぎも早く済みます。"]; | AD26: 予洗いとすすぎのときに、お湯を流すだけで大丈夫です。洗剤で洗いながらすすぐと、こびりついたご飯の粒に出くわした時に、時間のロスになります。固まったご飯のかけらに、お湯の洪水は必要ありません。
B27: 117 | C27: mHWdishWater | D27: 水が冷たくない時期には水で食器を洗う | E27: 水が冷たくない時期には水で食器を洗う | F27: consHWdishwash | G27: 食器水洗い | H27: 食器水洗い | I27: 2 | J27: 2 | L27: 13 | S27: 暖かい季節には、お湯を使わなくても十分すすぐことができます。たとえば食器を洗うのにお湯を10分使う場合、約50リットルのお湯が消費されます。油汚れは古布等でふき取っておくなど工夫することで、すすぎも速くすみます。 | T27: 暖かい季節には、お湯を使わなくても十分すすぐことができます。たとえば食器を洗うのにお湯を10分使う場合、約50リットルのお湯が消費されます。油汚れは古布等でふき取っておくなど工夫することで、すすぎも速くすみます。 | U27: 1 | V27: wss | Z27: ="D6.scenario.defMeasures['"&C27&"'] = { "&B$2&":"""&B27&""", "&C$2&":"""&C27&""", "&D$2&":"""&CLEAN(SUBSTITUTE(D27,"""","'"))&""", "&I$2&":"""&I27&""", "&F$2&":"""&F27&""", "&G$2&":"""&CLEAN(SUBSTITUTE(G27,"""","'"))&""", "&K$2&":"""&K27&""", "&L$2&":"""&L27&""", "&M$2&":"""&M27&""", "&N$2&":"""&N27&""", "&O$2&":"""&O27&""", "&P$2&":"""&P27&""", "&Q$2&":"""&Q27&""", "&S$2&":"""&CLEAN(SUBSTITUTE(S27,"""","'"))&""", "&U$2&":"""&U27&""", "&V$2&":"""&V27&"""};" -> D6.scenario.defMeasures['mHWdishWater'] = { mid:"117", name:"mHWdishWater", title:"水が冷たくない時期には水で食器を洗う", easyness:"2", refCons:"consHWdishwash", titleShort:"食器水洗い", level:"", figNum:"13", lifeTime:"", price:"", roanShow:"", standardType:"", subsidy :"", advice:"暖かい季節には、お湯を使わなくても十分すすぐことができます。たとえば食器を洗うのにお湯を10分使う場合、約50リットルのお湯が消費されます。油汚れは古布等でふき取っておくなど工夫することで、すすぎも速くすみます。", lifestyle:"1", season:"wss"}; | AB27: ="$defMeasures['"&C27&"'] = [ '"&B$2&"'=>"""&B27&""", '"&D$2&"'=>"""&CLEAN(SUBSTITUTE(D27,"""","'"))&""", '"&L$2&"'=>"""&L27&""", '"&S$2&"'=>"""&CLEAN(SUBSTITUTE(S27,"""","'"))&"""];" -> $defMeasures['mHWdishWater'] = [ 'mid'=>"117", 'title'=>"水が冷たくない時期には水で食器を洗う", 'figNum'=>"13", 'advice'=>"暖かい季節には、お湯を使わなくても十分すすぐことができます。たとえば食器を洗うのにお湯を10分使う場合、約50リットルのお湯が消費されます。油汚れは古布等でふき取っておくなど工夫することで、すすぎも速くすみます。"]; | AD27: さすがに水が冷たい時期では、汚れ落ちも悪いですし、あかぎれもできてしまいます。ちなみに、あかぎれには生味噌をすりこむと痛いですが、実際昔にされいていた民間療法のひとつです。せめてラジオでも聞きながら、楽しく食器洗いしましょう。
B28: 118 | C28: mCKdishWasher | D28: 食器洗い乾燥機を使う | E28: 食器洗い乾燥機を使う | F28: consHWdishwash | G28: 食器洗浄機 | H28: 食器洗浄機 | I28: 2 | J28: 2 | L28: 15 | M28: 10 | N28: 80000 | S28: 食器をお湯で流し洗いするのに比べると、お湯をためて洗浄しているため、食器洗浄乾燥機のほうが省エネとなります。なおお湯ではなく水で洗う場合には、食器洗浄機よりも省エネとなります。手洗いで工夫するのも有効な方法です。 | T28: 食器をお湯で流し洗いするのに比べると、お湯をためて洗浄しているため、食器洗浄乾燥機のほうが省エネとなります。なおお湯ではなく水で洗う場合には、食器洗浄機よりも省エネとなります。手洗いで工夫するのも有効な方法です。 | V28: wss | Z28: ="D6.scenario.defMeasures['"&C28&"'] = { "&B$2&":"""&B28&""", "&C$2&":"""&C28&""", "&D$2&":"""&CLEAN(SUBSTITUTE(D28,"""","'"))&""", "&I$2&":"""&I28&""", "&F$2&":"""&F28&""", "&G$2&":"""&CLEAN(SUBSTITUTE(G28,"""","'"))&""", "&K$2&":"""&K28&""", "&L$2&":"""&L28&""", "&M$2&":"""&M28&""", "&N$2&":"""&N28&""", "&O$2&":"""&O28&""", "&P$2&":"""&P28&""", "&Q$2&":"""&Q28&""", "&S$2&":"""&CLEAN(SUBSTITUTE(S28,"""","'"))&""", "&U$2&":"""&U28&""", "&V$2&":"""&V28&"""};" -> D6.scenario.defMeasures['mCKdishWasher'] = { mid:"118", name:"mCKdishWasher", title:"食器洗い乾燥機を使う", easyness:"2", refCons:"consHWdishwash", titleShort:"食器洗浄機", level:"", figNum:"15", lifeTime:"10", price:"80000", roanShow:"", standardType:"", subsidy :"", advice:"食器をお湯で流し洗いするのに比べると、お湯をためて洗浄しているため、食器洗浄乾燥機のほうが省エネとなります。なおお湯ではなく水で洗う場合には、食器洗浄機よりも省エネとなります。手洗いで工夫するのも有効な方法です。", lifestyle:"", season:"wss"}; | AB28: ="$defMeasures['"&C28&"'] = [ '"&B$2&"'=>"""&B28&""", '"&D$2&"'=>"""&CLEAN(SUBSTITUTE(D28,"""","'"))&""", '"&L$2&"'=>"""&L28&""", '"&S$2&"'=>"""&CLEAN(SUBSTITUTE(S28,"""","'"))&"""];" -> $defMeasures['mCKdishWasher'] = [ 'mid'=>"118", 'title'=>"食器洗い乾燥機を使う", 'figNum'=>"15", 'advice'=>"食器をお湯で流し洗いするのに比べると、お湯をためて洗浄しているため、食器洗浄乾燥機のほうが省エネとなります。なおお湯ではなく水で洗う場合には、食器洗浄機よりも省エネとなります。手洗いで工夫するのも有効な方法です。"]; | AD28: 食器洗いは家事の敵だと言われています。横着をしながら、環境負荷を下げられるのが、この食器洗い乾燥機です。ただ工夫して、水で食器を洗っている方の場合には、手洗いのほうが負荷が小さくなります。がんばるか、がんばらないか、ご自由に選んでください。
B29: 119 | C29: mHWtap | D29: 台所・洗面所に節湯水栓を設置する | E29: 台所・洗面所に節湯水栓を設置する | F29: consHWsum | G29: 節湯水栓 | H29: 節湯水栓 | I29: 2 | J29: 2 | L29: 13 | M29: 20 | S29: 手元ですぐ止められるようにしたり、シングルレバーを左に向けないとお湯がでないしくみにするなど、使い勝手は同じでも、お湯の消費量を2割以上減らせる機器があります。 | T29: 手元ですぐ止められるようにしたり、シングルレバーを左に向けないとお湯がでないしくみにするなど、使い勝手は同じでも、お湯の消費量を2割以上減らせる機器があります。 | V29: wss | Z29: ="D6.scenario.defMeasures['"&C29&"'] = { "&B$2&":"""&B29&""", "&C$2&":"""&C29&""", "&D$2&":"""&CLEAN(SUBSTITUTE(D29,"""","'"))&""", "&I$2&":"""&I29&""", "&F$2&":"""&F29&""", "&G$2&":"""&CLEAN(SUBSTITUTE(G29,"""","'"))&""", "&K$2&":"""&K29&""", "&L$2&":"""&L29&""", "&M$2&":"""&M29&""", "&N$2&":"""&N29&""", "&O$2&":"""&O29&""", "&P$2&":"""&P29&""", "&Q$2&":"""&Q29&""", "&S$2&":"""&CLEAN(SUBSTITUTE(S29,"""","'"))&""", "&U$2&":"""&U29&""", "&V$2&":"""&V29&"""};" -> D6.scenario.defMeasures['mHWtap'] = { mid:"119", name:"mHWtap", title:"台所・洗面所に節湯水栓を設置する", easyness:"2", refCons:"consHWsum", titleShort:"節湯水栓", level:"", figNum:"13", lifeTime:"20", price:"", roanShow:"", standardType:"", subsidy :"", advice:"手元ですぐ止められるようにしたり、シングルレバーを左に向けないとお湯がでないしくみにするなど、使い勝手は同じでも、お湯の消費量を2割以上減らせる機器があります。", lifestyle:"", season:"wss"}; | AB29: ="$defMeasures['"&C29&"'] = [ '"&B$2&"'=>"""&B29&""", '"&D$2&"'=>"""&CLEAN(SUBSTITUTE(D29,"""","'"))&""", '"&L$2&"'=>"""&L29&""", '"&S$2&"'=>"""&CLEAN(SUBSTITUTE(S29,"""","'"))&"""];" -> $defMeasures['mHWtap'] = [ 'mid'=>"119", 'title'=>"台所・洗面所に節湯水栓を設置する", 'figNum'=>"13", 'advice'=>"手元ですぐ止められるようにしたり、シングルレバーを左に向けないとお湯がでないしくみにするなど、使い勝手は同じでも、お湯の消費量を2割以上減らせる機器があります。"]; | AD29: 節水シャワーヘッドと並んで、画期的な器具です。量を測ってみると、いかにそれまでが無駄にお湯を使っていたのかがわかります。
B30: 120 | C30: mHWreplaceToilet5 | D30: 節水トイレを設置する | E30: 節水トイレを設置する | F30: consHWtoilet | G30: 節水トイレ | H30: 節水トイレ | I30: 1 | J30: 1 | L30: 19 | M30: 10 | N30: 200000 | P30: 既存型 | Q30: 子育てグリーン住宅支援事業の対象で、他の断熱工事や機器導入を行って補助額が5万円以上になると補助されます。 | S30: トイレ本体を工事して交換する必要がありますが、水の量を以前よりも半分以下に抑えることができます。以前は13リットル程度必要だったものが、4-6リットル程度で使えるようになっており、水道代を大きく削減できます。 | T30: トイレ本体を工事して交換する必要がありますが、水の量を以前よりも半分以下に抑えることができます。以前は13リットル程度必要だったものが、4-6リットル程度で使えるようになっており、水道代を大きく削減できます。 | V30: wss | Z30: ="D6.scenario.defMeasures['"&C30&"'] = { "&B$2&":"""&B30&""", "&C$2&":"""&C30&""", "&D$2&":"""&CLEAN(SUBSTITUTE(D30,"""","'"))&""", "&I$2&":"""&I30&""", "&F$2&":"""&F30&""", "&G$2&":"""&CLEAN(SUBSTITUTE(G30,"""","'"))&""", "&K$2&":"""&K30&""", "&L$2&":"""&L30&""", "&M$2&":"""&M30&""", "&N$2&":"""&N30&""", "&O$2&":"""&O30&""", "&P$2&":"""&P30&""", "&Q$2&":"""&Q30&""", "&S$2&":"""&CLEAN(SUBSTITUTE(S30,"""","'"))&""", "&U$2&":"""&U30&""", "&V$2&":"""&V30&"""};" -> D6.scenario.defMeasures['mHWreplaceToilet5'] = { mid:"120", name:"mHWreplaceToilet5", title:"節水トイレを設置する", easyness:"1", refCons:"consHWtoilet", titleShort:"節水トイレ", level:"", figNum:"19", lifeTime:"10", price:"200000", roanShow:"", standardType:"既存型", subsidy :"子育てグリーン住宅支援事業の対象で、他の断熱工事や機器導入を行って補助額が5万円以上になると補助されます。", advice:"トイレ本体を工事して交換する必要がありますが、水の量を以前よりも半分以下に抑えることができます。以前は13リットル程度必要だったものが、4-6リットル程度で使えるようになっており、水道代を大きく削減できます。", lifestyle:"", season:"wss"}; | AB30: ="$defMeasures['"&C30&"'] = [ '"&B$2&"'=>"""&B30&""", '"&D$2&"'=>"""&CLEAN(SUBSTITUTE(D30,"""","'"))&""", '"&L$2&"'=>"""&L30&""", '"&S$2&"'=>"""&CLEAN(SUBSTITUTE(S30,"""","'"))&"""];" -> $defMeasures['mHWreplaceToilet5'] = [ 'mid'=>"120", 'title'=>"節水トイレを設置する", 'figNum'=>"19", 'advice'=>"トイレ本体を工事して交換する必要がありますが、水の量を以前よりも半分以下に抑えることができます。以前は13リットル程度必要だったものが、4-6リットル程度で使えるようになっており、水道代を大きく削減できます。"]; | AD30: 目立たないものの、毎日確実にお世話になる部分です。水に流すだけの話ですが、回転やひねりをかけたり、見事に工夫がされています。コンピュータを使った「スマート」とは違いますが、職人技のような研ぎ澄まされた美しさがあります。
B31: 121 | C31: mHWreplaceToilet | D31: 瞬間式の温水洗浄便座に買い替える | E31: 瞬間式の温水洗浄便座に買い替える | F31: consHWtoilet | G31: 瞬間式便座 | H31: 瞬間式便座 | I31: 1 | J31: 1 | L31: 19 | M31: 10 | N31: 30000 | P31: 既存型 | S31: 新製品では省エネ機能があり、ふたを開けた瞬間に温めるタイプなど、消費電力が少なくてすみます。カタログに表示されている年間消費電力量を参考に省エネ型を選んでください。 | T31: 新製品では省エネ機能があり、ふたを開けた瞬間に温めるタイプなど、消費電力が少なくてすみます。カタログに表示されている年間消費電力量を参考に省エネ型を選んでください。 | V31: wss | Z31: ="D6.scenario.defMeasures['"&C31&"'] = { "&B$2&":"""&B31&""", "&C$2&":"""&C31&""", "&D$2&":"""&CLEAN(SUBSTITUTE(D31,"""","'"))&""", "&I$2&":"""&I31&""", "&F$2&":"""&F31&""", "&G$2&":"""&CLEAN(SUBSTITUTE(G31,"""","'"))&""", "&K$2&":"""&K31&""", "&L$2&":"""&L31&""", "&M$2&":"""&M31&""", "&N$2&":"""&N31&""", "&O$2&":"""&O31&""", "&P$2&":"""&P31&""", "&Q$2&":"""&Q31&""", "&S$2&":"""&CLEAN(SUBSTITUTE(S31,"""","'"))&""", "&U$2&":"""&U31&""", "&V$2&":"""&V31&"""};" -> D6.scenario.defMeasures['mHWreplaceToilet'] = { mid:"121", name:"mHWreplaceToilet", title:"瞬間式の温水洗浄便座に買い替える", easyness:"1", refCons:"consHWtoilet", titleShort:"瞬間式便座", level:"", figNum:"19", lifeTime:"10", price:"30000", roanShow:"", standardType:"既存型", subsidy :"", advice:"新製品では省エネ機能があり、ふたを開けた瞬間に温めるタイプなど、消費電力が少なくてすみます。カタログに表示されている年間消費電力量を参考に省エネ型を選んでください。", lifestyle:"", season:"wss"}; | AB31: ="$defMeasures['"&C31&"'] = [ '"&B$2&"'=>"""&B31&""", '"&D$2&"'=>"""&CLEAN(SUBSTITUTE(D31,"""","'"))&""", '"&L$2&"'=>"""&L31&""", '"&S$2&"'=>"""&CLEAN(SUBSTITUTE(S31,"""","'"))&"""];" -> $defMeasures['mHWreplaceToilet'] = [ 'mid'=>"121", 'title'=>"瞬間式の温水洗浄便座に買い替える", 'figNum'=>"19", 'advice'=>"新製品では省エネ機能があり、ふたを開けた瞬間に温めるタイプなど、消費電力が少なくてすみます。カタログに表示されている年間消費電力量を参考に省エネ型を選んでください。"]; | AD31: シャワーのお湯と違って少量なので、使うときに加温をしても間に合います。便座も同様に、人がトイレに入るのを関知してから、温めるものもあります。トイレはやはり、がんばらずにもすぐに楽に、というのがいいですね。
B32: 122 | C32: mHWtemplatureToilet | D32: 保温便座の温度設定を下げる | E32: 保温便座の温度設定を下げる | F32: consHWtoilet | G32: 便座温度調節 | H32: 便座温度調節 | I32: 3 | J32: 3 | L32: 19 | S32: 寒くない時期は保温を切ったり、温度設定を低めに設定することで省エネができます。便座にカバーをかけると、冷たさを感じにくくなります。 | T32: 寒くない時期は保温を切ったり、温度設定を低めに設定することで省エネができます。便座にカバーをかけると、冷たさを感じにくくなります。 | U32: 1 | V32: wss | Z32: ="D6.scenario.defMeasures['"&C32&"'] = { "&B$2&":"""&B32&""", "&C$2&":"""&C32&""", "&D$2&":"""&CLEAN(SUBSTITUTE(D32,"""","'"))&""", "&I$2&":"""&I32&""", "&F$2&":"""&F32&""", "&G$2&":"""&CLEAN(SUBSTITUTE(G32,"""","'"))&""", "&K$2&":"""&K32&""", "&L$2&":"""&L32&""", "&M$2&":"""&M32&""", "&N$2&":"""&N32&""", "&O$2&":"""&O32&""", "&P$2&":"""&P32&""", "&Q$2&":"""&Q32&""", "&S$2&":"""&CLEAN(SUBSTITUTE(S32,"""","'"))&""", "&U$2&":"""&U32&""", "&V$2&":"""&V32&"""};" -> D6.scenario.defMeasures['mHWtemplatureToilet'] = { mid:"122", name:"mHWtemplatureToilet", title:"保温便座の温度設定を下げる", easyness:"3", refCons:"consHWtoilet", titleShort:"便座温度調節", level:"", figNum:"19", lifeTime:"", price:"", roanShow:"", standardType:"", subsidy :"", advice:"寒くない時期は保温を切ったり、温度設定を低めに設定することで省エネができます。便座にカバーをかけると、冷たさを感じにくくなります。", lifestyle:"1", season:"wss"}; | AB32: ="$defMeasures['"&C32&"'] = [ '"&B$2&"'=>"""&B32&""", '"&D$2&"'=>"""&CLEAN(SUBSTITUTE(D32,"""","'"))&""", '"&L$2&"'=>"""&L32&""", '"&S$2&"'=>"""&CLEAN(SUBSTITUTE(S32,"""","'"))&"""];" -> $defMeasures['mHWtemplatureToilet'] = [ 'mid'=>"122", 'title'=>"保温便座の温度設定を下げる", 'figNum'=>"19", 'advice'=>"寒くない時期は保温を切ったり、温度設定を低めに設定することで省エネができます。便座にカバーをかけると、冷たさを感じにくくなります。"]; | AD32: せめて夏は止めておきましょう。そこまでして、がまんをしなくてもいいと思います。
B33: 123 | C33: mHWcoverTilet | D33: 保温洗浄便座のふたをしめる | E33: 保温洗浄便座のふたをしめる | F33: consHWtoilet | G33: 便座のふたを閉める | H33: 便座のふたを閉める | I33: 3 | J33: 3 | L33: 19 | S33: 便座のふたを上げた状態にしておくと、保温の熱が逃げやすく、消費電力が増えます。用を終えたら、ふたを閉めることで省エネになります。寒くなければ、保温をしないようにすることも省エネにつながります。 | T33: 便座のふたを上げた状態にしておくと、保温の熱が逃げやすく、消費電力が増えます。用を終えたら、ふたを閉めることで省エネになります。寒くなければ、保温をしないようにすることも省エネにつながります。 | U33: 1 | V33: wss | Z33: ="D6.scenario.defMeasures['"&C33&"'] = { "&B$2&":"""&B33&""", "&C$2&":"""&C33&""", "&D$2&":"""&CLEAN(SUBSTITUTE(D33,"""","'"))&""", "&I$2&":"""&I33&""", "&F$2&":"""&F33&""", "&G$2&":"""&CLEAN(SUBSTITUTE(G33,"""","'"))&""", "&K$2&":"""&K33&""", "&L$2&":"""&L33&""", "&M$2&":"""&M33&""", "&N$2&":"""&N33&""", "&O$2&":"""&O33&""", "&P$2&":"""&P33&""", "&Q$2&":"""&Q33&""", "&S$2&":"""&CLEAN(SUBSTITUTE(S33,"""","'"))&""", "&U$2&":"""&U33&""", "&V$2&":"""&V33&"""};" -> D6.scenario.defMeasures['mHWcoverTilet'] = { mid:"123", name:"mHWcoverTilet", title:"保温洗浄便座のふたをしめる", easyness:"3", refCons:"consHWtoilet", titleShort:"便座のふたを閉める", level:"", figNum:"19", lifeTime:"", price:"", roanShow:"", standardType:"", subsidy :"", advice:"便座のふたを上げた状態にしておくと、保温の熱が逃げやすく、消費電力が増えます。用を終えたら、ふたを閉めることで省エネになります。寒くなければ、保温をしないようにすることも省エネにつながります。", lifestyle:"1", season:"wss"}; | AB33: ="$defMeasures['"&C33&"'] = [ '"&B$2&"'=>"""&B33&""", '"&D$2&"'=>"""&CLEAN(SUBSTITUTE(D33,"""","'"))&""", '"&L$2&"'=>"""&L33&""", '"&S$2&"'=>"""&CLEAN(SUBSTITUTE(S33,"""","'"))&"""];" -> $defMeasures['mHWcoverTilet'] = [ 'mid'=>"123", 'title'=>"保温洗浄便座のふたをしめる", 'figNum'=>"19", 'advice'=>"便座のふたを上げた状態にしておくと、保温の熱が逃げやすく、消費電力が増えます。用を終えたら、ふたを閉めることで省エネになります。寒くなければ、保温をしないようにすることも省エネにつながります。"]; | AD33: かしこいもので、ふたが自動的に開くものもあります。<br> ただこうしたトイレのセンサーがあまり信用しきれていないようで、なぜかと言えば、大きい方でこもっているときに、照明が自動的に消えてしまって、あわてて手をふったりしないといけなかったという悲しい体験をお持ちの方が多いからのようです。
B34: 201 | C34: mACreplace | D34: エアコンを省エネ型に買い替える | E34: エアコンを省エネ型に買い替える | F34: consAC | G34: 省エネエアコン | H34: 省エネエアコン | I34: 1 | J34: 1 | L34: 1 | M34: 10 | N34: 160000 | S34: 同じだけ冷暖房をしても、省エネ性能の高いエアコンなら光熱費が安くなります。選ぶ時には、統一省エネラベルの★マークの数が多いものや、年間電気代の表示を参考に省エネ型を選んでください。暖房の性能もあがっており、ガスや灯油の暖房に比べてもCO2を削減することができます。 | T34: 同じだけ冷暖房をしても、30年前に比べると半分くらいの消費電力ですむ省エネ性能の高いエアコンがあります。選ぶ時には、統一省エネラベルの★マークの数が多いものや、年間電気代の表示を参考に省エネ型を選んでください。暖房の性能もあがっており、ガスや灯油の暖房に比べてもCO2を削減することができます。 | V34: wss | Z34: ="D6.scenario.defMeasures['"&C34&"'] = { "&B$2&":"""&B34&""", "&C$2&":"""&C34&""", "&D$2&":"""&CLEAN(SUBSTITUTE(D34,"""","'"))&""", "&I$2&":"""&I34&""", "&F$2&":"""&F34&""", "&G$2&":"""&CLEAN(SUBSTITUTE(G34,"""","'"))&""", "&K$2&":"""&K34&""", "&L$2&":"""&L34&""", "&M$2&":"""&M34&""", "&N$2&":"""&N34&""", "&O$2&":"""&O34&""", "&P$2&":"""&P34&""", "&Q$2&":"""&Q34&""", "&S$2&":"""&CLEAN(SUBSTITUTE(S34,"""","'"))&""", "&U$2&":"""&U34&""", "&V$2&":"""&V34&"""};" -> D6.scenario.defMeasures['mACreplace'] = { mid:"201", name:"mACreplace", title:"エアコンを省エネ型に買い替える", easyness:"1", refCons:"consAC", titleShort:"省エネエアコン", level:"", figNum:"1", lifeTime:"10", price:"160000", roanShow:"", standardType:"", subsidy :"", advice:"同じだけ冷暖房をしても、省エネ性能の高いエアコンなら光熱費が安くなります。選ぶ時には、統一省エネラベルの★マークの数が多いものや、年間電気代の表示を参考に省エネ型を選んでください。暖房の性能もあがっており、ガスや灯油の暖房に比べてもCO2を削減することができます。", lifestyle:"", season:"wss"}; | AB34: ="$defMeasures['"&C34&"'] = [ '"&B$2&"'=>"""&B34&""", '"&D$2&"'=>"""&CLEAN(SUBSTITUTE(D34,"""","'"))&""", '"&L$2&"'=>"""&L34&""", '"&S$2&"'=>"""&CLEAN(SUBSTITUTE(S34,"""","'"))&"""];" -> $defMeasures['mACreplace'] = [ 'mid'=>"201", 'title'=>"エアコンを省エネ型に買い替える", 'figNum'=>"1", 'advice'=>"同じだけ冷暖房をしても、省エネ性能の高いエアコンなら光熱費が安くなります。選ぶ時には、統一省エネラベルの★マークの数が多いものや、年間電気代の表示を参考に省エネ型を選んでください。暖房の性能もあがっており、ガスや灯油の暖房に比べてもCO2を削減することができます。"]; | AD34: 熱力学の法則上、現在以上に省エネのエアコンは作れないので、これから買うのなら、丈夫で長持ちするものがいいかもしれません。<br> ちなみに余計な機能は不要かもしれません。お掃除ロボットは、電気ばかり消費しながら、結果的に、時々手作業での掃除も必要となるようです。
B35: 202 | C35: mACreplaceHeat | D35: エアコンを省エネ型に買い替え、エアコンで暖房する | E35: エアコンを省エネ型に買い替え、エアコンで暖房する | F35: consAC | G35: 省エネエアコン＋暖房 | H35: 省エネエアコン＋暖房 | I35: 2 | J35: 2 | L35: 1 | M35: 10 | N35: 160000 | S35: 同じだけ冷暖房をしても、省エネ性能の高いエアコンなら光熱費が安くなります。エアコンは室外の熱を利用するために、ガスや灯油などの暖房とくらべても、CO2排出量が少なくなります。選ぶ時には、統一省エネラベルの★マークの数が多いものや、年間電気代の表示を参考に省エネ型を選んでください。また、エアコンで暖房をすると、外気の熱を利用するため、ガスや灯油の暖房に比べて大幅にCO2を削減でき、光熱費の削減にもつながります。 | T35: 同じだけ冷暖房をして、30年前に比べると半分くらいの消費電力ですむ省エネ性能の高いエアコンがあります。エアコンは室外の熱を利用するために、ガスや灯油などの暖房とくらべても、CO2排出量が少なくなります。選ぶ時には、統一省エネラベルの★マークの数が多いものや、年間電気代の表示を参考に省エネ型を選んでください。 | V35: wss | Z35: ="D6.scenario.defMeasures['"&C35&"'] = { "&B$2&":"""&B35&""", "&C$2&":"""&C35&""", "&D$2&":"""&CLEAN(SUBSTITUTE(D35,"""","'"))&""", "&I$2&":"""&I35&""", "&F$2&":"""&F35&""", "&G$2&":"""&CLEAN(SUBSTITUTE(G35,"""","'"))&""", "&K$2&":"""&K35&""", "&L$2&":"""&L35&""", "&M$2&":"""&M35&""", "&N$2&":"""&N35&""", "&O$2&":"""&O35&""", "&P$2&":"""&P35&""", "&Q$2&":"""&Q35&""", "&S$2&":"""&CLEAN(SUBSTITUTE(S35,"""","'"))&""", "&U$2&":"""&U35&""", "&V$2&":"""&V35&"""};" -> D6.scenario.defMeasures['mACreplaceHeat'] = { mid:"202", name:"mACreplaceHeat", title:"エアコンを省エネ型に買い替え、エアコンで暖房する", easyness:"2", refCons:"consAC", titleShort:"省エネエアコン＋暖房", level:"", figNum:"1", lifeTime:"10", price:"160000", roanShow:"", standardType:"", subsidy :"", advice:"同じだけ冷暖房をしても、省エネ性能の高いエアコンなら光熱費が安くなります。エアコンは室外の熱を利用するために、ガスや灯油などの暖房とくらべても、CO2排出量が少なくなります。選ぶ時には、統一省エネラベルの★マークの数が多いものや、年間電気代の表示を参考に省エネ型を選んでください。また、エアコンで暖房をすると、外気の熱を利用するため、ガスや灯油の暖房に比べて大幅にCO2を削減でき、光熱費の削減にもつながります。", lifestyle:"", season:"wss"}; | AB35: ="$defMeasures['"&C35&"'] = [ '"&B$2&"'=>"""&B35&""", '"&D$2&"'=>"""&CLEAN(SUBSTITUTE(D35,"""","'"))&""", '"&L$2&"'=>"""&L35&""", '"&S$2&"'=>"""&CLEAN(SUBSTITUTE(S35,"""","'"))&"""];" -> $defMeasures['mACreplaceHeat'] = [ 'mid'=>"202", 'title'=>"エアコンを省エネ型に買い替え、エアコンで暖房する", 'figNum'=>"1", 'advice'=>"同じだけ冷暖房をしても、省エネ性能の高いエアコンなら光熱費が安くなります。エアコンは室外の熱を利用するために、ガスや灯油などの暖房とくらべても、CO2排出量が少なくなります。選ぶ時には、統一省エネラベルの★マークの数が多いものや、年間電気代の表示を参考に省エネ型を選んでください。また、エアコンで暖房をすると、外気の熱を利用するため、ガスや灯油の暖房に比べて大幅にCO2を削減でき、光熱費の削減にもつながります。"]; | AD35: ガスや灯油のストーブのように、部屋の中で燃やすのは、室内空気汚染の観点から、世界的に規制されつつあります。また燃やすと水蒸気が発生し、窓や壁に結露を生じる原因にもなります。<br> エアコンは暖房っぽくないですが、「寒くないようにする」という点からは、省エネ性能も高いですし、理想的な暖房です。
B36: 203 | C36: mACchangeHeat | D36: 暖房をエアコンでする | E36: 暖房をエアコンでする | F36: consACheat | G36: エアコン暖房 | H36: エアコン暖房 | I36: 2 | J36: 2 | L36: 1 | S36: エアコンで暖房をすると、外気の熱を利用するため、ガスや灯油の暖房に比べて大幅にCO2を削減でき、光熱費の削減にもつながります。なお、暖かい空気は軽いために天井に集まりやすく、床までしっかり届くよう、強風の設定で運転したり、うちわなどを活用したりしてください。また、最近のエアコンは床まで暖める機能が充実しています。 | T36: エアコンで暖房をすると、外気の熱を利用するため、ガスや灯油の暖房に比べて大幅にCO2を削減でき、光熱費の削減にもつながります。なお、暖かい空気は軽いために天井に集まりやすく、床までしっかり届くよう、強風の設定で運転したり、うちわなどを活用したりしてください。また、最近のエアコンは床まで暖める機能が充実しています。 | U36: 1 | V36: wss | Z36: ="D6.scenario.defMeasures['"&C36&"'] = { "&B$2&":"""&B36&""", "&C$2&":"""&C36&""", "&D$2&":"""&CLEAN(SUBSTITUTE(D36,"""","'"))&""", "&I$2&":"""&I36&""", "&F$2&":"""&F36&""", "&G$2&":"""&CLEAN(SUBSTITUTE(G36,"""","'"))&""", "&K$2&":"""&K36&""", "&L$2&":"""&L36&""", "&M$2&":"""&M36&""", "&N$2&":"""&N36&""", "&O$2&":"""&O36&""", "&P$2&":"""&P36&""", "&Q$2&":"""&Q36&""", "&S$2&":"""&CLEAN(SUBSTITUTE(S36,"""","'"))&""", "&U$2&":"""&U36&""", "&V$2&":"""&V36&"""};" -> D6.scenario.defMeasures['mACchangeHeat'] = { mid:"203", name:"mACchangeHeat", title:"暖房をエアコンでする", easyness:"2", refCons:"consACheat", titleShort:"エアコン暖房", level:"", figNum:"1", lifeTime:"", price:"", roanShow:"", standardType:"", subsidy :"", advice:"エアコンで暖房をすると、外気の熱を利用するため、ガスや灯油の暖房に比べて大幅にCO2を削減でき、光熱費の削減にもつながります。なお、暖かい空気は軽いために天井に集まりやすく、床までしっかり届くよう、強風の設定で運転したり、うちわなどを活用したりしてください。また、最近のエアコンは床まで暖める機能が充実しています。", lifestyle:"1", season:"wss"}; | AB36: ="$defMeasures['"&C36&"'] = [ '"&B$2&"'=>"""&B36&""", '"&D$2&"'=>"""&CLEAN(SUBSTITUTE(D36,"""","'"))&""", '"&L$2&"'=>"""&L36&""", '"&S$2&"'=>"""&CLEAN(SUBSTITUTE(S36,"""","'"))&"""];" -> $defMeasures['mACchangeHeat'] = [ 'mid'=>"203", 'title'=>"暖房をエアコンでする", 'figNum'=>"1", 'advice'=>"エアコンで暖房をすると、外気の熱を利用するため、ガスや灯油の暖房に比べて大幅にCO2を削減でき、光熱費の削減にもつながります。なお、暖かい空気は軽いために天井に集まりやすく、床までしっかり届くよう、強風の設定で運転したり、うちわなどを活用したりしてください。また、最近のエアコンは床まで暖める機能が充実しています。"]; | AD36: ガスや灯油のストーブのように、部屋の中で燃やすのは、室内空気汚染の観点から、世界的に規制されつつあります。また燃やすと水蒸気が発生し、窓や壁に結露を生じる原因にもなります。<br> エアコンは暖房っぽくないですが、「寒くないようにする」という点からは、省エネ性能も高いですし、理想的な暖房です。
B37: 204 | C37: mHTchangeHeat | D37: 家の暖房をエアコンでする | E37: 家の暖房をエアコンでする | F37: consHTsum | G37: エアコン暖房 | H37: エアコン暖房 | I37: 1 | J37: 1 | L37: 1 | S37: エアコンで暖房をすると、外気の熱を利用するため、ガスや灯油の暖房に比べて大幅にCO2を削減でき、光熱費の削減にもつながります。なお、暖かい空気は軽いために天井に集まりやすく、床までしっかり届くよう、強風の設定で運転したり、うちわなどを活用したりしてください。また、最近のエアコンは床まで暖める機能が充実しています。 | T37: エアコンで暖房をすると、外気の熱を利用するため、ガスや灯油の暖房に比べて大幅にCO2を削減でき、光熱費の削減にもつながります。なお、暖かい空気は軽いために天井に集まりやすく、床までしっかり届くよう、強風の設定で運転したり、うちわなどを活用したりしてください。また、最近のエアコンは床まで暖める機能が充実しています。 | U37: 1 | V37: wss | Z37: ="D6.scenario.defMeasures['"&C37&"'] = { "&B$2&":"""&B37&""", "&C$2&":"""&C37&""", "&D$2&":"""&CLEAN(SUBSTITUTE(D37,"""","'"))&""", "&I$2&":"""&I37&""", "&F$2&":"""&F37&""", "&G$2&":"""&CLEAN(SUBSTITUTE(G37,"""","'"))&""", "&K$2&":"""&K37&""", "&L$2&":"""&L37&""", "&M$2&":"""&M37&""", "&N$2&":"""&N37&""", "&O$2&":"""&O37&""", "&P$2&":"""&P37&""", "&Q$2&":"""&Q37&""", "&S$2&":"""&CLEAN(SUBSTITUTE(S37,"""","'"))&""", "&U$2&":"""&U37&""", "&V$2&":"""&V37&"""};" -> D6.scenario.defMeasures['mHTchangeHeat'] = { mid:"204", name:"mHTchangeHeat", title:"家の暖房をエアコンでする", easyness:"1", refCons:"consHTsum", titleShort:"エアコン暖房", level:"", figNum:"1", lifeTime:"", price:"", roanShow:"", standardType:"", subsidy :"", advice:"エアコンで暖房をすると、外気の熱を利用するため、ガスや灯油の暖房に比べて大幅にCO2を削減でき、光熱費の削減にもつながります。なお、暖かい空気は軽いために天井に集まりやすく、床までしっかり届くよう、強風の設定で運転したり、うちわなどを活用したりしてください。また、最近のエアコンは床まで暖める機能が充実しています。", lifestyle:"1", season:"wss"}; | AB37: ="$defMeasures['"&C37&"'] = [ '"&B$2&"'=>"""&B37&""", '"&D$2&"'=>"""&CLEAN(SUBSTITUTE(D37,"""","'"))&""", '"&L$2&"'=>"""&L37&""", '"&S$2&"'=>"""&CLEAN(SUBSTITUTE(S37,"""","'"))&"""];" -> $defMeasures['mHTchangeHeat'] = [ 'mid'=>"204", 'title'=>"家の暖房をエアコンでする", 'figNum'=>"1", 'advice'=>"エアコンで暖房をすると、外気の熱を利用するため、ガスや灯油の暖房に比べて大幅にCO2を削減でき、光熱費の削減にもつながります。なお、暖かい空気は軽いために天井に集まりやすく、床までしっかり届くよう、強風の設定で運転したり、うちわなどを活用したりしてください。また、最近のエアコンは床まで暖める機能が充実しています。"]; | AD37: エアコンでだんぼうをする
B38: 205 | C38: mCOsunCut | D38: 冷房で、すだれ等を使い日射をカットする | E38: 冷房で、すだれ等を使い日射をカットする | F38: consCOsum | G38: 冷房日射カット | H38: 冷房日射カット | I38: 4 | J38: 4 | L38: 1 | M38: 5 | S38: 冷房時に日射が入るのは、窓にストーブを置いているようなものです。日射を遮ると、省エネになり、部屋が涼しくなります。カーテンでも日射を防ぐことができますが、部屋の内側にあるカーテンが暖まり、部屋が暑くなってしまいます。このため、窓の外にすだれ・よしずをするほうが涼しくなります。また、5月頃から、ゴーヤ・朝顔・ヘチマなどを植えて育てると、夏にはりっぱな「緑のカーテン」ができあがり、日射を防いでくれます。 | T38: 冷房時に日射が入るのは、窓にストーブを置いているようなものです。日射を遮ると、省エネになり、部屋が涼しくなります。カーテンでも日射を防ぐことができますが、部屋の内側にあるカーテンが暖まり、部屋が暑くなってしまいます。このため、窓の外にすだれ・よしずをするほうが涼しくなります。また、5月頃から、ゴーヤ・朝顔・ヘチマなどを植えて育てると、夏にはりっぱな「緑のカーテン」ができあがり、日射を防いでくれます。 | U38: 1 | V38: wss | Z38: ="D6.scenario.defMeasures['"&C38&"'] = { "&B$2&":"""&B38&""", "&C$2&":"""&C38&""", "&D$2&":"""&CLEAN(SUBSTITUTE(D38,"""","'"))&""", "&I$2&":"""&I38&""", "&F$2&":"""&F38&""", "&G$2&":"""&CLEAN(SUBSTITUTE(G38,"""","'"))&""", "&K$2&":"""&K38&""", "&L$2&":"""&L38&""", "&M$2&":"""&M38&""", "&N$2&":"""&N38&""", "&O$2&":"""&O38&""", "&P$2&":"""&P38&""", "&Q$2&":"""&Q38&""", "&S$2&":"""&CLEAN(SUBSTITUTE(S38,"""","'"))&""", "&U$2&":"""&U38&""", "&V$2&":"""&V38&"""};" -> D6.scenario.defMeasures['mCOsunCut'] = { mid:"205", name:"mCOsunCut", title:"冷房で、すだれ等を使い日射をカットする", easyness:"4", refCons:"consCOsum", titleShort:"冷房日射カット", level:"", figNum:"1", lifeTime:"5", price:"", roanShow:"", standardType:"", subsidy :"", advice:"冷房時に日射が入るのは、窓にストーブを置いているようなものです。日射を遮ると、省エネになり、部屋が涼しくなります。カーテンでも日射を防ぐことができますが、部屋の内側にあるカーテンが暖まり、部屋が暑くなってしまいます。このため、窓の外にすだれ・よしずをするほうが涼しくなります。また、5月頃から、ゴーヤ・朝顔・ヘチマなどを植えて育てると、夏にはりっぱな「緑のカーテン」ができあがり、日射を防いでくれます。", lifestyle:"1", season:"wss"}; | AB38: ="$defMeasures['"&C38&"'] = [ '"&B$2&"'=>"""&B38&""", '"&D$2&"'=>"""&CLEAN(SUBSTITUTE(D38,"""","'"))&""", '"&L$2&"'=>"""&L38&""", '"&S$2&"'=>"""&CLEAN(SUBSTITUTE(S38,"""","'"))&"""];" -> $defMeasures['mCOsunCut'] = [ 'mid'=>"205", 'title'=>"冷房で、すだれ等を使い日射をカットする", 'figNum'=>"1", 'advice'=>"冷房時に日射が入るのは、窓にストーブを置いているようなものです。日射を遮ると、省エネになり、部屋が涼しくなります。カーテンでも日射を防ぐことができますが、部屋の内側にあるカーテンが暖まり、部屋が暑くなってしまいます。このため、窓の外にすだれ・よしずをするほうが涼しくなります。また、5月頃から、ゴーヤ・朝顔・ヘチマなどを植えて育てると、夏にはりっぱな「緑のカーテン」ができあがり、日射を防いでくれます。"]; | AD38: とにかく夏は日陰にして、窓から日光を入れないようにしましょう。夕方の西日だけでなく、朝日も忘れないように。5月に気がつい方は、ゴーヤやヘチマなどつる植物を植えるのがお勧めです。7月になって耐えられなくなった方は、急いですだれを買いにいきましょう。
B39: 206 | C39: mCOtemplature | D39: 冷房の温度設定を控えめ（28℃）にする | E39: 冷房の温度設定を控えめ（28℃）にする | F39: consACcool | G39: 冷房設定温度 | H39: 冷房設定温度 | I39: 3 | J39: 3 | L39: 1 | S39: 省エネを考えた冷房設定温度の目安は28℃以上です。「涼しく感じるようにする」のではなく、「暑すぎないようにする」程度に考えてみてください。暑さの感じ方には個人差があるので無理をする必要はありませんが、扇風機を活用したり、薄着をするなどして工夫をしてみてください。窓をあけて風が入ると涼しく感じますし、風鈴の音なども、涼しく感じさせてくれます。設定温度を1℃控えめにすることで、CO2排出量や光熱費をおよそ1割削減することができます。また季節の終わりには、早めに冷房器具を使わないようにすることも効果的です。 | T39: 省エネを考えた冷房設定温度の目安は28℃以上です。「涼しく感じるようにする」のではなく、「暑すぎないようにする」程度に考えてみてください。暑さの感じ方には個人差があるので無理をする必要はありませんが、扇風機を活用したり、薄着をするなどして工夫をしてみてください。窓をあけて風が入ると涼しく感じますし、風鈴の音なども、涼しく感じさせてくれます。設定温度を1℃控えめにすることで、CO2排出量や光熱費をおよそ1割削減することができます。また季節の終わりには、早めに冷房器具を使わないようにすることも効果的です。 | U39: 1 | V39: wss | Z39: ="D6.scenario.defMeasures['"&C39&"'] = { "&B$2&":"""&B39&""", "&C$2&":"""&C39&""", "&D$2&":"""&CLEAN(SUBSTITUTE(D39,"""","'"))&""", "&I$2&":"""&I39&""", "&F$2&":"""&F39&""", "&G$2&":"""&CLEAN(SUBSTITUTE(G39,"""","'"))&""", "&K$2&":"""&K39&""", "&L$2&":"""&L39&""", "&M$2&":"""&M39&""", "&N$2&":"""&N39&""", "&O$2&":"""&O39&""", "&P$2&":"""&P39&""", "&Q$2&":"""&Q39&""", "&S$2&":"""&CLEAN(SUBSTITUTE(S39,"""","'"))&""", "&U$2&":"""&U39&""", "&V$2&":"""&V39&"""};" -> D6.scenario.defMeasures['mCOtemplature'] = { mid:"206", name:"mCOtemplature", title:"冷房の温度設定を控えめ（28℃）にする", easyness:"3", refCons:"consACcool", titleShort:"冷房設定温度", level:"", figNum:"1", lifeTime:"", price:"", roanShow:"", standardType:"", subsidy :"", advice:"省エネを考えた冷房設定温度の目安は28℃以上です。「涼しく感じるようにする」のではなく、「暑すぎないようにする」程度に考えてみてください。暑さの感じ方には個人差があるので無理をする必要はありませんが、扇風機を活用したり、薄着をするなどして工夫をしてみてください。窓をあけて風が入ると涼しく感じますし、風鈴の音なども、涼しく感じさせてくれます。設定温度を1℃控えめにすることで、CO2排出量や光熱費をおよそ1割削減することができます。また季節の終わりには、早めに冷房器具を使わないようにすることも効果的です。", lifestyle:"1", season:"wss"}; | AB39: ="$defMeasures['"&C39&"'] = [ '"&B$2&"'=>"""&B39&""", '"&D$2&"'=>"""&CLEAN(SUBSTITUTE(D39,"""","'"))&""", '"&L$2&"'=>"""&L39&""", '"&S$2&"'=>"""&CLEAN(SUBSTITUTE(S39,"""","'"))&"""];" -> $defMeasures['mCOtemplature'] = [ 'mid'=>"206", 'title'=>"冷房の温度設定を控えめ（28℃）にする", 'figNum'=>"1", 'advice'=>"省エネを考えた冷房設定温度の目安は28℃以上です。「涼しく感じるようにする」のではなく、「暑すぎないようにする」程度に考えてみてください。暑さの感じ方には個人差があるので無理をする必要はありませんが、扇風機を活用したり、薄着をするなどして工夫をしてみてください。窓をあけて風が入ると涼しく感じますし、風鈴の音なども、涼しく感じさせてくれます。設定温度を1℃控えめにすることで、CO2排出量や光熱費をおよそ1割削減することができます。また季節の終わりには、早めに冷房器具を使わないようにすることも効果的です。"]; | AD39: 健康を維持できる温度ですので、それ以下はあきらめましょう。昼間に冷房をつけていると、いつの間にか外のほうが涼しくなっている場合がありますので、様子を気にしながら消しましょう。このタイミングの判断は、非常に高度な知恵と経験が必要となるため、まだコンピュータは太刀打ちできません。
B40: 207 | C40: mHTtemplature | D40: 厚着をして暖房の温度設定を控えめ（20℃）にする | E40: 厚着をして暖房の温度設定を控えめ（20℃）にする | F40: consACheat | G40: 暖房設定温度 | H40: 暖房設定温度 | I40: 3 | J40: 3 | L40: 3 | S40: 省エネを考えた暖房設定温度の目安は20℃以下です。「暖かく感じるようにする」のではなく「寒くないようにする」程度に考えてみてください。寒さの感じ方には個人差があるので無理をする必要はありませんが、厚着をしたり、暖まる食事をとるなどして、工夫をしてみてください。設定温度を1℃控えめにすることで、CO2排出量や光熱費をおよそ1割削減することができます。また季節の終わりには、早めに冷暖房器具を使うのを止めることも効果的です。 | T40: 省エネを考えた暖房設定温度の目安は20℃以下です。「暖かく感じるようにする」のではなく「寒くないようにする」程度に考えてみてください。寒さの感じ方には個人差があるので無理をする必要はありませんが、厚着をしたり、暖まる食事をとるなどして、工夫をしてみてください。設定温度を1℃控えめにすることで、CO2排出量や光熱費をおよそ1割削減することができます。また季節の終わりには、早めに冷暖房器具を使うのを止めることも効果的です。 | U40: 1 | V40: wss | Z40: ="D6.scenario.defMeasures['"&C40&"'] = { "&B$2&":"""&B40&""", "&C$2&":"""&C40&""", "&D$2&":"""&CLEAN(SUBSTITUTE(D40,"""","'"))&""", "&I$2&":"""&I40&""", "&F$2&":"""&F40&""", "&G$2&":"""&CLEAN(SUBSTITUTE(G40,"""","'"))&""", "&K$2&":"""&K40&""", "&L$2&":"""&L40&""", "&M$2&":"""&M40&""", "&N$2&":"""&N40&""", "&O$2&":"""&O40&""", "&P$2&":"""&P40&""", "&Q$2&":"""&Q40&""", "&S$2&":"""&CLEAN(SUBSTITUTE(S40,"""","'"))&""", "&U$2&":"""&U40&""", "&V$2&":"""&V40&"""};" -> D6.scenario.defMeasures['mHTtemplature'] = { mid:"207", name:"mHTtemplature", title:"厚着をして暖房の温度設定を控えめ（20℃）にする", easyness:"3", refCons:"consACheat", titleShort:"暖房設定温度", level:"", figNum:"3", lifeTime:"", price:"", roanShow:"", standardType:"", subsidy :"", advice:"省エネを考えた暖房設定温度の目安は20℃以下です。「暖かく感じるようにする」のではなく「寒くないようにする」程度に考えてみてください。寒さの感じ方には個人差があるので無理をする必要はありませんが、厚着をしたり、暖まる食事をとるなどして、工夫をしてみてください。設定温度を1℃控えめにすることで、CO2排出量や光熱費をおよそ1割削減することができます。また季節の終わりには、早めに冷暖房器具を使うのを止めることも効果的です。", lifestyle:"1", season:"wss"}; | AB40: ="$defMeasures['"&C40&"'] = [ '"&B$2&"'=>"""&B40&""", '"&D$2&"'=>"""&CLEAN(SUBSTITUTE(D40,"""","'"))&""", '"&L$2&"'=>"""&L40&""", '"&S$2&"'=>"""&CLEAN(SUBSTITUTE(S40,"""","'"))&"""];" -> $defMeasures['mHTtemplature'] = [ 'mid'=>"207", 'title'=>"厚着をして暖房の温度設定を控えめ（20℃）にする", 'figNum'=>"3", 'advice'=>"省エネを考えた暖房設定温度の目安は20℃以下です。「暖かく感じるようにする」のではなく「寒くないようにする」程度に考えてみてください。寒さの感じ方には個人差があるので無理をする必要はありませんが、厚着をしたり、暖まる食事をとるなどして、工夫をしてみてください。設定温度を1℃控えめにすることで、CO2排出量や光熱費をおよそ1割削減することができます。また季節の終わりには、早めに冷暖房器具を使うのを止めることも効果的です。"]; | AD40: 健康を維持できる温度ですので、それ以上はあきらめましょう。健康のためと言えば、厚着をするより、身体を動かして筋肉をつけておくほうが、暖かく過ごせます。特に、足先の冷え性など、血行をよくしておくよう気を配ってください。<br> 飲み物として、熱いお茶を保温水筒に入れて、こまめに飲むと、かぜもひきにくくなります。
B41: 208 | C41: mHTwindowSheet | D41: 暖房時に、窓用の断熱シートを貼る | E41: 暖房時に、窓用の断熱シートを貼る | F41: consACheat | G41: 窓断熱シート | H41: 窓断熱シート | I41: 3 | J41: 3 | L41: 4 | M41: 3 | N41: 3000 | S41: 窓用の断熱シート（いわゆるプチプチシートのようなエアクションタイプのもの）は、ホームセンター等で売られています。窓をきれいに拭いてから、霧吹きをかけ、その水だけで窓に貼り付けることができます。断熱効果があるだけでなく、結露も抑えることができます。窓から吹き下ろしてくる冷たい風も和らぎ、快適性も向上します。 | T41: 窓用の断熱シート（いわゆるプチプチシートのようなエアクションタイプのもの）は、ホームセンター等で売られています。窓をきれいに拭いてから、霧吹きをかけ、その水だけで窓に貼り付けることができます。断熱効果があるだけでなく、結露も抑えることができます。窓から吹き下ろしてくる冷たい風も和らぎ、快適性も向上します。 | V41: wss | Z41: ="D6.scenario.defMeasures['"&C41&"'] = { "&B$2&":"""&B41&""", "&C$2&":"""&C41&""", "&D$2&":"""&CLEAN(SUBSTITUTE(D41,"""","'"))&""", "&I$2&":"""&I41&""", "&F$2&":"""&F41&""", "&G$2&":"""&CLEAN(SUBSTITUTE(G41,"""","'"))&""", "&K$2&":"""&K41&""", "&L$2&":"""&L41&""", "&M$2&":"""&M41&""", "&N$2&":"""&N41&""", "&O$2&":"""&O41&""", "&P$2&":"""&P41&""", "&Q$2&":"""&Q41&""", "&S$2&":"""&CLEAN(SUBSTITUTE(S41,"""","'"))&""", "&U$2&":"""&U41&""", "&V$2&":"""&V41&"""};" -> D6.scenario.defMeasures['mHTwindowSheet'] = { mid:"208", name:"mHTwindowSheet", title:"暖房時に、窓用の断熱シートを貼る", easyness:"3", refCons:"consACheat", titleShort:"窓断熱シート", level:"", figNum:"4", lifeTime:"3", price:"3000", roanShow:"", standardType:"", subsidy :"", advice:"窓用の断熱シート（いわゆるプチプチシートのようなエアクションタイプのもの）は、ホームセンター等で売られています。窓をきれいに拭いてから、霧吹きをかけ、その水だけで窓に貼り付けることができます。断熱効果があるだけでなく、結露も抑えることができます。窓から吹き下ろしてくる冷たい風も和らぎ、快適性も向上します。", lifestyle:"", season:"wss"}; | AB41: ="$defMeasures['"&C41&"'] = [ '"&B$2&"'=>"""&B41&""", '"&D$2&"'=>"""&CLEAN(SUBSTITUTE(D41,"""","'"))&""", '"&L$2&"'=>"""&L41&""", '"&S$2&"'=>"""&CLEAN(SUBSTITUTE(S41,"""","'"))&"""];" -> $defMeasures['mHTwindowSheet'] = [ 'mid'=>"208", 'title'=>"暖房時に、窓用の断熱シートを貼る", 'figNum'=>"4", 'advice'=>"窓用の断熱シート（いわゆるプチプチシートのようなエアクションタイプのもの）は、ホームセンター等で売られています。窓をきれいに拭いてから、霧吹きをかけ、その水だけで窓に貼り付けることができます。断熱効果があるだけでなく、結露も抑えることができます。窓から吹き下ろしてくる冷たい風も和らぎ、快適性も向上します。"]; | AD41: プチプチシートですので、正直言って、見栄えはよくないです。でも、結露や吹き下ろす冷たい風が減り、一度やったらやめられなくなるでしょう。とは言っても、暖かくなったら外してくださいね。
B42: 209 | C42: mHTdouble | D42: 窓・サッシを複合素材枠二重ガラスにする | E42: 窓・サッシを複合素材枠二重ガラスにする | F42: consACheat | G42: 二重ガラス | H42: 二重ガラス | I42: 1 | J42: 1 | K42: 5 | L42: 4 | M42: 30 | N42: 150000 | Q42: 子育てグリーン住宅支援事業の対象で、他の断熱工事や機器導入を行って補助額が5万円以上になると補助されます。家の窓全体の断熱工事をする場合、工事にかかった費用に応じて、固定資産税の控除の制度があります。 | R42: 家の窓全体の断熱工事をする場合、工事にかかった費用に応じて、固定資産税の控除や、ローン残高に応じた所得税控除の制度があります。 | S42: 暖房時は窓やサッシから逃げる熱の割合が多く、通常のシングルガラスを複層ガラスに取り替えることで熱の逃げ方を半分程度に抑えることができます。省エネだけでなく、結露がつきにくくなるというメリットもあります。窓から吹き下ろしてくる冷たい風も和らぎ、快適性も向上します。家屋に応じた手法がありますので、工務店などに相談してください。 | T42: 暖房時は窓やサッシから逃げる熱の割合が多く、通常のシングルガラスを複層ガラスに取り替えることで熱の逃げ方を半分程度に抑えることができます。省エネだけでなく、結露がつきにくくなるというメリットもあります。窓から吹き下ろしてくる冷たい風も和らぎ、快適性も向上します。家屋に応じた手法がありますので、工務店などに相談してください。 | V42: wss | Z42: ="D6.scenario.defMeasures['"&C42&"'] = { "&B$2&":"""&B42&""", "&C$2&":"""&C42&""", "&D$2&":"""&CLEAN(SUBSTITUTE(D42,"""","'"))&""", "&I$2&":"""&I42&""", "&F$2&":"""&F42&""", "&G$2&":"""&CLEAN(SUBSTITUTE(G42,"""","'"))&""", "&K$2&":"""&K42&""", "&L$2&":"""&L42&""", "&M$2&":"""&M42&""", "&N$2&":"""&N42&""", "&O$2&":"""&O42&""", "&P$2&":"""&P42&""", "&Q$2&":"""&Q42&""", "&S$2&":"""&CLEAN(SUBSTITUTE(S42,"""","'"))&""", "&U$2&":"""&U42&""", "&V$2&":"""&V42&"""};" -> D6.scenario.defMeasures['mHTdouble'] = { mid:"209", name:"mHTdouble", title:"窓・サッシを複合素材枠二重ガラスにする", easyness:"1", refCons:"consACheat", titleShort:"二重ガラス", level:"5", figNum:"4", lifeTime:"30", price:"150000", roanShow:"", standardType:"", subsidy :"子育てグリーン住宅支援事業の対象で、他の断熱工事や機器導入を行って補助額が5万円以上になると補助されます。家の窓全体の断熱工事をする場合、工事にかかった費用に応じて、固定資産税の控除の制度があります。", advice:"暖房時は窓やサッシから逃げる熱の割合が多く、通常のシングルガラスを複層ガラスに取り替えることで熱の逃げ方を半分程度に抑えることができます。省エネだけでなく、結露がつきにくくなるというメリットもあります。窓から吹き下ろしてくる冷たい風も和らぎ、快適性も向上します。家屋に応じた手法がありますので、工務店などに相談してください。", lifestyle:"", season:"wss"}; | AB42: ="$defMeasures['"&C42&"'] = [ '"&B$2&"'=>"""&B42&""", '"&D$2&"'=>"""&CLEAN(SUBSTITUTE(D42,"""","'"))&""", '"&L$2&"'=>"""&L42&""", '"&S$2&"'=>"""&CLEAN(SUBSTITUTE(S42,"""","'"))&"""];" -> $defMeasures['mHTdouble'] = [ 'mid'=>"209", 'title'=>"窓・サッシを複合素材枠二重ガラスにする", 'figNum'=>"4", 'advice'=>"暖房時は窓やサッシから逃げる熱の割合が多く、通常のシングルガラスを複層ガラスに取り替えることで熱の逃げ方を半分程度に抑えることができます。省エネだけでなく、結露がつきにくくなるというメリットもあります。窓から吹き下ろしてくる冷たい風も和らぎ、快適性も向上します。家屋に応じた手法がありますので、工務店などに相談してください。"]; | AD42: 割れない限り、付替えの必要性も感じない「窓・サッシ」ですが、・・・確かに以前の学校と違って割れないですね。二重になっているだけで、こんなに暖かいのかと、感動します。けれども、2020年までには複層ガラスが当然となり、やがて、もっと上のレベルが「いいよねえ」と話題になる時代が来るでしょう。
B43: 210 | C43: mHTlowe | D43: 窓・サッシを樹脂枠low-Eガラスにする | E43: 窓・サッシを樹脂枠low-Eガラスにする | F43: consACheat | G43: 樹脂枠low-Eガラス | H43: 樹脂枠low-Eガラス | I43: 1 | J43: 1 | L43: 4 | M43: 30 | N43: 170000 | Q43: 子育てグリーン住宅支援事業の対象で、他の断熱工事や機器導入を行って補助額が5万円以上になると補助されます。家の窓全体の断熱工事をする場合、工事にかかった費用に応じて、固定資産税の控除の制度があります。 | R43: 家の窓全体の断熱工事をする場合、工事にかかった費用に応じて、固定資産税の控除や、ローン残高に応じた所得税控除の制度があります。 | S43: 暖房時は窓やサッシから逃げる熱の割合が多く、通常のシングルガラスを複層ガラスに取り替えることで熱の逃げ方を半分程度に抑えることができます。省エネだけでなく、結露がつきにくくなるというメリットもあります。窓から吹き下ろしてくる冷たい風も和らぎ、快適性も向上します。家屋に応じた手法がありますので、工務店などに相談してください。 | T43: 暖房時は窓やサッシから逃げる熱の割合が多く、通常のシングルガラスを複層ガラスに取り替えることで熱の逃げ方を半分程度に抑えることができます。省エネだけでなく、結露がつきにくくなるというメリットもあります。窓から吹き下ろしてくる冷たい風も和らぎ、快適性も向上します。家屋に応じた手法がありますので、工務店などに相談してください。 | V43: wss | Z43: ="D6.scenario.defMeasures['"&C43&"'] = { "&B$2&":"""&B43&""", "&C$2&":"""&C43&""", "&D$2&":"""&CLEAN(SUBSTITUTE(D43,"""","'"))&""", "&I$2&":"""&I43&""", "&F$2&":"""&F43&""", "&G$2&":"""&CLEAN(SUBSTITUTE(G43,"""","'"))&""", "&K$2&":"""&K43&""", "&L$2&":"""&L43&""", "&M$2&":"""&M43&""", "&N$2&":"""&N43&""", "&O$2&":"""&O43&""", "&P$2&":"""&P43&""", "&Q$2&":"""&Q43&""", "&S$2&":"""&CLEAN(SUBSTITUTE(S43,"""","'"))&""", "&U$2&":"""&U43&""", "&V$2&":"""&V43&"""};" -> D6.scenario.defMeasures['mHTlowe'] = { mid:"210", name:"mHTlowe", title:"窓・サッシを樹脂枠low-Eガラスにする", easyness:"1", refCons:"consACheat", titleShort:"樹脂枠low-Eガラス", level:"", figNum:"4", lifeTime:"30", price:"170000", roanShow:"", standardType:"", subsidy :"子育てグリーン住宅支援事業の対象で、他の断熱工事や機器導入を行って補助額が5万円以上になると補助されます。家の窓全体の断熱工事をする場合、工事にかかった費用に応じて、固定資産税の控除の制度があります。", advice:"暖房時は窓やサッシから逃げる熱の割合が多く、通常のシングルガラスを複層ガラスに取り替えることで熱の逃げ方を半分程度に抑えることができます。省エネだけでなく、結露がつきにくくなるというメリットもあります。窓から吹き下ろしてくる冷たい風も和らぎ、快適性も向上します。家屋に応じた手法がありますので、工務店などに相談してください。", lifestyle:"", season:"wss"}; | AB43: ="$defMeasures['"&C43&"'] = [ '"&B$2&"'=>"""&B43&""", '"&D$2&"'=>"""&CLEAN(SUBSTITUTE(D43,"""","'"))&""", '"&L$2&"'=>"""&L43&""", '"&S$2&"'=>"""&CLEAN(SUBSTITUTE(S43,"""","'"))&"""];" -> $defMeasures['mHTlowe'] = [ 'mid'=>"210", 'title'=>"窓・サッシを樹脂枠low-Eガラスにする", 'figNum'=>"4", 'advice'=>"暖房時は窓やサッシから逃げる熱の割合が多く、通常のシングルガラスを複層ガラスに取り替えることで熱の逃げ方を半分程度に抑えることができます。省エネだけでなく、結露がつきにくくなるというメリットもあります。窓から吹き下ろしてくる冷たい風も和らぎ、快適性も向上します。家屋に応じた手法がありますので、工務店などに相談してください。"]; | AD43: 寒冷地では当然となりつつあるレベルの断熱窓です。このレベルを組み合わせて、エネルギー消費をゼロにしようという住宅が、2030年頃には、全国で標準になります。<br> すでに建ててしまった方も、取り替える手段はありますので、ご安心を。
B44: 211 | C44: mHTuchimado | D44: 内窓をとりつける | E44: 内窓をとりつける | F44: consACheat | G44: 内窓 | H44: 内窓 | I44: 2 | J44: 2 | K44: 5 | L44: 4 | M44: 30 | N44: 100000 | Q44: 子育てグリーン住宅支援事業の対象で、他の断熱工事や機器導入を行って補助額が5万円以上になると補助されます。家の窓全体の断熱工事をする場合、工事にかかった費用に応じて、固定資産税の控除の制度があります。 | R44: 家の窓全体の断熱工事をする場合、工事にかかった費用に応じて、固定資産税の控除や、ローン残高に応じた所得税控除の制度があります。 | S44: 暖房時は窓やサッシから逃げる熱の割合が多く、現在の窓やサッシの内側に追加して「内窓」をつけることでより熱が逃げにくくなります。内窓は比較的工事費が安く、約1時間で工事も完了し、結露防止や防犯にも効果があります。詳しくは工務店などに相談してください。 | T44: 暖房時は窓やサッシから逃げる熱の割合が多く、現在の窓やサッシの内側に追加して「内窓」をつけることでより熱が逃げにくくなります。内窓は比較的工事費が安く、約1時間で工事も完了し、結露防止や防犯にも効果があります。詳しくは工務店などに相談してください。 | V44: wss | Z44: ="D6.scenario.defMeasures['"&C44&"'] = { "&B$2&":"""&B44&""", "&C$2&":"""&C44&""", "&D$2&":"""&CLEAN(SUBSTITUTE(D44,"""","'"))&""", "&I$2&":"""&I44&""", "&F$2&":"""&F44&""", "&G$2&":"""&CLEAN(SUBSTITUTE(G44,"""","'"))&""", "&K$2&":"""&K44&""", "&L$2&":"""&L44&""", "&M$2&":"""&M44&""", "&N$2&":"""&N44&""", "&O$2&":"""&O44&""", "&P$2&":"""&P44&""", "&Q$2&":"""&Q44&""", "&S$2&":"""&CLEAN(SUBSTITUTE(S44,"""","'"))&""", "&U$2&":"""&U44&""", "&V$2&":"""&V44&"""};" -> D6.scenario.defMeasures['mHTuchimado'] = { mid:"211", name:"mHTuchimado", title:"内窓をとりつける", easyness:"2", refCons:"consACheat", titleShort:"内窓", level:"5", figNum:"4", lifeTime:"30", price:"100000", roanShow:"", standardType:"", subsidy :"子育てグリーン住宅支援事業の対象で、他の断熱工事や機器導入を行って補助額が5万円以上になると補助されます。家の窓全体の断熱工事をする場合、工事にかかった費用に応じて、固定資産税の控除の制度があります。", advice:"暖房時は窓やサッシから逃げる熱の割合が多く、現在の窓やサッシの内側に追加して「内窓」をつけることでより熱が逃げにくくなります。内窓は比較的工事費が安く、約1時間で工事も完了し、結露防止や防犯にも効果があります。詳しくは工務店などに相談してください。", lifestyle:"", season:"wss"}; | AB44: ="$defMeasures['"&C44&"'] = [ '"&B$2&"'=>"""&B44&""", '"&D$2&"'=>"""&CLEAN(SUBSTITUTE(D44,"""","'"))&""", '"&L$2&"'=>"""&L44&""", '"&S$2&"'=>"""&CLEAN(SUBSTITUTE(S44,"""","'"))&"""];" -> $defMeasures['mHTuchimado'] = [ 'mid'=>"211", 'title'=>"内窓をとりつける", 'figNum'=>"4", 'advice'=>"暖房時は窓やサッシから逃げる熱の割合が多く、現在の窓やサッシの内側に追加して「内窓」をつけることでより熱が逃げにくくなります。内窓は比較的工事費が安く、約1時間で工事も完了し、結露防止や防犯にも効果があります。詳しくは工務店などに相談してください。"]; | AD44: もう一枚内側に窓をつけるというのも、面倒そうに見えて、意外と簡単に安く工事をしてくれます。それでいて、断熱性能は拡大にアップしますし、音の漏れも少なくなります。<br> 窓を開けるときが少しわずらわしいかもしれませんが、まあ網戸が二重になっているよりは、わかりやすいです。
B45: 212 | C45: mHTdoubleGlassAll | D45: 全ての部屋の窓ガラスを複層ガラスに置き換える | E45: 全ての部屋の窓ガラスを複層ガラスに置き換える | F45: consHTsum | G45: 全居室を複層ガラスに | H45: 全居室を複層ガラスに | I45: 1 | J45: 1 | L45: 4 | M45: 30 | N45: =N42*5 -> 750000 | Q45: 子育てグリーン住宅支援事業の対象で、他の断熱工事や機器導入を行って補助額が5万円以上になると補助されます。家の窓全体の断熱工事をする場合、工事にかかった費用に応じて、固定資産税の控除の制度があります。 | R45: 家の窓全体の断熱工事をする場合、工事にかかった費用に応じて、固定資産税の控除や、ローン残高に応じた所得税控除の制度があります。 | S45: 暖房時は窓やサッシから逃げる熱の割合が多く、通常のシングルガラスを複層ガラスに取り替えることで熱の逃げ方を半分程度に抑えることができます。省エネだけでなく、結露がつきにくくなるというメリットもあります。窓から吹き下ろしてくる冷たい風も和らいだり、冬の朝方の寒さが改善されたりなど、快適性も向上します。家屋に応じた手法がありますので、工務店などに相談してください。 | T45: 暖房時は窓やサッシから逃げる熱の割合が多く、通常のシングルガラスを複層ガラスに取り替えることで熱の逃げ方を半分程度に抑えることができます。省エネだけでなく、結露がつきにくくなるというメリットもあります。窓から吹き下ろしてくる冷たい風も和らいだり、冬の朝方の寒さが改善されたりなど、快適性も向上します。家屋に応じた手法がありますので、工務店などに相談してください。 | V45: wss | Z45: ="D6.scenario.defMeasures['"&C45&"'] = { "&B$2&":"""&B45&""", "&C$2&":"""&C45&""", "&D$2&":"""&CLEAN(SUBSTITUTE(D45,"""","'"))&""", "&I$2&":"""&I45&""", "&F$2&":"""&F45&""", "&G$2&":"""&CLEAN(SUBSTITUTE(G45,"""","'"))&""", "&K$2&":"""&K45&""", "&L$2&":"""&L45&""", "&M$2&":"""&M45&""", "&N$2&":"""&N45&""", "&O$2&":"""&O45&""", "&P$2&":"""&P45&""", "&Q$2&":"""&Q45&""", "&S$2&":"""&CLEAN(SUBSTITUTE(S45,"""","'"))&""", "&U$2&":"""&U45&""", "&V$2&":"""&V45&"""};" -> D6.scenario.defMeasures['mHTdoubleGlassAll'] = { mid:"212", name:"mHTdoubleGlassAll", title:"全ての部屋の窓ガラスを複層ガラスに置き換える", easyness:"1", refCons:"consHTsum", titleShort:"全居室を複層ガラスに", level:"", figNum:"4", lifeTime:"30", price:"750000", roanShow:"", standardType:"", subsidy :"子育てグリーン住宅支援事業の対象で、他の断熱工事や機器導入を行って補助額が5万円以上になると補助されます。家の窓全体の断熱工事をする場合、工事にかかった費用に応じて、固定資産税の控除の制度があります。", advice:"暖房時は窓やサッシから逃げる熱の割合が多く、通常のシングルガラスを複層ガラスに取り替えることで熱の逃げ方を半分程度に抑えることができます。省エネだけでなく、結露がつきにくくなるというメリットもあります。窓から吹き下ろしてくる冷たい風も和らいだり、冬の朝方の寒さが改善されたりなど、快適性も向上します。家屋に応じた手法がありますので、工務店などに相談してください。", lifestyle:"", season:"wss"}; | AB45: ="$defMeasures['"&C45&"'] = [ '"&B$2&"'=>"""&B45&""", '"&D$2&"'=>"""&CLEAN(SUBSTITUTE(D45,"""","'"))&""", '"&L$2&"'=>"""&L45&""", '"&S$2&"'=>"""&CLEAN(SUBSTITUTE(S45,"""","'"))&"""];" -> $defMeasures['mHTdoubleGlassAll'] = [ 'mid'=>"212", 'title'=>"全ての部屋の窓ガラスを複層ガラスに置き換える", 'figNum'=>"4", 'advice'=>"暖房時は窓やサッシから逃げる熱の割合が多く、通常のシングルガラスを複層ガラスに取り替えることで熱の逃げ方を半分程度に抑えることができます。省エネだけでなく、結露がつきにくくなるというメリットもあります。窓から吹き下ろしてくる冷たい風も和らいだり、冬の朝方の寒さが改善されたりなど、快適性も向上します。家屋に応じた手法がありますので、工務店などに相談してください。"]; | AD45: 割れない限り、付替えの必要性も感じない「窓・サッシ」ですが、・・・確かに以前の学校と違って割れないですね。二重になっているだけで、こんなに暖かいのかと、感動します。けれども、2020年までには複層ガラスが当然となり、やがて、もっと上のレベルが「いいよねえ」と話題になる時代が来るでしょう。
B46: 213 | C46: mHTuchimadoAll | D46: 全ての部屋に内窓をとりつける | E46: 全ての部屋に内窓をとりつける | F46: consHTsum | G46: 全居室を内窓に | H46: 全居室を内窓に | I46: 1 | J46: 1 | L46: 4 | M46: 30 | N46: =N44*5 -> 500000 | Q46: 子育てグリーン住宅支援事業の対象で、他の断熱工事や機器導入を行って補助額が5万円以上になると補助されます。家の窓全体の断熱工事をする場合、工事にかかった費用に応じて、固定資産税の控除の制度があります。 | R46: 家の窓全体の断熱工事をする場合、工事にかかった費用に応じて、固定資産税の控除や、ローン残高に応じた所得税控除の制度があります。 | S46: 暖房時は窓やサッシから逃げる熱の割合が多く、現在の窓やサッシの内側に追加して「内窓」をつけることでより熱が逃げにくくなります。内窓は比較的工事費が安く、約1時間で工事も完了し、結露防止や防犯にも効果があります。窓から吹き下ろしてくる冷たい風も和らいだり、冬の朝方の寒さが改善されたりなど、快適性も向上します。詳しくは工務店などに相談してください。 | T46: 暖房時は窓やサッシから逃げる熱の割合が多く、現在の窓やサッシの内側に追加して「内窓」をつけることでより熱が逃げにくくなります。内窓は比較的工事費が安く、約1時間で工事も完了し、結露防止や防犯にも効果があります。窓から吹き下ろしてくる冷たい風も和らぎ、冬の朝方の寒さが改善されたりなど、快適性も向上します。詳しくは工務店などに相談してください。 | V46: wss | Z46: ="D6.scenario.defMeasures['"&C46&"'] = { "&B$2&":"""&B46&""", "&C$2&":"""&C46&""", "&D$2&":"""&CLEAN(SUBSTITUTE(D46,"""","'"))&""", "&I$2&":"""&I46&""", "&F$2&":"""&F46&""", "&G$2&":"""&CLEAN(SUBSTITUTE(G46,"""","'"))&""", "&K$2&":"""&K46&""", "&L$2&":"""&L46&""", "&M$2&":"""&M46&""", "&N$2&":"""&N46&""", "&O$2&":"""&O46&""", "&P$2&":"""&P46&""", "&Q$2&":"""&Q46&""", "&S$2&":"""&CLEAN(SUBSTITUTE(S46,"""","'"))&""", "&U$2&":"""&U46&""", "&V$2&":"""&V46&"""};" -> D6.scenario.defMeasures['mHTuchimadoAll'] = { mid:"213", name:"mHTuchimadoAll", title:"全ての部屋に内窓をとりつける", easyness:"1", refCons:"consHTsum", titleShort:"全居室を内窓に", level:"", figNum:"4", lifeTime:"30", price:"500000", roanShow:"", standardType:"", subsidy :"子育てグリーン住宅支援事業の対象で、他の断熱工事や機器導入を行って補助額が5万円以上になると補助されます。家の窓全体の断熱工事をする場合、工事にかかった費用に応じて、固定資産税の控除の制度があります。", advice:"暖房時は窓やサッシから逃げる熱の割合が多く、現在の窓やサッシの内側に追加して「内窓」をつけることでより熱が逃げにくくなります。内窓は比較的工事費が安く、約1時間で工事も完了し、結露防止や防犯にも効果があります。窓から吹き下ろしてくる冷たい風も和らいだり、冬の朝方の寒さが改善されたりなど、快適性も向上します。詳しくは工務店などに相談してください。", lifestyle:"", season:"wss"}; | AB46: ="$defMeasures['"&C46&"'] = [ '"&B$2&"'=>"""&B46&""", '"&D$2&"'=>"""&CLEAN(SUBSTITUTE(D46,"""","'"))&""", '"&L$2&"'=>"""&L46&""", '"&S$2&"'=>"""&CLEAN(SUBSTITUTE(S46,"""","'"))&"""];" -> $defMeasures['mHTuchimadoAll'] = [ 'mid'=>"213", 'title'=>"全ての部屋に内窓をとりつける", 'figNum'=>"4", 'advice'=>"暖房時は窓やサッシから逃げる熱の割合が多く、現在の窓やサッシの内側に追加して「内窓」をつけることでより熱が逃げにくくなります。内窓は比較的工事費が安く、約1時間で工事も完了し、結露防止や防犯にも効果があります。窓から吹き下ろしてくる冷たい風も和らいだり、冬の朝方の寒さが改善されたりなど、快適性も向上します。詳しくは工務店などに相談してください。"]; | AD46: 寒冷地では当然となりつつあるレベルの断熱窓です。このレベルを組み合わせて、エネルギー消費をゼロにしようという住宅が、2030年頃には、全国で標準になります。<br> すでに建ててしまった方も、取り替える手段はありますので、ご安心を。
B47: 214 | C47: mHTloweAll | D47: 全ての部屋の窓・サッシを樹脂枠low-Eガラスにする | E47: 全ての部屋の窓・サッシを樹脂枠low-Eガラスにする | F47: consHTsum | G47: 全居室を樹脂枠low-Eガラスに | H47: 全居室を樹脂枠low-Eガラスに | I47: 1 | J47: 1 | L47: 4 | M47: 30 | N47: =N43*5 -> 850000 | Q47: 子育てグリーン住宅支援事業の対象で、他の断熱工事や機器導入を行って補助額が5万円以上になると補助されます。家の窓全体の断熱工事をする場合、工事にかかった費用に応じて、固定資産税の控除の制度があります。 | R47: 家の窓全体の断熱工事をする場合、工事にかかった費用に応じて、固定資産税の控除や、ローン残高に応じた所得税控除の制度があります。 | S47: 暖房時は窓やサッシから逃げる熱の割合が多く、通常のシングルガラスを複層ガラスに取り替えることで熱の逃げ方を半分程度に抑えることができます。省エネだけでなく、結露がつきにくくなるというメリットもあります。窓から吹き下ろしてくる冷たい風も和らいだり、冬の朝方の寒さが改善されたりなど、快適性も向上します。家屋に応じた手法がありますので、工務店などに相談してください。 | T47: 暖房時は窓やサッシから逃げる熱の割合が多く、通常のシングルガラスを複層ガラスに取り替えることで熱の逃げ方を半分程度に抑えることができます。省エネだけでなく、結露がつきにくくなるというメリットもあります。窓から吹き下ろしてくる冷たい風も和らいだり、冬の朝方の寒さが改善されたりなど、快適性も向上します。家屋に応じた手法がありますので、工務店などに相談してください。 | V47: wss | Z47: ="D6.scenario.defMeasures['"&C47&"'] = { "&B$2&":"""&B47&""", "&C$2&":"""&C47&""", "&D$2&":"""&CLEAN(SUBSTITUTE(D47,"""","'"))&""", "&I$2&":"""&I47&""", "&F$2&":"""&F47&""", "&G$2&":"""&CLEAN(SUBSTITUTE(G47,"""","'"))&""", "&K$2&":"""&K47&""", "&L$2&":"""&L47&""", "&M$2&":"""&M47&""", "&N$2&":"""&N47&""", "&O$2&":"""&O47&""", "&P$2&":"""&P47&""", "&Q$2&":"""&Q47&""", "&S$2&":"""&CLEAN(SUBSTITUTE(S47,"""","'"))&""", "&U$2&":"""&U47&""", "&V$2&":"""&V47&"""};" -> D6.scenario.defMeasures['mHTloweAll'] = { mid:"214", name:"mHTloweAll", title:"全ての部屋の窓・サッシを樹脂枠low-Eガラスにする", easyness:"1", refCons:"consHTsum", titleShort:"全居室を樹脂枠low-Eガラスに", level:"", figNum:"4", lifeTime:"30", price:"850000", roanShow:"", standardType:"", subsidy :"子育てグリーン住宅支援事業の対象で、他の断熱工事や機器導入を行って補助額が5万円以上になると補助されます。家の窓全体の断熱工事をする場合、工事にかかった費用に応じて、固定資産税の控除の制度があります。", advice:"暖房時は窓やサッシから逃げる熱の割合が多く、通常のシングルガラスを複層ガラスに取り替えることで熱の逃げ方を半分程度に抑えることができます。省エネだけでなく、結露がつきにくくなるというメリットもあります。窓から吹き下ろしてくる冷たい風も和らいだり、冬の朝方の寒さが改善されたりなど、快適性も向上します。家屋に応じた手法がありますので、工務店などに相談してください。", lifestyle:"", season:"wss"}; | AB47: ="$defMeasures['"&C47&"'] = [ '"&B$2&"'=>"""&B47&""", '"&D$2&"'=>"""&CLEAN(SUBSTITUTE(D47,"""","'"))&""", '"&L$2&"'=>"""&L47&""", '"&S$2&"'=>"""&CLEAN(SUBSTITUTE(S47,"""","'"))&"""];" -> $defMeasures['mHTloweAll'] = [ 'mid'=>"214", 'title'=>"全ての部屋の窓・サッシを樹脂枠low-Eガラスにする", 'figNum'=>"4", 'advice'=>"暖房時は窓やサッシから逃げる熱の割合が多く、通常のシングルガラスを複層ガラスに取り替えることで熱の逃げ方を半分程度に抑えることができます。省エネだけでなく、結露がつきにくくなるというメリットもあります。窓から吹き下ろしてくる冷たい風も和らいだり、冬の朝方の寒さが改善されたりなど、快適性も向上します。家屋に応じた手法がありますので、工務店などに相談してください。"]; | AD47: もう一枚内側に窓をつけるというのも、面倒そうに見えて、意外と簡単に安く工事をしてくれます。それでいて、断熱性能は拡大にアップしますし、音の漏れも少なくなります。<br> 窓を開けるときが少しわずらわしいかもしれませんが、まあ網戸が二重になっているよりは、わかりやすいです。
B48: 215 | C48: mACfilter | D48: エアコンのフィルターを掃除する | E48: エアコンのフィルターを掃除する | F48: consACheat | G48: フィルター掃除 | H48: フィルター掃除 | I48: 2 | J48: 2 | K48: 5 | L48: 1 | S48: エアコンは1ヶ月利用するごとにフィルター掃除するのが望ましいです。フィルターの目が詰まると、送風が弱くなり、特に暖房での効率が大きく落ちてしまいます。特にキッチンを含む部屋では、油煙がつきやすいのでこまめに掃除してください。最近のエアコンでは、自動的にフィルターを掃除する機種もあります。 | T48: エアコンは1ヶ月利用するごとにフィルター掃除するのが望ましいです。フィルターの目が詰まると、送風が弱くなり、特に暖房での効率が大きく落ちてしまいます。特にキッチンを含む部屋では、油煙がつきやすいのでこまめに掃除してください。最近のエアコンでは、自動的にフィルターを掃除する機種もあります。 | U48: 1 | V48: wss | Z48: ="D6.scenario.defMeasures['"&C48&"'] = { "&B$2&":"""&B48&""", "&C$2&":"""&C48&""", "&D$2&":"""&CLEAN(SUBSTITUTE(D48,"""","'"))&""", "&I$2&":"""&I48&""", "&F$2&":"""&F48&""", "&G$2&":"""&CLEAN(SUBSTITUTE(G48,"""","'"))&""", "&K$2&":"""&K48&""", "&L$2&":"""&L48&""", "&M$2&":"""&M48&""", "&N$2&":"""&N48&""", "&O$2&":"""&O48&""", "&P$2&":"""&P48&""", "&Q$2&":"""&Q48&""", "&S$2&":"""&CLEAN(SUBSTITUTE(S48,"""","'"))&""", "&U$2&":"""&U48&""", "&V$2&":"""&V48&"""};" -> D6.scenario.defMeasures['mACfilter'] = { mid:"215", name:"mACfilter", title:"エアコンのフィルターを掃除する", easyness:"2", refCons:"consACheat", titleShort:"フィルター掃除", level:"5", figNum:"1", lifeTime:"", price:"", roanShow:"", standardType:"", subsidy :"", advice:"エアコンは1ヶ月利用するごとにフィルター掃除するのが望ましいです。フィルターの目が詰まると、送風が弱くなり、特に暖房での効率が大きく落ちてしまいます。特にキッチンを含む部屋では、油煙がつきやすいのでこまめに掃除してください。最近のエアコンでは、自動的にフィルターを掃除する機種もあります。", lifestyle:"1", season:"wss"}; | AB48: ="$defMeasures['"&C48&"'] = [ '"&B$2&"'=>"""&B48&""", '"&D$2&"'=>"""&CLEAN(SUBSTITUTE(D48,"""","'"))&""", '"&L$2&"'=>"""&L48&""", '"&S$2&"'=>"""&CLEAN(SUBSTITUTE(S48,"""","'"))&"""];" -> $defMeasures['mACfilter'] = [ 'mid'=>"215", 'title'=>"エアコンのフィルターを掃除する", 'figNum'=>"1", 'advice'=>"エアコンは1ヶ月利用するごとにフィルター掃除するのが望ましいです。フィルターの目が詰まると、送風が弱くなり、特に暖房での効率が大きく落ちてしまいます。特にキッチンを含む部屋では、油煙がつきやすいのでこまめに掃除してください。最近のエアコンでは、自動的にフィルターを掃除する機種もあります。"]; | AD48: 簡単にする場合には、掃除機で吸い取ってください。もっとするときは外してはたいてください。油汚れまでついていたら、洗剤で洗ってください。エアコンの自動掃除機能は、あまり期待しないでください。
B49: 216 | C49: mHTtime | D49: 暖房の使用時間を1時間短くする | E49: 暖房の使用時間を1時間短くする | F49: consACheat | G49: 暖房1時間短縮 | H49: 暖房1時間短縮 | I49: 3 | J49: 3 | L49: 3 | S49: 暖房はつい長い時間つけっぱなしにしがちです。暖かくなったら止めるようにしましょう。就寝前や外出時などは30分前に止めるのも一つの方法です。また、人がいない部屋を暖房するのは無駄ですので、なるべく切るようにしましょう。 | T49: 暖房はつい長い時間つけっぱなしにしがちです。暖かくなったら止めるようにしましょう。就寝前や外出時などは30分前に止めるのも一つの方法です。また、人がいない部屋を暖房するのは無駄ですので、なるべく切るようにしましょう。 | U49: 1 | V49: wss | Z49: ="D6.scenario.defMeasures['"&C49&"'] = { "&B$2&":"""&B49&""", "&C$2&":"""&C49&""", "&D$2&":"""&CLEAN(SUBSTITUTE(D49,"""","'"))&""", "&I$2&":"""&I49&""", "&F$2&":"""&F49&""", "&G$2&":"""&CLEAN(SUBSTITUTE(G49,"""","'"))&""", "&K$2&":"""&K49&""", "&L$2&":"""&L49&""", "&M$2&":"""&M49&""", "&N$2&":"""&N49&""", "&O$2&":"""&O49&""", "&P$2&":"""&P49&""", "&Q$2&":"""&Q49&""", "&S$2&":"""&CLEAN(SUBSTITUTE(S49,"""","'"))&""", "&U$2&":"""&U49&""", "&V$2&":"""&V49&"""};" -> D6.scenario.defMeasures['mHTtime'] = { mid:"216", name:"mHTtime", title:"暖房の使用時間を1時間短くする", easyness:"3", refCons:"consACheat", titleShort:"暖房1時間短縮", level:"", figNum:"3", lifeTime:"", price:"", roanShow:"", standardType:"", subsidy :"", advice:"暖房はつい長い時間つけっぱなしにしがちです。暖かくなったら止めるようにしましょう。就寝前や外出時などは30分前に止めるのも一つの方法です。また、人がいない部屋を暖房するのは無駄ですので、なるべく切るようにしましょう。", lifestyle:"1", season:"wss"}; | AB49: ="$defMeasures['"&C49&"'] = [ '"&B$2&"'=>"""&B49&""", '"&D$2&"'=>"""&CLEAN(SUBSTITUTE(D49,"""","'"))&""", '"&L$2&"'=>"""&L49&""", '"&S$2&"'=>"""&CLEAN(SUBSTITUTE(S49,"""","'"))&"""];" -> $defMeasures['mHTtime'] = [ 'mid'=>"216", 'title'=>"暖房の使用時間を1時間短くする", 'figNum'=>"3", 'advice'=>"暖房はつい長い時間つけっぱなしにしがちです。暖かくなったら止めるようにしましょう。就寝前や外出時などは30分前に止めるのも一つの方法です。また、人がいない部屋を暖房するのは無駄ですので、なるべく切るようにしましょう。"]; | AD49: どの1時間を短くするかが、家族で話し合うと、話題がつきないでしょう。出かける前に早めに切るもよし、みなで早く寝るもよし、温まったとき1時間途中で止めておくもよし、最も減らしやすい時間はどこか探してみてください。出かける前に早めに消しても、しばらくは暖気が残っています。だんだん寒くなって、もう耐えられないというときに外出すると、いちばん省エネになります。<br> 暖房はトータルでみると、点ける回数と消す回数は一致しているはずです。あなたは暖房を点ける回数が多いですか、消す回数が多いですか。
B50: 217 | C50: mHTpartialHeating | D50: こたつやホットカーペットを活用して、部屋暖房を控える | E50: こたつやホットカーペットを活用して、部屋暖房を控える | F50: consACheat | G50: こたつ・ホットカーペット | H50: こたつ・ホットカーペット | I50: 2 | J50: 2 | L50: 3 | S50: こたつやホットカーペットなどの部分暖房は、身体の近くだけを温めるので、消費エネルギーが少なくなっています。部屋暖房の設定温度を大きく下げても、同じ快適性を維持できます。特に、吹き抜け構造だったり、暖房部屋から階段が上階に続いている構造の場合、せっかく温めた空気が天井に抜けてしまい、部屋を温めるのに効率が悪くなります。こうした場合には、足元を温める暖房も検討してみてください。靴下をはいたり、厚着をすることも効果的です。<br> こたつやホットカーペットを使う場合には、床との間に断熱シートを敷いたり、こたつの掛け布団も厚めにすると、より消費電力を減らせます。 | T50: こたつやホットカーペットなどの部分暖房は、身体の近くだけを温めるので、消費エネルギーが少なくなっています。部屋暖房の設定温度を大きく下げても、同じ快適性を維持できます。特に、吹き抜け構造だったり、暖房部屋から階段が上階に続いている構造の場合、せっかく温めた空気が天井に抜けてしまい、部屋を温めるのに効率が悪くなります。こうした場合には、足元を温める暖房も検討してみてください。靴下をはいたり、厚着をすることも効果的です。<br> こたつやホットカーペットを使う場合には、床との間に断熱シートを敷いたり、こたつの掛け布団も厚めにすると、より消費電力を減らせます。 | U50: 1 | V50: wss | Z50: ="D6.scenario.defMeasures['"&C50&"'] = { "&B$2&":"""&B50&""", "&C$2&":"""&C50&""", "&D$2&":"""&CLEAN(SUBSTITUTE(D50,"""","'"))&""", "&I$2&":"""&I50&""", "&F$2&":"""&F50&""", "&G$2&":"""&CLEAN(SUBSTITUTE(G50,"""","'"))&""", "&K$2&":"""&K50&""", "&L$2&":"""&L50&""", "&M$2&":"""&M50&""", "&N$2&":"""&N50&""", "&O$2&":"""&O50&""", "&P$2&":"""&P50&""", "&Q$2&":"""&Q50&""", "&S$2&":"""&CLEAN(SUBSTITUTE(S50,"""","'"))&""", "&U$2&":"""&U50&""", "&V$2&":"""&V50&"""};" -> D6.scenario.defMeasures['mHTpartialHeating'] = { mid:"217", name:"mHTpartialHeating", title:"こたつやホットカーペットを活用して、部屋暖房を控える", easyness:"2", refCons:"consACheat", titleShort:"こたつ・ホットカーペット", level:"", figNum:"3", lifeTime:"", price:"", roanShow:"", standardType:"", subsidy :"", advice:"こたつやホットカーペットなどの部分暖房は、身体の近くだけを温めるので、消費エネルギーが少なくなっています。部屋暖房の設定温度を大きく下げても、同じ快適性を維持できます。特に、吹き抜け構造だったり、暖房部屋から階段が上階に続いている構造の場合、せっかく温めた空気が天井に抜けてしまい、部屋を温めるのに効率が悪くなります。こうした場合には、足元を温める暖房も検討してみてください。靴下をはいたり、厚着をすることも効果的です。<br> こたつやホットカーペットを使う場合には、床との間に断熱シートを敷いたり、こたつの掛け布団も厚めにすると、より消費電力を減らせます。", lifestyle:"1", season:"wss"}; | AB50: ="$defMeasures['"&C50&"'] = [ '"&B$2&"'=>"""&B50&""", '"&D$2&"'=>"""&CLEAN(SUBSTITUTE(D50,"""","'"))&""", '"&L$2&"'=>"""&L50&""", '"&S$2&"'=>"""&CLEAN(SUBSTITUTE(S50,"""","'"))&"""];" -> $defMeasures['mHTpartialHeating'] = [ 'mid'=>"217", 'title'=>"こたつやホットカーペットを活用して、部屋暖房を控える", 'figNum'=>"3", 'advice'=>"こたつやホットカーペットなどの部分暖房は、身体の近くだけを温めるので、消費エネルギーが少なくなっています。部屋暖房の設定温度を大きく下げても、同じ快適性を維持できます。特に、吹き抜け構造だったり、暖房部屋から階段が上階に続いている構造の場合、せっかく温めた空気が天井に抜けてしまい、部屋を温めるのに効率が悪くなります。こうした場合には、足元を温める暖房も検討してみてください。靴下をはいたり、厚着をすることも効果的です。<br> こたつやホットカーペットを使う場合には、床との間に断熱シートを敷いたり、こたつの掛け布団も厚めにすると、より消費電力を減らせます。"]; | AD50: こたつは日本が世界に誇る省エネ暖房器具です。電気を多く消費しそうですが、消えている時間が長いので、平均すると100W程度の消費です。しかも、家族で足をつっこんでいると、足の熱でほとんど電気を消費しない場合もあります。これだけの電気で、家族全員が暖まれるというのは、画期的です。<br> ただ、こたつには致命的な欠点があります。一度入ると二度と出てこれなくなるのです。この問題を解決することができれば、ノーベル賞ものだと言われています。
B51: 218 | C51: mHTceiling | D51: 暖房時に天井の暖気をかきまぜる | E51: 暖房時に天井の暖気をかきまぜる | F51: consACheat | G51: サーキュレータ | H51: サーキュレータ | I51: 2 | J51: 2 | L51: 3 | S51: 部屋暖房をしていると、床に比べて天井のほうが5～10℃近くも温度が高くなっていることが多くあります。うちわなどでかきまぜたり、サーキュレータや扇風機を上向きにしてかきまぜることで、暖かい空気を床まで届けることができ、快適に過ごせます。靴下をはいたり、厚着をすることも効果的です。 | T51: 部屋暖房をしていると、床に比べて天井のほうが5～10℃近くも温度が高くなっていることが多くあります。うちわなどでかきまぜたり、サーキュレータや扇風機を上向きにしてかきまぜることで、暖かい空気を床まで届けることができ、快適に過ごせます。靴下をはいたり、厚着をすることも効果的です。 | U51: 1 | V51: wss | Z51: ="D6.scenario.defMeasures['"&C51&"'] = { "&B$2&":"""&B51&""", "&C$2&":"""&C51&""", "&D$2&":"""&CLEAN(SUBSTITUTE(D51,"""","'"))&""", "&I$2&":"""&I51&""", "&F$2&":"""&F51&""", "&G$2&":"""&CLEAN(SUBSTITUTE(G51,"""","'"))&""", "&K$2&":"""&K51&""", "&L$2&":"""&L51&""", "&M$2&":"""&M51&""", "&N$2&":"""&N51&""", "&O$2&":"""&O51&""", "&P$2&":"""&P51&""", "&Q$2&":"""&Q51&""", "&S$2&":"""&CLEAN(SUBSTITUTE(S51,"""","'"))&""", "&U$2&":"""&U51&""", "&V$2&":"""&V51&"""};" -> D6.scenario.defMeasures['mHTceiling'] = { mid:"218", name:"mHTceiling", title:"暖房時に天井の暖気をかきまぜる", easyness:"2", refCons:"consACheat", titleShort:"サーキュレータ", level:"", figNum:"3", lifeTime:"", price:"", roanShow:"", standardType:"", subsidy :"", advice:"部屋暖房をしていると、床に比べて天井のほうが5～10℃近くも温度が高くなっていることが多くあります。うちわなどでかきまぜたり、サーキュレータや扇風機を上向きにしてかきまぜることで、暖かい空気を床まで届けることができ、快適に過ごせます。靴下をはいたり、厚着をすることも効果的です。", lifestyle:"1", season:"wss"}; | AB51: ="$defMeasures['"&C51&"'] = [ '"&B$2&"'=>"""&B51&""", '"&D$2&"'=>"""&CLEAN(SUBSTITUTE(D51,"""","'"))&""", '"&L$2&"'=>"""&L51&""", '"&S$2&"'=>"""&CLEAN(SUBSTITUTE(S51,"""","'"))&"""];" -> $defMeasures['mHTceiling'] = [ 'mid'=>"218", 'title'=>"暖房時に天井の暖気をかきまぜる", 'figNum'=>"3", 'advice'=>"部屋暖房をしていると、床に比べて天井のほうが5～10℃近くも温度が高くなっていることが多くあります。うちわなどでかきまぜたり、サーキュレータや扇風機を上向きにしてかきまぜることで、暖かい空気を床まで届けることができ、快適に過ごせます。靴下をはいたり、厚着をすることも効果的です。"]; | AD51: ストーブなどを使っていると、天井のほうが5℃以上も高くなることがあります。人間は床で生活する生き物で、天井に張り付いて生活することはできません。天井裏のネズミばかり喜ばせても仕方ありませんので、しっかり床まで暖気を送ってあげましょう。<br> 扇風機やサーキュレータを上向きに設置するのもいいのですが、おすすめは「うちわ」です。パタパタさせるだけで、しっかり床まで暖気が届きますし、運動をして身体も暖まります。ただし、あらかじめ天井を掃除してからやらないと、ホコリが舞ってどうしようもないので、まずは掃除からはじめてください。
B52: 219 | C52: mHTareaLimit | D52: 暖房時に部屋のドアやふすまを閉め、暖房範囲を小さくする | E52: 暖房時に部屋のドアやふすまを閉め、暖房範囲を小さくする | F52: consACheat | G52: 暖房範囲 | H52: 暖房範囲 | I52: 2 | J52: 2 | K52: 5 | L52: 3 | S52: 広い部屋を暖房するのには多くのエネルギーが必要です。ふすまや扉などで部屋を区切ると、小さい暖房器具でもよく暖まります。逆に吹き抜け構造など天井が高い場合は、多くの暖房が必要になります。 | T52: 広い部屋を暖房するのには多くのエネルギーが必要です。ふすまや扉などで部屋を区切ると、小さい暖房器具でもよく暖まります。逆に吹き抜け構造など天井が高い場合は、多くの暖房が必要になります。 | U52: 1 | V52: wss | Z52: ="D6.scenario.defMeasures['"&C52&"'] = { "&B$2&":"""&B52&""", "&C$2&":"""&C52&""", "&D$2&":"""&CLEAN(SUBSTITUTE(D52,"""","'"))&""", "&I$2&":"""&I52&""", "&F$2&":"""&F52&""", "&G$2&":"""&CLEAN(SUBSTITUTE(G52,"""","'"))&""", "&K$2&":"""&K52&""", "&L$2&":"""&L52&""", "&M$2&":"""&M52&""", "&N$2&":"""&N52&""", "&O$2&":"""&O52&""", "&P$2&":"""&P52&""", "&Q$2&":"""&Q52&""", "&S$2&":"""&CLEAN(SUBSTITUTE(S52,"""","'"))&""", "&U$2&":"""&U52&""", "&V$2&":"""&V52&"""};" -> D6.scenario.defMeasures['mHTareaLimit'] = { mid:"219", name:"mHTareaLimit", title:"暖房時に部屋のドアやふすまを閉め、暖房範囲を小さくする", easyness:"2", refCons:"consACheat", titleShort:"暖房範囲", level:"5", figNum:"3", lifeTime:"", price:"", roanShow:"", standardType:"", subsidy :"", advice:"広い部屋を暖房するのには多くのエネルギーが必要です。ふすまや扉などで部屋を区切ると、小さい暖房器具でもよく暖まります。逆に吹き抜け構造など天井が高い場合は、多くの暖房が必要になります。", lifestyle:"1", season:"wss"}; | AB52: ="$defMeasures['"&C52&"'] = [ '"&B$2&"'=>"""&B52&""", '"&D$2&"'=>"""&CLEAN(SUBSTITUTE(D52,"""","'"))&""", '"&L$2&"'=>"""&L52&""", '"&S$2&"'=>"""&CLEAN(SUBSTITUTE(S52,"""","'"))&"""];" -> $defMeasures['mHTareaLimit'] = [ 'mid'=>"219", 'title'=>"暖房時に部屋のドアやふすまを閉め、暖房範囲を小さくする", 'figNum'=>"3", 'advice'=>"広い部屋を暖房するのには多くのエネルギーが必要です。ふすまや扉などで部屋を区切ると、小さい暖房器具でもよく暖まります。逆に吹き抜け構造など天井が高い場合は、多くの暖房が必要になります。"]; | AD52: 広い部屋を狭く使おうという提案です。もしくは、狭い家もいいところがあるよ、というお話です。<br> 必要なものが全て手が届く範囲に置いてあり、過ごせるというのも、なかなか便利な生活かもしれません。
B53: 220 | C53: mHTdanran | D53: 家族だんらんで一部屋で過ごすようにする | E53: 家族だんらんで一部屋で過ごすようにする | F53: consHTsum | G53: 家族だんらん | H53: 家族だんらん | I53: 3 | J53: 3 | L53: 3 | S53: 家族が別々の部屋で過ごすと、それぞれに暖房や照明をつける必要があります。いっしょの部屋で過ごすことで、暖房も照明も減らすことができます。ぜひ団らんの時間を楽しみながら、省エネをしてみてください。 | T53: 家族が別々の部屋で過ごすと、それぞれに暖房や照明をつける必要があります。いっしょの部屋で過ごすことで、暖房も照明も減らすことができます。ぜひ団らんの時間を楽しみながら、省エネをしてみてください。 | U53: 1 | V53: wss | Z53: ="D6.scenario.defMeasures['"&C53&"'] = { "&B$2&":"""&B53&""", "&C$2&":"""&C53&""", "&D$2&":"""&CLEAN(SUBSTITUTE(D53,"""","'"))&""", "&I$2&":"""&I53&""", "&F$2&":"""&F53&""", "&G$2&":"""&CLEAN(SUBSTITUTE(G53,"""","'"))&""", "&K$2&":"""&K53&""", "&L$2&":"""&L53&""", "&M$2&":"""&M53&""", "&N$2&":"""&N53&""", "&O$2&":"""&O53&""", "&P$2&":"""&P53&""", "&Q$2&":"""&Q53&""", "&S$2&":"""&CLEAN(SUBSTITUTE(S53,"""","'"))&""", "&U$2&":"""&U53&""", "&V$2&":"""&V53&"""};" -> D6.scenario.defMeasures['mHTdanran'] = { mid:"220", name:"mHTdanran", title:"家族だんらんで一部屋で過ごすようにする", easyness:"3", refCons:"consHTsum", titleShort:"家族だんらん", level:"", figNum:"3", lifeTime:"", price:"", roanShow:"", standardType:"", subsidy :"", advice:"家族が別々の部屋で過ごすと、それぞれに暖房や照明をつける必要があります。いっしょの部屋で過ごすことで、暖房も照明も減らすことができます。ぜひ団らんの時間を楽しみながら、省エネをしてみてください。", lifestyle:"1", season:"wss"}; | AB53: ="$defMeasures['"&C53&"'] = [ '"&B$2&"'=>"""&B53&""", '"&D$2&"'=>"""&CLEAN(SUBSTITUTE(D53,"""","'"))&""", '"&L$2&"'=>"""&L53&""", '"&S$2&"'=>"""&CLEAN(SUBSTITUTE(S53,"""","'"))&"""];" -> $defMeasures['mHTdanran'] = [ 'mid'=>"220", 'title'=>"家族だんらんで一部屋で過ごすようにする", 'figNum'=>"3", 'advice'=>"家族が別々の部屋で過ごすと、それぞれに暖房や照明をつける必要があります。いっしょの部屋で過ごすことで、暖房も照明も減らすことができます。ぜひ団らんの時間を楽しみながら、省エネをしてみてください。"]; | AD53: 最近は家族ばらばらで過ごすことが多いですね。子どもは子ども部屋で、勉強しているふりをし、お父さんは自分の部屋で、よくわからないことをしています。ばらばらで過ごすと、それぞれの部屋の照明をつけて、冷暖房をしないといけません。いっしょに過ごすことができれば、一部屋の照明と冷暖房で、みなが過ごすことができます。<br> ただしそのためには、家族仲良くすることが大事です。地球環境の前に、まずは家族環境を整えましょう。
B54: 221 | C54: mHTbiomass | D54: 薪ストーブ（ペレットストーブ）を導入する | E54: 薪ストーブ（ペレットストーブ）を導入する | F54: consACheat | G54: 薪・ペレットストーブ | H54: 薪・ペレットストーブ | I54: 1 | J54: 1 | L54: 3 | M54: 20 | N54: 300000 | S54: 薪ストーブもしくはペレットストーブを使うと、石油やガスなどの化石燃料を使わないため二酸化炭素排出量を減らすことができます。昔からの暖房燃料ですが、むしろ暖炉などおしゃれな作りで、都市部でも導入する事例が増えています。ペレットストーブは、燃料を自動的に供給するために、手間がかからないのもメリットです。設置には煙突の設置など、工事が必要になります。 | T54: 薪ストーブもしくはペレットストーブを使うと、石油やガスなどの化石燃料を使わないため二酸化炭素排出量を減らすことができます。昔からの暖房燃料ですが、むしろ暖炉などおしゃれな作りで、都市部でも導入する事例が増えています。ペレットストーブは、燃料を自動的に供給するために、手間がかからないのもメリットです。設置には煙突の設置など、工事が必要になります。 | V54: wss | Z54: ="D6.scenario.defMeasures['"&C54&"'] = { "&B$2&":"""&B54&""", "&C$2&":"""&C54&""", "&D$2&":"""&CLEAN(SUBSTITUTE(D54,"""","'"))&""", "&I$2&":"""&I54&""", "&F$2&":"""&F54&""", "&G$2&":"""&CLEAN(SUBSTITUTE(G54,"""","'"))&""", "&K$2&":"""&K54&""", "&L$2&":"""&L54&""", "&M$2&":"""&M54&""", "&N$2&":"""&N54&""", "&O$2&":"""&O54&""", "&P$2&":"""&P54&""", "&Q$2&":"""&Q54&""", "&S$2&":"""&CLEAN(SUBSTITUTE(S54,"""","'"))&""", "&U$2&":"""&U54&""", "&V$2&":"""&V54&"""};" -> D6.scenario.defMeasures['mHTbiomass'] = { mid:"221", name:"mHTbiomass", title:"薪ストーブ（ペレットストーブ）を導入する", easyness:"1", refCons:"consACheat", titleShort:"薪・ペレットストーブ", level:"", figNum:"3", lifeTime:"20", price:"300000", roanShow:"", standardType:"", subsidy :"", advice:"薪ストーブもしくはペレットストーブを使うと、石油やガスなどの化石燃料を使わないため二酸化炭素排出量を減らすことができます。昔からの暖房燃料ですが、むしろ暖炉などおしゃれな作りで、都市部でも導入する事例が増えています。ペレットストーブは、燃料を自動的に供給するために、手間がかからないのもメリットです。設置には煙突の設置など、工事が必要になります。", lifestyle:"", season:"wss"}; | AB54: ="$defMeasures['"&C54&"'] = [ '"&B$2&"'=>"""&B54&""", '"&D$2&"'=>"""&CLEAN(SUBSTITUTE(D54,"""","'"))&""", '"&L$2&"'=>"""&L54&""", '"&S$2&"'=>"""&CLEAN(SUBSTITUTE(S54,"""","'"))&"""];" -> $defMeasures['mHTbiomass'] = [ 'mid'=>"221", 'title'=>"薪ストーブ（ペレットストーブ）を導入する", 'figNum'=>"3", 'advice'=>"薪ストーブもしくはペレットストーブを使うと、石油やガスなどの化石燃料を使わないため二酸化炭素排出量を減らすことができます。昔からの暖房燃料ですが、むしろ暖炉などおしゃれな作りで、都市部でも導入する事例が増えています。ペレットストーブは、燃料を自動的に供給するために、手間がかからないのもメリットです。設置には煙突の設置など、工事が必要になります。"]; | AD54: 木が燃える炎を見ながら過ごすのは、単に暖房をする以上のくつろぎが生まれます。北欧では、暖炉の火を延々と放送するテレビ番組が大人気になっているほどです。
B55: 222 | C55: mHTcentralNotUse | D55: 使っていない部屋の設定温度を下げる | E55: セントラルヒーティングで使っていない部屋の設定温度を下げる | F55: consHTsum | G55: 未使用部屋の暖房温度 | H55: 未使用部屋の暖房温度 | I55: 2 | J55: 2 | K55: 5 | L55: 3 | S55: 使わない部屋の暖房を止めてしまうと結露・凍結などの問題がある場合には、そうならない程度に暖房設定を控えめにしてください。暖房設定の目標とする温度は20℃です。 | T55: セントラルヒーティングをしている場合には、使わない部屋まで暖めていることになります。使わない部屋の暖房を止めてしまうと結露・凍結などの問題がある場合には、そうならない程度に暖房設定を控えめにしてください。暖房設定の目標とする温度は20℃です。 | U55: 1 | V55: wss | Z55: ="D6.scenario.defMeasures['"&C55&"'] = { "&B$2&":"""&B55&""", "&C$2&":"""&C55&""", "&D$2&":"""&CLEAN(SUBSTITUTE(D55,"""","'"))&""", "&I$2&":"""&I55&""", "&F$2&":"""&F55&""", "&G$2&":"""&CLEAN(SUBSTITUTE(G55,"""","'"))&""", "&K$2&":"""&K55&""", "&L$2&":"""&L55&""", "&M$2&":"""&M55&""", "&N$2&":"""&N55&""", "&O$2&":"""&O55&""", "&P$2&":"""&P55&""", "&Q$2&":"""&Q55&""", "&S$2&":"""&CLEAN(SUBSTITUTE(S55,"""","'"))&""", "&U$2&":"""&U55&""", "&V$2&":"""&V55&"""};" -> D6.scenario.defMeasures['mHTcentralNotUse'] = { mid:"222", name:"mHTcentralNotUse", title:"使っていない部屋の設定温度を下げる", easyness:"2", refCons:"consHTsum", titleShort:"未使用部屋の暖房温度", level:"5", figNum:"3", lifeTime:"", price:"", roanShow:"", standardType:"", subsidy :"", advice:"使わない部屋の暖房を止めてしまうと結露・凍結などの問題がある場合には、そうならない程度に暖房設定を控えめにしてください。暖房設定の目標とする温度は20℃です。", lifestyle:"1", season:"wss"}; | AB55: ="$defMeasures['"&C55&"'] = [ '"&B$2&"'=>"""&B55&""", '"&D$2&"'=>"""&CLEAN(SUBSTITUTE(D55,"""","'"))&""", '"&L$2&"'=>"""&L55&""", '"&S$2&"'=>"""&CLEAN(SUBSTITUTE(S55,"""","'"))&"""];" -> $defMeasures['mHTcentralNotUse'] = [ 'mid'=>"222", 'title'=>"使っていない部屋の設定温度を下げる", 'figNum'=>"3", 'advice'=>"使わない部屋の暖房を止めてしまうと結露・凍結などの問題がある場合には、そうならない程度に暖房設定を控えめにしてください。暖房設定の目標とする温度は20℃です。"]; | AD55: 断熱がしっかりしていれば、家全体を暖めるのが健康面でも望ましい方法です。けれども、人がいない部屋まで暖めるのは、少しロスになるため、温度設定を下げてから部屋を離れるのがベストです。これは、スマートハウスでどうにか自動化してくれたらうれしいですね。
B56: 223 | C56: mHTkanki | D56: 全熱交換換気装置を設置する | E56: 全熱交換換気装置を設置する | F56: consHTsum | G56: 全熱交換換気 | H56: 全熱交換換気 | I56: 1 | J56: 1 | L56: 3 | M56: 20 | N56: 100000 | S56: 新しい家では換気設備の導入が義務付けられていますが、暖房をしているときには、暖まった空気を屋外に捨ててしまいます。全熱交換換気装置ではその熱を回収することができ、捨てられる熱の量を少なくできます。 | T56: 新しい家では換気設備の導入が義務付けられていますが、暖房をしているときには、暖まった空気を屋外に捨ててしまいます。全熱交換換気装置ではその熱を回収することができ、捨てられる熱の量を少なくできます。 | V56: wss | Z56: ="D6.scenario.defMeasures['"&C56&"'] = { "&B$2&":"""&B56&""", "&C$2&":"""&C56&""", "&D$2&":"""&CLEAN(SUBSTITUTE(D56,"""","'"))&""", "&I$2&":"""&I56&""", "&F$2&":"""&F56&""", "&G$2&":"""&CLEAN(SUBSTITUTE(G56,"""","'"))&""", "&K$2&":"""&K56&""", "&L$2&":"""&L56&""", "&M$2&":"""&M56&""", "&N$2&":"""&N56&""", "&O$2&":"""&O56&""", "&P$2&":"""&P56&""", "&Q$2&":"""&Q56&""", "&S$2&":"""&CLEAN(SUBSTITUTE(S56,"""","'"))&""", "&U$2&":"""&U56&""", "&V$2&":"""&V56&"""};" -> D6.scenario.defMeasures['mHTkanki'] = { mid:"223", name:"mHTkanki", title:"全熱交換換気装置を設置する", easyness:"1", refCons:"consHTsum", titleShort:"全熱交換換気", level:"", figNum:"3", lifeTime:"20", price:"100000", roanShow:"", standardType:"", subsidy :"", advice:"新しい家では換気設備の導入が義務付けられていますが、暖房をしているときには、暖まった空気を屋外に捨ててしまいます。全熱交換換気装置ではその熱を回収することができ、捨てられる熱の量を少なくできます。", lifestyle:"", season:"wss"}; | AB56: ="$defMeasures['"&C56&"'] = [ '"&B$2&"'=>"""&B56&""", '"&D$2&"'=>"""&CLEAN(SUBSTITUTE(D56,"""","'"))&""", '"&L$2&"'=>"""&L56&""", '"&S$2&"'=>"""&CLEAN(SUBSTITUTE(S56,"""","'"))&"""];" -> $defMeasures['mHTkanki'] = [ 'mid'=>"223", 'title'=>"全熱交換換気装置を設置する", 'figNum'=>"3", 'advice'=>"新しい家では換気設備の導入が義務付けられていますが、暖房をしているときには、暖まった空気を屋外に捨ててしまいます。全熱交換換気装置ではその熱を回収することができ、捨てられる熱の量を少なくできます。"]; | AD56: 息をするたびに二酸化炭素が出てきますし、調理やストーブなどからも排ガスが出てきます。窓を開けたり、換気扇を使うのも一つの方法ですが、暖房時には温まった空気を捨ててしまうことにもなります。その熱まで回収しようというのですから、見事です。新築住宅で寒冷地を中心に普及しつつあります。
B57: 224 | C57: mHTreformLV5 | D57: 省エネ等級5（ZEH相当）の省エネ住宅にリフォームする | F57: consHTsum | G57: 省エネ住宅等級5 | H57: 全熱交換換気 | I57: 1 | J57: 1 | L57: 3 | M57: 20 | N57: 10000000 | Q57: 太陽光も併せて導入する場合にはZEH補助金、そうでない場合は長期優良リフォーム補助金や子育てグリーン住宅支援事業などがあり、減税もされます。 | S57: 断熱性能を高めることは、温暖化対策としてメリットがあるだけでなく、冬は暖かく、夏は涼しく、快適に過ごすことができ、健康面でもメリットがあることがわかっています。新築に建て替える方法だけでなく、土台や柱などの耐震補強をしながら、壁や窓などを全面的に作り直すリフォームは、リノベーションとも呼ばれ、新築よりも安くできます。 | T57: 断熱性能を高めることは、温暖化対策としてメリットがあるだけでなく、冬は暖かく、夏は涼しく、快適に過ごすことができ、健康面でもメリットがあることがわかっています。新築に建て替える方法だけでなく、土台や柱などの耐震補強をしながら、壁や窓などを全面的に作り直すリフォームは、リノベーションとも呼ばれ、新築よりも安くできます。 | V57: wss | Z57: ="D6.scenario.defMeasures['"&C57&"'] = { "&B$2&":"""&B57&""", "&C$2&":"""&C57&""", "&D$2&":"""&CLEAN(SUBSTITUTE(D57,"""","'"))&""", "&I$2&":"""&I57&""", "&F$2&":"""&F57&""", "&G$2&":"""&CLEAN(SUBSTITUTE(G57,"""","'"))&""", "&K$2&":"""&K57&""", "&L$2&":"""&L57&""", "&M$2&":"""&M57&""", "&N$2&":"""&N57&""", "&O$2&":"""&O57&""", "&P$2&":"""&P57&""", "&Q$2&":"""&Q57&""", "&S$2&":"""&CLEAN(SUBSTITUTE(S57,"""","'"))&""", "&U$2&":"""&U57&""", "&V$2&":"""&V57&"""};" -> D6.scenario.defMeasures['mHTreformLV5'] = { mid:"224", name:"mHTreformLV5", title:"省エネ等級5（ZEH相当）の省エネ住宅にリフォームする", easyness:"1", refCons:"consHTsum", titleShort:"省エネ住宅等級5", level:"", figNum:"3", lifeTime:"20", price:"10000000", roanShow:"", standardType:"", subsidy :"太陽光も併せて導入する場合にはZEH補助金、そうでない場合は長期優良リフォーム補助金や子育てグリーン住宅支援事業などがあり、減税もされます。", advice:"断熱性能を高めることは、温暖化対策としてメリットがあるだけでなく、冬は暖かく、夏は涼しく、快適に過ごすことができ、健康面でもメリットがあることがわかっています。新築に建て替える方法だけでなく、土台や柱などの耐震補強をしながら、壁や窓などを全面的に作り直すリフォームは、リノベーションとも呼ばれ、新築よりも安くできます。", lifestyle:"", season:"wss"}; | AB57: ="$defMeasures['"&C57&"'] = [ '"&B$2&"'=>"""&B57&""", '"&D$2&"'=>"""&CLEAN(SUBSTITUTE(D57,"""","'"))&""", '"&L$2&"'=>"""&L57&""", '"&S$2&"'=>"""&CLEAN(SUBSTITUTE(S57,"""","'"))&"""];" -> $defMeasures['mHTreformLV5'] = [ 'mid'=>"224", 'title'=>"省エネ等級5（ZEH相当）の省エネ住宅にリフォームする", 'figNum'=>"3", 'advice'=>"断熱性能を高めることは、温暖化対策としてメリットがあるだけでなく、冬は暖かく、夏は涼しく、快適に過ごすことができ、健康面でもメリットがあることがわかっています。新築に建て替える方法だけでなく、土台や柱などの耐震補強をしながら、壁や窓などを全面的に作り直すリフォームは、リノベーションとも呼ばれ、新築よりも安くできます。"]; | AD57: 息をするたびに二酸化炭素が出てきますし、調理やストーブなどからも排ガスが出てきます。窓を開けたり、換気扇を使うのも一つの方法ですが、暖房時には温まった空気を捨ててしまうことにもなります。その熱まで回収しようというのですから、見事です。新築住宅で寒冷地を中心に普及しつつあります。
B58: 225 | C58: mHTreformLV6 | D58: 省エネ等級6相当の省エネ住宅にリフォームする | F58: consHTsum | G58: 省エネ住宅等級6 | H58: 全熱交換換気 | I58: 1 | J58: 1 | L58: 3 | M58: 20 | N58: 11000000 | Q58: 太陽光も併せて導入する場合にはZEH補助金、そうでない場合は長期優良リフォーム補助金や子育てグリーン住宅支援事業などがあり、減税もされます。 | S58: 断熱性能を高めることは、温暖化対策としてメリットがあるだけでなく、冬は暖かく、夏は涼しく、快適に過ごすことができ、健康面でもメリットがあることがわかっています。新築に建て替える方法だけでなく、土台や柱などの耐震補強をしながら、壁や窓などを全面的に作り直すリフォームは、リノベーションとも呼ばれ、新築よりも安くできます。等級6は、現在の省エネ基準より、さらに暖房負荷を減らすことができます。 | T58: 断熱性能を高めることは、温暖化対策としてメリットがあるだけでなく、冬は暖かく、夏は涼しく、快適に過ごすことができ、健康面でもメリットがあることがわかっています。新築に建て替える方法だけでなく、土台や柱などの耐震補強をしながら、壁や窓などを全面的に作り直すリフォームは、リノベーションとも呼ばれ、新築よりも安くできます。等級6は、現在の省エネ基準より、さらに暖房負荷を減らすことができます。 | V58: wss | Z58: ="D6.scenario.defMeasures['"&C58&"'] = { "&B$2&":"""&B58&""", "&C$2&":"""&C58&""", "&D$2&":"""&CLEAN(SUBSTITUTE(D58,"""","'"))&""", "&I$2&":"""&I58&""", "&F$2&":"""&F58&""", "&G$2&":"""&CLEAN(SUBSTITUTE(G58,"""","'"))&""", "&K$2&":"""&K58&""", "&L$2&":"""&L58&""", "&M$2&":"""&M58&""", "&N$2&":"""&N58&""", "&O$2&":"""&O58&""", "&P$2&":"""&P58&""", "&Q$2&":"""&Q58&""", "&S$2&":"""&CLEAN(SUBSTITUTE(S58,"""","'"))&""", "&U$2&":"""&U58&""", "&V$2&":"""&V58&"""};" -> D6.scenario.defMeasures['mHTreformLV6'] = { mid:"225", name:"mHTreformLV6", title:"省エネ等級6相当の省エネ住宅にリフォームする", easyness:"1", refCons:"consHTsum", titleShort:"省エネ住宅等級6", level:"", figNum:"3", lifeTime:"20", price:"11000000", roanShow:"", standardType:"", subsidy :"太陽光も併せて導入する場合にはZEH補助金、そうでない場合は長期優良リフォーム補助金や子育てグリーン住宅支援事業などがあり、減税もされます。", advice:"断熱性能を高めることは、温暖化対策としてメリットがあるだけでなく、冬は暖かく、夏は涼しく、快適に過ごすことができ、健康面でもメリットがあることがわかっています。新築に建て替える方法だけでなく、土台や柱などの耐震補強をしながら、壁や窓などを全面的に作り直すリフォームは、リノベーションとも呼ばれ、新築よりも安くできます。等級6は、現在の省エネ基準より、さらに暖房負荷を減らすことができます。", lifestyle:"", season:"wss"}; | AB58: ="$defMeasures['"&C58&"'] = [ '"&B$2&"'=>"""&B58&""", '"&D$2&"'=>"""&CLEAN(SUBSTITUTE(D58,"""","'"))&""", '"&L$2&"'=>"""&L58&""", '"&S$2&"'=>"""&CLEAN(SUBSTITUTE(S58,"""","'"))&"""];" -> $defMeasures['mHTreformLV6'] = [ 'mid'=>"225", 'title'=>"省エネ等級6相当の省エネ住宅にリフォームする", 'figNum'=>"3", 'advice'=>"断熱性能を高めることは、温暖化対策としてメリットがあるだけでなく、冬は暖かく、夏は涼しく、快適に過ごすことができ、健康面でもメリットがあることがわかっています。新築に建て替える方法だけでなく、土台や柱などの耐震補強をしながら、壁や窓などを全面的に作り直すリフォームは、リノベーションとも呼ばれ、新築よりも安くできます。等級6は、現在の省エネ基準より、さらに暖房負荷を減らすことができます。"]; | AD58: 息をするたびに二酸化炭素が出てきますし、調理やストーブなどからも排ガスが出てきます。窓を開けたり、換気扇を使うのも一つの方法ですが、暖房時には温まった空気を捨ててしまうことにもなります。その熱まで回収しようというのですから、見事です。新築住宅で寒冷地を中心に普及しつつあります。
B59: 301 | C59: mPTstopPot | D59: 電気ポットで保温をしない | E59: 電気ポットで保温をしない | F59: consCKpot | G59: ポット保温しない | H59: ポット保温しない | I59: 2 | J59: 2 | L59: 17 | S59: 電気ポットでは、長時間保温をすると多くの電気が消費されます。必要に応じてお湯を沸かすようにするか、電気を使わない魔法瓶を活用してみてください。 | T59: 電気ポットでは、長時間保温をすると多くの電気が消費されます。必要に応じてお湯を沸かすようにするか、電気を使わない魔法瓶を活用してみてください。 | U59: 1 | V59: wss | Z59: ="D6.scenario.defMeasures['"&C59&"'] = { "&B$2&":"""&B59&""", "&C$2&":"""&C59&""", "&D$2&":"""&CLEAN(SUBSTITUTE(D59,"""","'"))&""", "&I$2&":"""&I59&""", "&F$2&":"""&F59&""", "&G$2&":"""&CLEAN(SUBSTITUTE(G59,"""","'"))&""", "&K$2&":"""&K59&""", "&L$2&":"""&L59&""", "&M$2&":"""&M59&""", "&N$2&":"""&N59&""", "&O$2&":"""&O59&""", "&P$2&":"""&P59&""", "&Q$2&":"""&Q59&""", "&S$2&":"""&CLEAN(SUBSTITUTE(S59,"""","'"))&""", "&U$2&":"""&U59&""", "&V$2&":"""&V59&"""};" -> D6.scenario.defMeasures['mPTstopPot'] = { mid:"301", name:"mPTstopPot", title:"電気ポットで保温をしない", easyness:"2", refCons:"consCKpot", titleShort:"ポット保温しない", level:"", figNum:"17", lifeTime:"", price:"", roanShow:"", standardType:"", subsidy :"", advice:"電気ポットでは、長時間保温をすると多くの電気が消費されます。必要に応じてお湯を沸かすようにするか、電気を使わない魔法瓶を活用してみてください。", lifestyle:"1", season:"wss"}; | AB59: ="$defMeasures['"&C59&"'] = [ '"&B$2&"'=>"""&B59&""", '"&D$2&"'=>"""&CLEAN(SUBSTITUTE(D59,"""","'"))&""", '"&L$2&"'=>"""&L59&""", '"&S$2&"'=>"""&CLEAN(SUBSTITUTE(S59,"""","'"))&"""];" -> $defMeasures['mPTstopPot'] = [ 'mid'=>"301", 'title'=>"電気ポットで保温をしない", 'figNum'=>"17", 'advice'=>"電気ポットでは、長時間保温をすると多くの電気が消費されます。必要に応じてお湯を沸かすようにするか、電気を使わない魔法瓶を活用してみてください。"]; | AD59: 電気ポットを保温し続けていると、保温のために、年間数千円の電気代がかかります。有名どころでは「てぃ◯～る」など、すぐに必要な分のお湯をわかすこともでき、保温の電気代が安くすみます。
B60: 302 | C60: mPTstopPotNight | D60: 外出時や夜間に電気ポットの保温を止める | E60: 外出時や夜間に電気ポットの保温を止める | F60: consCKpot | G60: 夜間保温停止 | H60: 夜間保温停止 | I60: 3 | J60: 3 | L60: 17 | S60: 外出時や夜間など、長時間お湯を使わない場合には、電気ポットを止めておくことで保温電力を削減できます。炊飯ジャーや、便座の保温なども、同様に止めておくほうが省エネになります。 | T60: 外出時や夜間など、長時間お湯を使わない場合には、電気ポットを止めておくことで保温電力を削減できます。炊飯ジャーや、便座の保温なども、同様に止めておくほうが省エネになります。 | U60: 1 | V60: wss | Z60: ="D6.scenario.defMeasures['"&C60&"'] = { "&B$2&":"""&B60&""", "&C$2&":"""&C60&""", "&D$2&":"""&CLEAN(SUBSTITUTE(D60,"""","'"))&""", "&I$2&":"""&I60&""", "&F$2&":"""&F60&""", "&G$2&":"""&CLEAN(SUBSTITUTE(G60,"""","'"))&""", "&K$2&":"""&K60&""", "&L$2&":"""&L60&""", "&M$2&":"""&M60&""", "&N$2&":"""&N60&""", "&O$2&":"""&O60&""", "&P$2&":"""&P60&""", "&Q$2&":"""&Q60&""", "&S$2&":"""&CLEAN(SUBSTITUTE(S60,"""","'"))&""", "&U$2&":"""&U60&""", "&V$2&":"""&V60&"""};" -> D6.scenario.defMeasures['mPTstopPotNight'] = { mid:"302", name:"mPTstopPotNight", title:"外出時や夜間に電気ポットの保温を止める", easyness:"3", refCons:"consCKpot", titleShort:"夜間保温停止", level:"", figNum:"17", lifeTime:"", price:"", roanShow:"", standardType:"", subsidy :"", advice:"外出時や夜間など、長時間お湯を使わない場合には、電気ポットを止めておくことで保温電力を削減できます。炊飯ジャーや、便座の保温なども、同様に止めておくほうが省エネになります。", lifestyle:"1", season:"wss"}; | AB60: ="$defMeasures['"&C60&"'] = [ '"&B$2&"'=>"""&B60&""", '"&D$2&"'=>"""&CLEAN(SUBSTITUTE(D60,"""","'"))&""", '"&L$2&"'=>"""&L60&""", '"&S$2&"'=>"""&CLEAN(SUBSTITUTE(S60,"""","'"))&"""];" -> $defMeasures['mPTstopPotNight'] = [ 'mid'=>"302", 'title'=>"外出時や夜間に電気ポットの保温を止める", 'figNum'=>"17", 'advice'=>"外出時や夜間など、長時間お湯を使わない場合には、電気ポットを止めておくことで保温電力を削減できます。炊飯ジャーや、便座の保温なども、同様に止めておくほうが省エネになります。"]; | AD60: 電気ポットを保温し続けていると、保温のために、年間数千円の電気代がかかります。せめて使わない時には止めておきましょう。暖房代わりに使うとしても、少しロスが大きい使い方です。
B61: 303 | C61: mPTstopRiceCooker | D61: 炊飯ジャーの保温をやめる | E61: 炊飯ジャーの保温をやめる | F61: consCKrice | G61: ジャー保温 | H61: ジャー保温 | I61: 3 | J61: 3 | L61: 18 | S61: 暖かいご飯を食べるのに、炊飯ジャーで保温をするより、食べる直前に電子レンジで温め直すほうが省エネになります。長時間にわたり高温で保温をすると、ご飯が変色することもあり、常温で置いておくほうがおいしく食べられます。 | T61: 暖かいご飯を食べるのに、炊飯ジャーで保温をするより、食べる直前に電子レンジで温め直すほうが省エネになります。長時間にわたり高温で保温をすると、ご飯が変色することもあり、常温で置いておくほうがおいしく食べられます。 | U61: 1 | V61: wss | Z61: ="D6.scenario.defMeasures['"&C61&"'] = { "&B$2&":"""&B61&""", "&C$2&":"""&C61&""", "&D$2&":"""&CLEAN(SUBSTITUTE(D61,"""","'"))&""", "&I$2&":"""&I61&""", "&F$2&":"""&F61&""", "&G$2&":"""&CLEAN(SUBSTITUTE(G61,"""","'"))&""", "&K$2&":"""&K61&""", "&L$2&":"""&L61&""", "&M$2&":"""&M61&""", "&N$2&":"""&N61&""", "&O$2&":"""&O61&""", "&P$2&":"""&P61&""", "&Q$2&":"""&Q61&""", "&S$2&":"""&CLEAN(SUBSTITUTE(S61,"""","'"))&""", "&U$2&":"""&U61&""", "&V$2&":"""&V61&"""};" -> D6.scenario.defMeasures['mPTstopRiceCooker'] = { mid:"303", name:"mPTstopRiceCooker", title:"炊飯ジャーの保温をやめる", easyness:"3", refCons:"consCKrice", titleShort:"ジャー保温", level:"", figNum:"18", lifeTime:"", price:"", roanShow:"", standardType:"", subsidy :"", advice:"暖かいご飯を食べるのに、炊飯ジャーで保温をするより、食べる直前に電子レンジで温め直すほうが省エネになります。長時間にわたり高温で保温をすると、ご飯が変色することもあり、常温で置いておくほうがおいしく食べられます。", lifestyle:"1", season:"wss"}; | AB61: ="$defMeasures['"&C61&"'] = [ '"&B$2&"'=>"""&B61&""", '"&D$2&"'=>"""&CLEAN(SUBSTITUTE(D61,"""","'"))&""", '"&L$2&"'=>"""&L61&""", '"&S$2&"'=>"""&CLEAN(SUBSTITUTE(S61,"""","'"))&"""];" -> $defMeasures['mPTstopRiceCooker'] = [ 'mid'=>"303", 'title'=>"炊飯ジャーの保温をやめる", 'figNum'=>"18", 'advice'=>"暖かいご飯を食べるのに、炊飯ジャーで保温をするより、食べる直前に電子レンジで温め直すほうが省エネになります。長時間にわたり高温で保温をすると、ご飯が変色することもあり、常温で置いておくほうがおいしく食べられます。"]; | AD61: 保温をせずにチンするほうが、電気の消費量は少なくなります。保温し続けていると、乾燥したり黄ばんだりするので、その面でも止めておいたほうがいいです。
B62: 304 | C62: mPTreplacePot | D62: 省エネタイプの電気ポットに買い替える | E62: 省エネタイプの電気ポットに買い替える | F62: consCKpot | G62: 省エネ電気ポット | H62: 省エネ電気ポット | I62: 2 | J62: 2 | L62: 17 | M62: 10 | N62: 20000 | P62: 既存型 | S62: 魔法瓶のような断熱がされている電気ポットがあり、保温の電気消費を少なくすることができます。カタログに保温消費電力が表示されていいますので、これを参考にして選んでください。 | T62: 魔法瓶のような断熱がされている電気ポットがあり、保温の電気消費を少なくすることができます。カタログに保温消費電力が表示されていいますので、これを参考にして選んでください。 | V62: wss | Z62: ="D6.scenario.defMeasures['"&C62&"'] = { "&B$2&":"""&B62&""", "&C$2&":"""&C62&""", "&D$2&":"""&CLEAN(SUBSTITUTE(D62,"""","'"))&""", "&I$2&":"""&I62&""", "&F$2&":"""&F62&""", "&G$2&":"""&CLEAN(SUBSTITUTE(G62,"""","'"))&""", "&K$2&":"""&K62&""", "&L$2&":"""&L62&""", "&M$2&":"""&M62&""", "&N$2&":"""&N62&""", "&O$2&":"""&O62&""", "&P$2&":"""&P62&""", "&Q$2&":"""&Q62&""", "&S$2&":"""&CLEAN(SUBSTITUTE(S62,"""","'"))&""", "&U$2&":"""&U62&""", "&V$2&":"""&V62&"""};" -> D6.scenario.defMeasures['mPTreplacePot'] = { mid:"304", name:"mPTreplacePot", title:"省エネタイプの電気ポットに買い替える", easyness:"2", refCons:"consCKpot", titleShort:"省エネ電気ポット", level:"", figNum:"17", lifeTime:"10", price:"20000", roanShow:"", standardType:"既存型", subsidy :"", advice:"魔法瓶のような断熱がされている電気ポットがあり、保温の電気消費を少なくすることができます。カタログに保温消費電力が表示されていいますので、これを参考にして選んでください。", lifestyle:"", season:"wss"}; | AB62: ="$defMeasures['"&C62&"'] = [ '"&B$2&"'=>"""&B62&""", '"&D$2&"'=>"""&CLEAN(SUBSTITUTE(D62,"""","'"))&""", '"&L$2&"'=>"""&L62&""", '"&S$2&"'=>"""&CLEAN(SUBSTITUTE(S62,"""","'"))&"""];" -> $defMeasures['mPTreplacePot'] = [ 'mid'=>"304", 'title'=>"省エネタイプの電気ポットに買い替える", 'figNum'=>"17", 'advice'=>"魔法瓶のような断熱がされている電気ポットがあり、保温の電気消費を少なくすることができます。カタログに保温消費電力が表示されていいますので、これを参考にして選んでください。"]; | AD62: 電気ポットが魔法瓶だったら省エネなのに、といわれ続けて、10年ほど前に完成しています。魔法瓶よりは、構造上熱が逃げやすいようですが、消費電力は大きく削減できます。
B63: 305 | C63: mCKflame | D63: 鍋から炎がはみ出さないようにする | E63: 鍋から炎がはみ出さないようにする | F63: consCKcook | G63: 調理炎調整 | H63: 調理炎調整 | I63: 2 | J63: 2 | L63: 14 | S63: 鍋底から炎がはみ出すのは、ガスが無駄になるだけで、調理時間の短縮にはなりません。鍋底から炎がはみ出さない程度に調節して使いましょう。このほかにも、段取りよく調理をする工夫によって、ガスの消費を減らすことができます。 | T63: 鍋底から炎がはみ出すのは、ガスが無駄になるだけで、調理時間の短縮にはなりません。鍋底から炎がはみ出さない程度に調節して使いましょう。このほかにも、段取りよく調理をする工夫によって、ガスの消費を減らすことができます。 | U63: 1 | V63: wss | Z63: ="D6.scenario.defMeasures['"&C63&"'] = { "&B$2&":"""&B63&""", "&C$2&":"""&C63&""", "&D$2&":"""&CLEAN(SUBSTITUTE(D63,"""","'"))&""", "&I$2&":"""&I63&""", "&F$2&":"""&F63&""", "&G$2&":"""&CLEAN(SUBSTITUTE(G63,"""","'"))&""", "&K$2&":"""&K63&""", "&L$2&":"""&L63&""", "&M$2&":"""&M63&""", "&N$2&":"""&N63&""", "&O$2&":"""&O63&""", "&P$2&":"""&P63&""", "&Q$2&":"""&Q63&""", "&S$2&":"""&CLEAN(SUBSTITUTE(S63,"""","'"))&""", "&U$2&":"""&U63&""", "&V$2&":"""&V63&"""};" -> D6.scenario.defMeasures['mCKflame'] = { mid:"305", name:"mCKflame", title:"鍋から炎がはみ出さないようにする", easyness:"2", refCons:"consCKcook", titleShort:"調理炎調整", level:"", figNum:"14", lifeTime:"", price:"", roanShow:"", standardType:"", subsidy :"", advice:"鍋底から炎がはみ出すのは、ガスが無駄になるだけで、調理時間の短縮にはなりません。鍋底から炎がはみ出さない程度に調節して使いましょう。このほかにも、段取りよく調理をする工夫によって、ガスの消費を減らすことができます。", lifestyle:"1", season:"wss"}; | AB63: ="$defMeasures['"&C63&"'] = [ '"&B$2&"'=>"""&B63&""", '"&D$2&"'=>"""&CLEAN(SUBSTITUTE(D63,"""","'"))&""", '"&L$2&"'=>"""&L63&""", '"&S$2&"'=>"""&CLEAN(SUBSTITUTE(S63,"""","'"))&"""];" -> $defMeasures['mCKflame'] = [ 'mid'=>"305", 'title'=>"鍋から炎がはみ出さないようにする", 'figNum'=>"14", 'advice'=>"鍋底から炎がはみ出すのは、ガスが無駄になるだけで、調理時間の短縮にはなりません。鍋底から炎がはみ出さない程度に調節して使いましょう。このほかにも、段取りよく調理をする工夫によって、ガスの消費を減らすことができます。"]; | AD63: 炎の温度が一番高いのは、輝いている一番先端です。その部分が鍋にかかっていないというのは、無駄にしているということです。少しひねるだけなので、調節してやってください。
B64: 401 | C64: mDRsolar | D64: 晴れた日は衣類乾燥機や乾燥機能を使わずに天日乾燥させる | E64: 晴れた日は衣類乾燥機や乾燥機能を使わずに天日乾燥させる | F64: consDRsum | G64: 天日干し | H64: 天日干し | I64: 2 | J64: 2 | L64: 16 | S64: 衣類の乾燥機能は便利ですが、洗濯の10倍以上のエネルギーがかかります。なるべく天日で乾かすようにし、乾燥機能を使わないことが省エネです。 | T64: 衣類の乾燥機能は便利ですが、洗濯の10倍以上のエネルギーがかかります。なるべく天日で乾かすようにし、乾燥機能を使わないことが省エネです。 | U64: 1 | V64: wss | Z64: ="D6.scenario.defMeasures['"&C64&"'] = { "&B$2&":"""&B64&""", "&C$2&":"""&C64&""", "&D$2&":"""&CLEAN(SUBSTITUTE(D64,"""","'"))&""", "&I$2&":"""&I64&""", "&F$2&":"""&F64&""", "&G$2&":"""&CLEAN(SUBSTITUTE(G64,"""","'"))&""", "&K$2&":"""&K64&""", "&L$2&":"""&L64&""", "&M$2&":"""&M64&""", "&N$2&":"""&N64&""", "&O$2&":"""&O64&""", "&P$2&":"""&P64&""", "&Q$2&":"""&Q64&""", "&S$2&":"""&CLEAN(SUBSTITUTE(S64,"""","'"))&""", "&U$2&":"""&U64&""", "&V$2&":"""&V64&"""};" -> D6.scenario.defMeasures['mDRsolar'] = { mid:"401", name:"mDRsolar", title:"晴れた日は衣類乾燥機や乾燥機能を使わずに天日乾燥させる", easyness:"2", refCons:"consDRsum", titleShort:"天日干し", level:"", figNum:"16", lifeTime:"", price:"", roanShow:"", standardType:"", subsidy :"", advice:"衣類の乾燥機能は便利ですが、洗濯の10倍以上のエネルギーがかかります。なるべく天日で乾かすようにし、乾燥機能を使わないことが省エネです。", lifestyle:"1", season:"wss"}; | AB64: ="$defMeasures['"&C64&"'] = [ '"&B$2&"'=>"""&B64&""", '"&D$2&"'=>"""&CLEAN(SUBSTITUTE(D64,"""","'"))&""", '"&L$2&"'=>"""&L64&""", '"&S$2&"'=>"""&CLEAN(SUBSTITUTE(S64,"""","'"))&"""];" -> $defMeasures['mDRsolar'] = [ 'mid'=>"401", 'title'=>"晴れた日は衣類乾燥機や乾燥機能を使わずに天日乾燥させる", 'figNum'=>"16", 'advice'=>"衣類の乾燥機能は便利ですが、洗濯の10倍以上のエネルギーがかかります。なるべく天日で乾かすようにし、乾燥機能を使わないことが省エネです。"]; | AD64: 雨の日でも雨があたらない場所なら、干しておくと少しは乾きます。冬場は乾きにくいですが、エアコン暖房をかけた部屋で干すと、乾燥もやわらぐメリットもあります。<br> 1回につき、テレビ40時間分くらいの電気を消費します。これも一つの「自然エネルギーの利用」と言えます。
B65: 402 | C65: mDRheatPump | D65: ヒートポンプ式の衣類乾燥ができる洗濯機に買い替える | E65: ヒートポンプ式の衣類乾燥ができる洗濯機に買い替える | F65: consDRsum | G65: ヒートポンプ乾燥 | H65: ヒートポンプ乾燥 | I65: 1 | J65: 1 | L65: 16 | M65: 10 | N65: 140000 | S65: 衣類乾燥機や乾燥機能付き洗濯機の中で、ヒートポンプ式のものは、通常の乾燥機に比べてエネルギー消費が半分程度で済みます。よく乾燥機能を利用する場合には、光熱費の削減額も大きく効いてきます。ただし、乾燥機能自体が多くのエネルギーを使うため、なるべく乾燥機能を使わないことが望ましいです。 | T65: 衣類乾燥機や乾燥機能付き洗濯機の中で、ヒートポンプ式のものは、通常の乾燥機に比べてエネルギー消費が半分程度で済みます。よく乾燥機能を利用する場合には、光熱費の削減額も大きく効いてきます。ただし、乾燥機能自体が多くのエネルギーを使うため、なるべく乾燥機能を使わないことが望ましいです。 | V65: wss | Z65: ="D6.scenario.defMeasures['"&C65&"'] = { "&B$2&":"""&B65&""", "&C$2&":"""&C65&""", "&D$2&":"""&CLEAN(SUBSTITUTE(D65,"""","'"))&""", "&I$2&":"""&I65&""", "&F$2&":"""&F65&""", "&G$2&":"""&CLEAN(SUBSTITUTE(G65,"""","'"))&""", "&K$2&":"""&K65&""", "&L$2&":"""&L65&""", "&M$2&":"""&M65&""", "&N$2&":"""&N65&""", "&O$2&":"""&O65&""", "&P$2&":"""&P65&""", "&Q$2&":"""&Q65&""", "&S$2&":"""&CLEAN(SUBSTITUTE(S65,"""","'"))&""", "&U$2&":"""&U65&""", "&V$2&":"""&V65&"""};" -> D6.scenario.defMeasures['mDRheatPump'] = { mid:"402", name:"mDRheatPump", title:"ヒートポンプ式の衣類乾燥ができる洗濯機に買い替える", easyness:"1", refCons:"consDRsum", titleShort:"ヒートポンプ乾燥", level:"", figNum:"16", lifeTime:"10", price:"140000", roanShow:"", standardType:"", subsidy :"", advice:"衣類乾燥機や乾燥機能付き洗濯機の中で、ヒートポンプ式のものは、通常の乾燥機に比べてエネルギー消費が半分程度で済みます。よく乾燥機能を利用する場合には、光熱費の削減額も大きく効いてきます。ただし、乾燥機能自体が多くのエネルギーを使うため、なるべく乾燥機能を使わないことが望ましいです。", lifestyle:"", season:"wss"}; | AB65: ="$defMeasures['"&C65&"'] = [ '"&B$2&"'=>"""&B65&""", '"&D$2&"'=>"""&CLEAN(SUBSTITUTE(D65,"""","'"))&""", '"&L$2&"'=>"""&L65&""", '"&S$2&"'=>"""&CLEAN(SUBSTITUTE(S65,"""","'"))&"""];" -> $defMeasures['mDRheatPump'] = [ 'mid'=>"402", 'title'=>"ヒートポンプ式の衣類乾燥ができる洗濯機に買い替える", 'figNum'=>"16", 'advice'=>"衣類乾燥機や乾燥機能付き洗濯機の中で、ヒートポンプ式のものは、通常の乾燥機に比べてエネルギー消費が半分程度で済みます。よく乾燥機能を利用する場合には、光熱費の削減額も大きく効いてきます。ただし、乾燥機能自体が多くのエネルギーを使うため、なるべく乾燥機能を使わないことが望ましいです。"]; | AD65: 洗濯機も省エネ化が進みましたが、その一つが乾燥機能のヒートポンプ化です。値段が高いのでまだ限られた機種ですし、いままで乾燥機を使ってこなかった家庭にとっては、増エネになりますので、注意してください。
B66: 501 | C66: mLIceilingLED | D66: 蛍光灯器具をLEDシーリングライトに付け替える | E66: 蛍光灯器具をLEDシーリングライトに付け替える | F66: consLI | G66: LEDライト | H66: LEDライト | I66: 4 | J66: 4 | L66: 6 | M66: 20 | P66: 蛍光灯 | S66: LEDの省エネ性能は高く、長持ちします。蛍光灯と異なり、照明器具のカバーの中に虫が入らないため、掃除の手間も省くことができます。照明器具から取り替えますが、ソケットがあるので、通常は電気屋に頼まなくても自分で交換できます。光の色合いなども調整したり、細かく明るさを調整したりすることもできます。2027年度までに計億棟の新規の製造・輸入は禁止され、LEDに置き換わります。 | T66: LEDの省エネ性能は高く、長持ちします。蛍光灯と異なり、照明器具のカバーの中に虫が入らないため、掃除の手間も省くことができます。照明器具から取り替えますが、ソケットがあるので、通常は電気屋に頼まなくても自分で交換できます。光の色合いなども調整したり、細かく明るさを調整したりすることもできます。 | V66: wss | Z66: ="D6.scenario.defMeasures['"&C66&"'] = { "&B$2&":"""&B66&""", "&C$2&":"""&C66&""", "&D$2&":"""&CLEAN(SUBSTITUTE(D66,"""","'"))&""", "&I$2&":"""&I66&""", "&F$2&":"""&F66&""", "&G$2&":"""&CLEAN(SUBSTITUTE(G66,"""","'"))&""", "&K$2&":"""&K66&""", "&L$2&":"""&L66&""", "&M$2&":"""&M66&""", "&N$2&":"""&N66&""", "&O$2&":"""&O66&""", "&P$2&":"""&P66&""", "&Q$2&":"""&Q66&""", "&S$2&":"""&CLEAN(SUBSTITUTE(S66,"""","'"))&""", "&U$2&":"""&U66&""", "&V$2&":"""&V66&"""};" -> D6.scenario.defMeasures['mLIceilingLED'] = { mid:"501", name:"mLIceilingLED", title:"蛍光灯器具をLEDシーリングライトに付け替える", easyness:"4", refCons:"consLI", titleShort:"LEDライト", level:"", figNum:"6", lifeTime:"20", price:"", roanShow:"", standardType:"蛍光灯", subsidy :"", advice:"LEDの省エネ性能は高く、長持ちします。蛍光灯と異なり、照明器具のカバーの中に虫が入らないため、掃除の手間も省くことができます。照明器具から取り替えますが、ソケットがあるので、通常は電気屋に頼まなくても自分で交換できます。光の色合いなども調整したり、細かく明るさを調整したりすることもできます。2027年度までに計億棟の新規の製造・輸入は禁止され、LEDに置き換わります。", lifestyle:"", season:"wss"}; | AB66: ="$defMeasures['"&C66&"'] = [ '"&B$2&"'=>"""&B66&""", '"&D$2&"'=>"""&CLEAN(SUBSTITUTE(D66,"""","'"))&""", '"&L$2&"'=>"""&L66&""", '"&S$2&"'=>"""&CLEAN(SUBSTITUTE(S66,"""","'"))&"""];" -> $defMeasures['mLIceilingLED'] = [ 'mid'=>"501", 'title'=>"蛍光灯器具をLEDシーリングライトに付け替える", 'figNum'=>"6", 'advice'=>"LEDの省エネ性能は高く、長持ちします。蛍光灯と異なり、照明器具のカバーの中に虫が入らないため、掃除の手間も省くことができます。照明器具から取り替えますが、ソケットがあるので、通常は電気屋に頼まなくても自分で交換できます。光の色合いなども調整したり、細かく明るさを調整したりすることもできます。2027年度までに計億棟の新規の製造・輸入は禁止され、LEDに置き換わります。"]; | AD66: 省エネなのはもちろんですが、電気屋さんによると、虫が入らないので掃除をしなくてもいいのが、喜ばれているようです。蛍光灯のシーリングライトは、虫が入り込みやすく、大掃除で取り外そうとしてカバーを壊してしまう人が多いそうです。
B67: 502 | C67: mLILED | D67: LEDに付け替える | E67: LEDに付け替える | F67: consLI | G67: LED電球 | H67: LED電球 | I67: 2 | J67: 2 | L67: 5 | M67: 40000h | N67: 1500 | P67: 電球 | S67: LED電球は、白熱電球と同じソケットを使っており、電球が切れたときにそのまま付け替えることができます。電気の消費を8割削減でき、寿命は40倍以上になります。 | T67: LED電球は、白熱電球と同じソケットを使っており、電球が切れたときにそのまま付け替えることができます。電気の消費を8割削減でき、寿命は40倍以上になります。 | V67: wss | Z67: ="D6.scenario.defMeasures['"&C67&"'] = { "&B$2&":"""&B67&""", "&C$2&":"""&C67&""", "&D$2&":"""&CLEAN(SUBSTITUTE(D67,"""","'"))&""", "&I$2&":"""&I67&""", "&F$2&":"""&F67&""", "&G$2&":"""&CLEAN(SUBSTITUTE(G67,"""","'"))&""", "&K$2&":"""&K67&""", "&L$2&":"""&L67&""", "&M$2&":"""&M67&""", "&N$2&":"""&N67&""", "&O$2&":"""&O67&""", "&P$2&":"""&P67&""", "&Q$2&":"""&Q67&""", "&S$2&":"""&CLEAN(SUBSTITUTE(S67,"""","'"))&""", "&U$2&":"""&U67&""", "&V$2&":"""&V67&"""};" -> D6.scenario.defMeasures['mLILED'] = { mid:"502", name:"mLILED", title:"LEDに付け替える", easyness:"2", refCons:"consLI", titleShort:"LED電球", level:"", figNum:"5", lifeTime:"40000h", price:"1500", roanShow:"", standardType:"電球", subsidy :"", advice:"LED電球は、白熱電球と同じソケットを使っており、電球が切れたときにそのまま付け替えることができます。電気の消費を8割削減でき、寿命は40倍以上になります。", lifestyle:"", season:"wss"}; | AB67: ="$defMeasures['"&C67&"'] = [ '"&B$2&"'=>"""&B67&""", '"&D$2&"'=>"""&CLEAN(SUBSTITUTE(D67,"""","'"))&""", '"&L$2&"'=>"""&L67&""", '"&S$2&"'=>"""&CLEAN(SUBSTITUTE(S67,"""","'"))&"""];" -> $defMeasures['mLILED'] = [ 'mid'=>"502", 'title'=>"LEDに付け替える", 'figNum'=>"5", 'advice'=>"LED電球は、白熱電球と同じソケットを使っており、電球が切れたときにそのまま付け替えることができます。電気の消費を8割削減でき、寿命は40倍以上になります。"]; | AD67: 白熱電球は手で触れないほどの、ヒータのようなものです。夏場につけていると、まさに暖房器具をつけているような暑さが伝わります。LEDは発熱が少なく、省エネに加えて、夏に涼しく過ごせるというメリットもあります。
B68: 503 | C68: mLIsensor | D68: 人感センサー式に付け替える | E68: 人感センサー式に付け替える | F68: consLI | G68: センサー照明 | H68: センサー照明 | I68: 2 | J68: 2 | L68: 5 | M68: 10 | N68: 1500 | P68: 電球 | S68: 玄関の照明を、センサー式にすると、人を感知して点灯するため、防犯性能が高くなります。電気が流れている時間が大幅に減り、省エネになります。また、廊下は人が通るときだけ明るくなればいいので、人感センサーの照明を設置をして、人が通るときだけ照らすことも実用的で省エネになります。 | T68: 玄関の照明を、センサー式にすると、人を感知して点灯するため、防犯性能が高くなります。電気が流れている時間が大幅に減り、省エネになります。また、廊下は人が通るときだけ明るくなればいいので、人感センサーの照明を設置をして、人が通るときだけ照らすことも実用的で省エネになります。 | V68: wss | Z68: ="D6.scenario.defMeasures['"&C68&"'] = { "&B$2&":"""&B68&""", "&C$2&":"""&C68&""", "&D$2&":"""&CLEAN(SUBSTITUTE(D68,"""","'"))&""", "&I$2&":"""&I68&""", "&F$2&":"""&F68&""", "&G$2&":"""&CLEAN(SUBSTITUTE(G68,"""","'"))&""", "&K$2&":"""&K68&""", "&L$2&":"""&L68&""", "&M$2&":"""&M68&""", "&N$2&":"""&N68&""", "&O$2&":"""&O68&""", "&P$2&":"""&P68&""", "&Q$2&":"""&Q68&""", "&S$2&":"""&CLEAN(SUBSTITUTE(S68,"""","'"))&""", "&U$2&":"""&U68&""", "&V$2&":"""&V68&"""};" -> D6.scenario.defMeasures['mLIsensor'] = { mid:"503", name:"mLIsensor", title:"人感センサー式に付け替える", easyness:"2", refCons:"consLI", titleShort:"センサー照明", level:"", figNum:"5", lifeTime:"10", price:"1500", roanShow:"", standardType:"電球", subsidy :"", advice:"玄関の照明を、センサー式にすると、人を感知して点灯するため、防犯性能が高くなります。電気が流れている時間が大幅に減り、省エネになります。また、廊下は人が通るときだけ明るくなればいいので、人感センサーの照明を設置をして、人が通るときだけ照らすことも実用的で省エネになります。", lifestyle:"", season:"wss"}; | AB68: ="$defMeasures['"&C68&"'] = [ '"&B$2&"'=>"""&B68&""", '"&D$2&"'=>"""&CLEAN(SUBSTITUTE(D68,"""","'"))&""", '"&L$2&"'=>"""&L68&""", '"&S$2&"'=>"""&CLEAN(SUBSTITUTE(S68,"""","'"))&"""];" -> $defMeasures['mLIsensor'] = [ 'mid'=>"503", 'title'=>"人感センサー式に付け替える", 'figNum'=>"5", 'advice'=>"玄関の照明を、センサー式にすると、人を感知して点灯するため、防犯性能が高くなります。電気が流れている時間が大幅に減り、省エネになります。また、廊下は人が通るときだけ明るくなればいいので、人感センサーの照明を設置をして、人が通るときだけ照らすことも実用的で省エネになります。"]; | AD68: トイレの照明では苦い思いをした人が多いと思われるセンサーですが、玄関や廊下、門灯などにはうってつけです。どろぼうも、突然点く照明は、やりにくいという話です（直接聞いたわけではありませんが）。<br> ただあまりこうした自動消灯になれてしまうと、消さない習慣がついてしまうこともあり、注意が必要です。
B69: 504 | C69: mLItime | D69: 照明を使う時間を1時間短くする | E69: 照明を使う時間を1時間短くする | F69: consLI | G69: 照明短縮 | H69: 照明短縮 | I69: 3 | J69: 3 | L69: 6 | S69: 照明を点けるときに多くの電気が流れますが、ほんの一瞬であるため、結果的にこまめに消すことで省エネになります。部屋を離れるときには必ず照明を消す習慣をつけることが大切です。また、夜に明るい光をあびると、睡眠のサイクルが狂ってしまい、身体にとってよくないことになります。 | T69: 照明を点けるときに多くの電気が流れますが、ほんの一瞬であるため、結果的にこまめに消すことで省エネになります。部屋を離れるときには必ず照明を消す習慣をつけることが大切です。また、夜に明るい光をあびると、睡眠のサイクルが狂ってしまい、身体にとってよくないことになります。 | U69: 1 | V69: wss | Z69: ="D6.scenario.defMeasures['"&C69&"'] = { "&B$2&":"""&B69&""", "&C$2&":"""&C69&""", "&D$2&":"""&CLEAN(SUBSTITUTE(D69,"""","'"))&""", "&I$2&":"""&I69&""", "&F$2&":"""&F69&""", "&G$2&":"""&CLEAN(SUBSTITUTE(G69,"""","'"))&""", "&K$2&":"""&K69&""", "&L$2&":"""&L69&""", "&M$2&":"""&M69&""", "&N$2&":"""&N69&""", "&O$2&":"""&O69&""", "&P$2&":"""&P69&""", "&Q$2&":"""&Q69&""", "&S$2&":"""&CLEAN(SUBSTITUTE(S69,"""","'"))&""", "&U$2&":"""&U69&""", "&V$2&":"""&V69&"""};" -> D6.scenario.defMeasures['mLItime'] = { mid:"504", name:"mLItime", title:"照明を使う時間を1時間短くする", easyness:"3", refCons:"consLI", titleShort:"照明短縮", level:"", figNum:"6", lifeTime:"", price:"", roanShow:"", standardType:"", subsidy :"", advice:"照明を点けるときに多くの電気が流れますが、ほんの一瞬であるため、結果的にこまめに消すことで省エネになります。部屋を離れるときには必ず照明を消す習慣をつけることが大切です。また、夜に明るい光をあびると、睡眠のサイクルが狂ってしまい、身体にとってよくないことになります。", lifestyle:"1", season:"wss"}; | AB69: ="$defMeasures['"&C69&"'] = [ '"&B$2&"'=>"""&B69&""", '"&D$2&"'=>"""&CLEAN(SUBSTITUTE(D69,"""","'"))&""", '"&L$2&"'=>"""&L69&""", '"&S$2&"'=>"""&CLEAN(SUBSTITUTE(S69,"""","'"))&"""];" -> $defMeasures['mLItime'] = [ 'mid'=>"504", 'title'=>"照明を使う時間を1時間短くする", 'figNum'=>"6", 'advice'=>"照明を点けるときに多くの電気が流れますが、ほんの一瞬であるため、結果的にこまめに消すことで省エネになります。部屋を離れるときには必ず照明を消す習慣をつけることが大切です。また、夜に明るい光をあびると、睡眠のサイクルが狂ってしまい、身体にとってよくないことになります。"]; | AD69: 暖房なら暖気が残るので、早めに消すということができますが、照明は難しいですね。「早く寝ろ」ということでしょうか。それはそれで幸せかもしれません。
B70: 505 | C70: mLIoff | D70: 部屋を出るときに照明を消す | E70: 部屋を出るときに照明を消す | F70: consLIsum | G70: 照明消灯 | H70: 照明消灯 | I70: 4 | J70: 4 | L70: 6 | S70: 部屋を離れるときには、こまめに照明を消すようにしましょう。点けるときに多くの電気が流れますが、ほんの一瞬であるため、すぐに戻ってくる予定でも、こまめに照明を消すほうが省エネになります。 | T70: 部屋を離れるときには、こまめに照明を消すようにしましょう。点けるときに多くの電気が流れますが、ほんの一瞬であるため、すぐに戻ってくる予定でも、こまめに照明を消すほうが省エネになります。 | U70: 1 | V70: wss | Z70: ="D6.scenario.defMeasures['"&C70&"'] = { "&B$2&":"""&B70&""", "&C$2&":"""&C70&""", "&D$2&":"""&CLEAN(SUBSTITUTE(D70,"""","'"))&""", "&I$2&":"""&I70&""", "&F$2&":"""&F70&""", "&G$2&":"""&CLEAN(SUBSTITUTE(G70,"""","'"))&""", "&K$2&":"""&K70&""", "&L$2&":"""&L70&""", "&M$2&":"""&M70&""", "&N$2&":"""&N70&""", "&O$2&":"""&O70&""", "&P$2&":"""&P70&""", "&Q$2&":"""&Q70&""", "&S$2&":"""&CLEAN(SUBSTITUTE(S70,"""","'"))&""", "&U$2&":"""&U70&""", "&V$2&":"""&V70&"""};" -> D6.scenario.defMeasures['mLIoff'] = { mid:"505", name:"mLIoff", title:"部屋を出るときに照明を消す", easyness:"4", refCons:"consLIsum", titleShort:"照明消灯", level:"", figNum:"6", lifeTime:"", price:"", roanShow:"", standardType:"", subsidy :"", advice:"部屋を離れるときには、こまめに照明を消すようにしましょう。点けるときに多くの電気が流れますが、ほんの一瞬であるため、すぐに戻ってくる予定でも、こまめに照明を消すほうが省エネになります。", lifestyle:"1", season:"wss"}; | AB70: ="$defMeasures['"&C70&"'] = [ '"&B$2&"'=>"""&B70&""", '"&D$2&"'=>"""&CLEAN(SUBSTITUTE(D70,"""","'"))&""", '"&L$2&"'=>"""&L70&""", '"&S$2&"'=>"""&CLEAN(SUBSTITUTE(S70,"""","'"))&"""];" -> $defMeasures['mLIoff'] = [ 'mid'=>"505", 'title'=>"部屋を出るときに照明を消す", 'figNum'=>"6", 'advice'=>"部屋を離れるときには、こまめに照明を消すようにしましょう。点けるときに多くの電気が流れますが、ほんの一瞬であるため、すぐに戻ってくる予定でも、こまめに照明を消すほうが省エネになります。"]; | AD70: 人がいない部屋は消す
B71: 601 | C71: mTVreplace | D71: 省エネ性能の高いテレビに買い替える | E71: 省エネ性能の高いテレビに買い替える | F71: consTV | G71: 省エネテレビ購入 | H71: 省エネテレビ購入 | I71: 2 | J71: 2 | L71: 7 | M71: 10 | N71: 50000 | P71: 普及型 | S71: テレビの省エネ性能が向上しているため、以前と比べて同じサイズであれば半分以下の消費電力になるタイプが販売されています。店頭では、なるべく年間電気代が安いテレビを選ぶようにしてください。 | T71: テレビの省エネ性能が向上しているため、以前と比べて同じサイズであれば半分以下の消費電力になるタイプが販売されています。店頭では、なるべく年間電気代が安いテレビを選ぶようにしてください。 | V71: wss | Z71: ="D6.scenario.defMeasures['"&C71&"'] = { "&B$2&":"""&B71&""", "&C$2&":"""&C71&""", "&D$2&":"""&CLEAN(SUBSTITUTE(D71,"""","'"))&""", "&I$2&":"""&I71&""", "&F$2&":"""&F71&""", "&G$2&":"""&CLEAN(SUBSTITUTE(G71,"""","'"))&""", "&K$2&":"""&K71&""", "&L$2&":"""&L71&""", "&M$2&":"""&M71&""", "&N$2&":"""&N71&""", "&O$2&":"""&O71&""", "&P$2&":"""&P71&""", "&Q$2&":"""&Q71&""", "&S$2&":"""&CLEAN(SUBSTITUTE(S71,"""","'"))&""", "&U$2&":"""&U71&""", "&V$2&":"""&V71&"""};" -> D6.scenario.defMeasures['mTVreplace'] = { mid:"601", name:"mTVreplace", title:"省エネ性能の高いテレビに買い替える", easyness:"2", refCons:"consTV", titleShort:"省エネテレビ購入", level:"", figNum:"7", lifeTime:"10", price:"50000", roanShow:"", standardType:"普及型", subsidy :"", advice:"テレビの省エネ性能が向上しているため、以前と比べて同じサイズであれば半分以下の消費電力になるタイプが販売されています。店頭では、なるべく年間電気代が安いテレビを選ぶようにしてください。", lifestyle:"", season:"wss"}; | AB71: ="$defMeasures['"&C71&"'] = [ '"&B$2&"'=>"""&B71&""", '"&D$2&"'=>"""&CLEAN(SUBSTITUTE(D71,"""","'"))&""", '"&L$2&"'=>"""&L71&""", '"&S$2&"'=>"""&CLEAN(SUBSTITUTE(S71,"""","'"))&"""];" -> $defMeasures['mTVreplace'] = [ 'mid'=>"601", 'title'=>"省エネ性能の高いテレビに買い替える", 'figNum'=>"7", 'advice'=>"テレビの省エネ性能が向上しているため、以前と比べて同じサイズであれば半分以下の消費電力になるタイプが販売されています。店頭では、なるべく年間電気代が安いテレビを選ぶようにしてください。"]; | AD71: テレビを買いかえる
B72: 602 | C72: mTVradio | D72: テレビの時間の半分をラジオにする | E72: テレビの時間の半分をラジオにする | F72: consTVsum | G72: ラジオ | H72: ラジオ | I72: 1 | J72: 1 | L72: 7 | S72: テレビは画面を映し出す必要があるため、ラジオの10～100倍の消費電力を消費しています。寂しいためにテレビを点けている場合には、省エネのために、ラジオやCDなどに代えてみてください。 | T72: テレビは画面を映し出す必要があるため、ラジオの10～100倍の消費電力を消費しています。寂しいためにテレビを点けている場合には、省エネのために、ラジオやCDなどに代えてみてください。 | U72: 1 | V72: wss | Z72: ="D6.scenario.defMeasures['"&C72&"'] = { "&B$2&":"""&B72&""", "&C$2&":"""&C72&""", "&D$2&":"""&CLEAN(SUBSTITUTE(D72,"""","'"))&""", "&I$2&":"""&I72&""", "&F$2&":"""&F72&""", "&G$2&":"""&CLEAN(SUBSTITUTE(G72,"""","'"))&""", "&K$2&":"""&K72&""", "&L$2&":"""&L72&""", "&M$2&":"""&M72&""", "&N$2&":"""&N72&""", "&O$2&":"""&O72&""", "&P$2&":"""&P72&""", "&Q$2&":"""&Q72&""", "&S$2&":"""&CLEAN(SUBSTITUTE(S72,"""","'"))&""", "&U$2&":"""&U72&""", "&V$2&":"""&V72&"""};" -> D6.scenario.defMeasures['mTVradio'] = { mid:"602", name:"mTVradio", title:"テレビの時間の半分をラジオにする", easyness:"1", refCons:"consTVsum", titleShort:"ラジオ", level:"", figNum:"7", lifeTime:"", price:"", roanShow:"", standardType:"", subsidy :"", advice:"テレビは画面を映し出す必要があるため、ラジオの10～100倍の消費電力を消費しています。寂しいためにテレビを点けている場合には、省エネのために、ラジオやCDなどに代えてみてください。", lifestyle:"1", season:"wss"}; | AB72: ="$defMeasures['"&C72&"'] = [ '"&B$2&"'=>"""&B72&""", '"&D$2&"'=>"""&CLEAN(SUBSTITUTE(D72,"""","'"))&""", '"&L$2&"'=>"""&L72&""", '"&S$2&"'=>"""&CLEAN(SUBSTITUTE(S72,"""","'"))&"""];" -> $defMeasures['mTVradio'] = [ 'mid'=>"602", 'title'=>"テレビの時間の半分をラジオにする", 'figNum'=>"7", 'advice'=>"テレビは画面を映し出す必要があるため、ラジオの10～100倍の消費電力を消費しています。寂しいためにテレビを点けている場合には、省エネのために、ラジオやCDなどに代えてみてください。"]; | AD72: テレビでなくラジオをつかう
B73: 603 | C73: mTVtime | D73: テレビを点ける時間を1日1時間短くする | E73: テレビを点ける時間を1日1時間短くする | F73: consTV | G73: テレビ短縮 | H73: テレビ短縮 | I73: 3 | J73: 3 | L73: 7 | S73: あらかじめ視るテレビ番組を決めておき、終わったらテレビを消すようにしましょう。点けっぱなしにしていると、意図せずに次の番組まで見てしまうことになります。またテレビゲームの場合にもは、長時間しがちですので、使う時間を短くするように心がけましょう。 | T73: あらかじめ視るテレビ番組を決めておき、終わったらテレビを消すようにしましょう。点けっぱなしにしていると、意図せずに次の番組まで見てしまうことになります。またテレビゲームの場合にもは、長時間しがちですので、使う時間を短くするように心がけましょう。 | U73: 1 | V73: wss | Z73: ="D6.scenario.defMeasures['"&C73&"'] = { "&B$2&":"""&B73&""", "&C$2&":"""&C73&""", "&D$2&":"""&CLEAN(SUBSTITUTE(D73,"""","'"))&""", "&I$2&":"""&I73&""", "&F$2&":"""&F73&""", "&G$2&":"""&CLEAN(SUBSTITUTE(G73,"""","'"))&""", "&K$2&":"""&K73&""", "&L$2&":"""&L73&""", "&M$2&":"""&M73&""", "&N$2&":"""&N73&""", "&O$2&":"""&O73&""", "&P$2&":"""&P73&""", "&Q$2&":"""&Q73&""", "&S$2&":"""&CLEAN(SUBSTITUTE(S73,"""","'"))&""", "&U$2&":"""&U73&""", "&V$2&":"""&V73&"""};" -> D6.scenario.defMeasures['mTVtime'] = { mid:"603", name:"mTVtime", title:"テレビを点ける時間を1日1時間短くする", easyness:"3", refCons:"consTV", titleShort:"テレビ短縮", level:"", figNum:"7", lifeTime:"", price:"", roanShow:"", standardType:"", subsidy :"", advice:"あらかじめ視るテレビ番組を決めておき、終わったらテレビを消すようにしましょう。点けっぱなしにしていると、意図せずに次の番組まで見てしまうことになります。またテレビゲームの場合にもは、長時間しがちですので、使う時間を短くするように心がけましょう。", lifestyle:"1", season:"wss"}; | AB73: ="$defMeasures['"&C73&"'] = [ '"&B$2&"'=>"""&B73&""", '"&D$2&"'=>"""&CLEAN(SUBSTITUTE(D73,"""","'"))&""", '"&L$2&"'=>"""&L73&""", '"&S$2&"'=>"""&CLEAN(SUBSTITUTE(S73,"""","'"))&"""];" -> $defMeasures['mTVtime'] = [ 'mid'=>"603", 'title'=>"テレビを点ける時間を1日1時間短くする", 'figNum'=>"7", 'advice'=>"あらかじめ視るテレビ番組を決めておき、終わったらテレビを消すようにしましょう。点けっぱなしにしていると、意図せずに次の番組まで見てしまうことになります。またテレビゲームの場合にもは、長時間しがちですので、使う時間を短くするように心がけましょう。"]; | AD73: テレビを1時間みじかくする
B74: 604 | C74: mTVbright | D74: テレビの画面を明るすぎないよう調整する | E74: テレビの画面を明るすぎないよう調整する | F74: consTV | G74: テレビ明るさ調節 | H74: テレビ明るさ調節 | I74: 2 | J74: 2 | L74: 7 | S74: テレビの画面の明るさを調節できるようになっています。販売時には明るく設定がされており、このままでは家ではまぶしすぎ、消費電力も多くなります。明るさを控えめに設定することで、2～4割程度消費電力が削減されます。新しいテレビでは、センサーで自動調節するタイプもあります。 | T74: テレビの画面の明るさを調節できるようになっています。販売時には明るく設定がされており、このままでは家ではまぶしすぎ、消費電力も多くなります。明るさを控えめに設定することで、2～4割程度消費電力が削減されます。新しいテレビでは、センサーで自動調節するタイプもあります。 | U74: 1 | V74: wss | Z74: ="D6.scenario.defMeasures['"&C74&"'] = { "&B$2&":"""&B74&""", "&C$2&":"""&C74&""", "&D$2&":"""&CLEAN(SUBSTITUTE(D74,"""","'"))&""", "&I$2&":"""&I74&""", "&F$2&":"""&F74&""", "&G$2&":"""&CLEAN(SUBSTITUTE(G74,"""","'"))&""", "&K$2&":"""&K74&""", "&L$2&":"""&L74&""", "&M$2&":"""&M74&""", "&N$2&":"""&N74&""", "&O$2&":"""&O74&""", "&P$2&":"""&P74&""", "&Q$2&":"""&Q74&""", "&S$2&":"""&CLEAN(SUBSTITUTE(S74,"""","'"))&""", "&U$2&":"""&U74&""", "&V$2&":"""&V74&"""};" -> D6.scenario.defMeasures['mTVbright'] = { mid:"604", name:"mTVbright", title:"テレビの画面を明るすぎないよう調整する", easyness:"2", refCons:"consTV", titleShort:"テレビ明るさ調節", level:"", figNum:"7", lifeTime:"", price:"", roanShow:"", standardType:"", subsidy :"", advice:"テレビの画面の明るさを調節できるようになっています。販売時には明るく設定がされており、このままでは家ではまぶしすぎ、消費電力も多くなります。明るさを控えめに設定することで、2～4割程度消費電力が削減されます。新しいテレビでは、センサーで自動調節するタイプもあります。", lifestyle:"1", season:"wss"}; | AB74: ="$defMeasures['"&C74&"'] = [ '"&B$2&"'=>"""&B74&""", '"&D$2&"'=>"""&CLEAN(SUBSTITUTE(D74,"""","'"))&""", '"&L$2&"'=>"""&L74&""", '"&S$2&"'=>"""&CLEAN(SUBSTITUTE(S74,"""","'"))&"""];" -> $defMeasures['mTVbright'] = [ 'mid'=>"604", 'title'=>"テレビの画面を明るすぎないよう調整する", 'figNum'=>"7", 'advice'=>"テレビの画面の明るさを調節できるようになっています。販売時には明るく設定がされており、このままでは家ではまぶしすぎ、消費電力も多くなります。明るさを控えめに設定することで、2～4割程度消費電力が削減されます。新しいテレビでは、センサーで自動調節するタイプもあります。"]; | AD74: テレビの明るさをちょうせつする
B75: 701 | C75: mRFreplace | D75: 冷蔵庫を省エネ型に買い替える | E75: 冷蔵庫を省エネ型に買い替える | F75: consRF | G75: 省エネ冷蔵庫 | H75: 省エネ冷蔵庫 | I75: 2 | J75: 2 | L75: 2 | M75: 10 | N75: 150000 | P75: 普及型 | S75: 以前の機種に比べると半分くらいの電気ですむ省エネ型冷蔵庫があります。選ぶ時には、統一省エネラベルの★マークの数が多いものや、年間電気代の表示を参考に省エネ型を選んでください。買換のときには、古い冷蔵庫は家電リサイクルの制度で引き取ってもらうようにしましょう。 | T75: 以前の機種に比べると半分くらいの電気ですむ省エネ型冷蔵庫があります。選ぶ時には、統一省エネラベルの★マークの数が多いものや、年間電気代の表示を参考に省エネ型を選んでください。買換のときには、古い冷蔵庫は家電リサイクルの制度で引き取ってもらうようにしましょう。 | V75: wss | Z75: ="D6.scenario.defMeasures['"&C75&"'] = { "&B$2&":"""&B75&""", "&C$2&":"""&C75&""", "&D$2&":"""&CLEAN(SUBSTITUTE(D75,"""","'"))&""", "&I$2&":"""&I75&""", "&F$2&":"""&F75&""", "&G$2&":"""&CLEAN(SUBSTITUTE(G75,"""","'"))&""", "&K$2&":"""&K75&""", "&L$2&":"""&L75&""", "&M$2&":"""&M75&""", "&N$2&":"""&N75&""", "&O$2&":"""&O75&""", "&P$2&":"""&P75&""", "&Q$2&":"""&Q75&""", "&S$2&":"""&CLEAN(SUBSTITUTE(S75,"""","'"))&""", "&U$2&":"""&U75&""", "&V$2&":"""&V75&"""};" -> D6.scenario.defMeasures['mRFreplace'] = { mid:"701", name:"mRFreplace", title:"冷蔵庫を省エネ型に買い替える", easyness:"2", refCons:"consRF", titleShort:"省エネ冷蔵庫", level:"", figNum:"2", lifeTime:"10", price:"150000", roanShow:"", standardType:"普及型", subsidy :"", advice:"以前の機種に比べると半分くらいの電気ですむ省エネ型冷蔵庫があります。選ぶ時には、統一省エネラベルの★マークの数が多いものや、年間電気代の表示を参考に省エネ型を選んでください。買換のときには、古い冷蔵庫は家電リサイクルの制度で引き取ってもらうようにしましょう。", lifestyle:"", season:"wss"}; | AB75: ="$defMeasures['"&C75&"'] = [ '"&B$2&"'=>"""&B75&""", '"&D$2&"'=>"""&CLEAN(SUBSTITUTE(D75,"""","'"))&""", '"&L$2&"'=>"""&L75&""", '"&S$2&"'=>"""&CLEAN(SUBSTITUTE(S75,"""","'"))&"""];" -> $defMeasures['mRFreplace'] = [ 'mid'=>"701", 'title'=>"冷蔵庫を省エネ型に買い替える", 'figNum'=>"2", 'advice'=>"以前の機種に比べると半分くらいの電気ですむ省エネ型冷蔵庫があります。選ぶ時には、統一省エネラベルの★マークの数が多いものや、年間電気代の表示を参考に省エネ型を選んでください。買換のときには、古い冷蔵庫は家電リサイクルの制度で引き取ってもらうようにしましょう。"]; | AD75: 冷ぞう庫を買いかえる
B76: 702 | C76: mRFstop | D76: 冷蔵庫のうち１台を止める | E76: 冷蔵庫のうち１台を止める | F76: consRF | G76: 冷蔵庫停止 | H76: 冷蔵庫停止 | I76: 2 | J76: 2 | L76: 2 | S76: 冷蔵庫を2台以上使っている場合には、1台を止めてください。小型の冷蔵庫でも大型と同じくらい多くの電気を消費します。使えるのに使わないでおくと「もったいない」と感じるかもしれませんが、電気を入れているだけで大きな環境負荷が生じますので、使わないほうが望ましいです。 | T76: 冷蔵庫を2台以上使っている場合には、1台を止めてください。小型の冷蔵庫でも大型と同じくらい多くの電気を消費します。使えるのに使わないでおくと「もったいない」と感じるかもしれませんが、電気を入れているだけで大きな環境負荷が生じますので、使わないほうが望ましいです。 | U76: 1 | V76: wss | Z76: ="D6.scenario.defMeasures['"&C76&"'] = { "&B$2&":"""&B76&""", "&C$2&":"""&C76&""", "&D$2&":"""&CLEAN(SUBSTITUTE(D76,"""","'"))&""", "&I$2&":"""&I76&""", "&F$2&":"""&F76&""", "&G$2&":"""&CLEAN(SUBSTITUTE(G76,"""","'"))&""", "&K$2&":"""&K76&""", "&L$2&":"""&L76&""", "&M$2&":"""&M76&""", "&N$2&":"""&N76&""", "&O$2&":"""&O76&""", "&P$2&":"""&P76&""", "&Q$2&":"""&Q76&""", "&S$2&":"""&CLEAN(SUBSTITUTE(S76,"""","'"))&""", "&U$2&":"""&U76&""", "&V$2&":"""&V76&"""};" -> D6.scenario.defMeasures['mRFstop'] = { mid:"702", name:"mRFstop", title:"冷蔵庫のうち１台を止める", easyness:"2", refCons:"consRF", titleShort:"冷蔵庫停止", level:"", figNum:"2", lifeTime:"", price:"", roanShow:"", standardType:"", subsidy :"", advice:"冷蔵庫を2台以上使っている場合には、1台を止めてください。小型の冷蔵庫でも大型と同じくらい多くの電気を消費します。使えるのに使わないでおくと「もったいない」と感じるかもしれませんが、電気を入れているだけで大きな環境負荷が生じますので、使わないほうが望ましいです。", lifestyle:"1", season:"wss"}; | AB76: ="$defMeasures['"&C76&"'] = [ '"&B$2&"'=>"""&B76&""", '"&D$2&"'=>"""&CLEAN(SUBSTITUTE(D76,"""","'"))&""", '"&L$2&"'=>"""&L76&""", '"&S$2&"'=>"""&CLEAN(SUBSTITUTE(S76,"""","'"))&"""];" -> $defMeasures['mRFstop'] = [ 'mid'=>"702", 'title'=>"冷蔵庫のうち１台を止める", 'figNum'=>"2", 'advice'=>"冷蔵庫を2台以上使っている場合には、1台を止めてください。小型の冷蔵庫でも大型と同じくらい多くの電気を消費します。使えるのに使わないでおくと「もったいない」と感じるかもしれませんが、電気を入れているだけで大きな環境負荷が生じますので、使わないほうが望ましいです。"]; | AD76: 冷ぞう庫を止める
B77: 703 | C77: mRFwall | D77: 冷蔵庫を壁から離す | E77: 冷蔵庫を壁から離す | F77: consRF | G77: 冷蔵庫位置 | H77: 冷蔵庫位置 | I77: 4 | J77: 4 | L77: 2 | S77: 冷蔵庫は壁から5cm程度離すのが目安です。冷蔵庫は側面や天井面から熱を逃がしていますが、壁に接していると熱が逃げにくくなり、消費電力が1割程度増えてしまいます。 | T77: 冷蔵庫は壁から5cm程度離すのが目安です。冷蔵庫は側面や天井面から熱を逃がしていますが、壁に接していると熱が逃げにくくなり、消費電力が1割程度増えてしまいます。 | U77: 1 | V77: wss | Z77: ="D6.scenario.defMeasures['"&C77&"'] = { "&B$2&":"""&B77&""", "&C$2&":"""&C77&""", "&D$2&":"""&CLEAN(SUBSTITUTE(D77,"""","'"))&""", "&I$2&":"""&I77&""", "&F$2&":"""&F77&""", "&G$2&":"""&CLEAN(SUBSTITUTE(G77,"""","'"))&""", "&K$2&":"""&K77&""", "&L$2&":"""&L77&""", "&M$2&":"""&M77&""", "&N$2&":"""&N77&""", "&O$2&":"""&O77&""", "&P$2&":"""&P77&""", "&Q$2&":"""&Q77&""", "&S$2&":"""&CLEAN(SUBSTITUTE(S77,"""","'"))&""", "&U$2&":"""&U77&""", "&V$2&":"""&V77&"""};" -> D6.scenario.defMeasures['mRFwall'] = { mid:"703", name:"mRFwall", title:"冷蔵庫を壁から離す", easyness:"4", refCons:"consRF", titleShort:"冷蔵庫位置", level:"", figNum:"2", lifeTime:"", price:"", roanShow:"", standardType:"", subsidy :"", advice:"冷蔵庫は壁から5cm程度離すのが目安です。冷蔵庫は側面や天井面から熱を逃がしていますが、壁に接していると熱が逃げにくくなり、消費電力が1割程度増えてしまいます。", lifestyle:"1", season:"wss"}; | AB77: ="$defMeasures['"&C77&"'] = [ '"&B$2&"'=>"""&B77&""", '"&D$2&"'=>"""&CLEAN(SUBSTITUTE(D77,"""","'"))&""", '"&L$2&"'=>"""&L77&""", '"&S$2&"'=>"""&CLEAN(SUBSTITUTE(S77,"""","'"))&"""];" -> $defMeasures['mRFwall'] = [ 'mid'=>"703", 'title'=>"冷蔵庫を壁から離す", 'figNum'=>"2", 'advice'=>"冷蔵庫は壁から5cm程度離すのが目安です。冷蔵庫は側面や天井面から熱を逃がしていますが、壁に接していると熱が逃げにくくなり、消費電力が1割程度増えてしまいます。"]; | AD77: 冷ぞうこを、かべからはなす
B78: 704 | C78: mRFtemplature | D78: 冷蔵庫の温度設定を控えめにする | E78: 冷蔵庫の温度設定を控えめにする | F78: consRF | G78: 冷蔵温度 | H78: 冷蔵温度 | I78: 4 | J78: 4 | L78: 2 | S78: 冷蔵庫は温度調節ができます。設定を、強から中へ、中から弱へするとそれぞれ1割程度省エネができます。食品の傷みがやや速くなりますので、支障がないか確認しながら試してみてください。 | T78: 冷蔵庫は温度調節ができます。設定を、強から中へ、中から弱へするとそれぞれ1割程度省エネができます。食品の傷みがやや速くなりますので、支障がないか確認しながら試してみてください。 | U78: 1 | V78: wss | Z78: ="D6.scenario.defMeasures['"&C78&"'] = { "&B$2&":"""&B78&""", "&C$2&":"""&C78&""", "&D$2&":"""&CLEAN(SUBSTITUTE(D78,"""","'"))&""", "&I$2&":"""&I78&""", "&F$2&":"""&F78&""", "&G$2&":"""&CLEAN(SUBSTITUTE(G78,"""","'"))&""", "&K$2&":"""&K78&""", "&L$2&":"""&L78&""", "&M$2&":"""&M78&""", "&N$2&":"""&N78&""", "&O$2&":"""&O78&""", "&P$2&":"""&P78&""", "&Q$2&":"""&Q78&""", "&S$2&":"""&CLEAN(SUBSTITUTE(S78,"""","'"))&""", "&U$2&":"""&U78&""", "&V$2&":"""&V78&"""};" -> D6.scenario.defMeasures['mRFtemplature'] = { mid:"704", name:"mRFtemplature", title:"冷蔵庫の温度設定を控えめにする", easyness:"4", refCons:"consRF", titleShort:"冷蔵温度", level:"", figNum:"2", lifeTime:"", price:"", roanShow:"", standardType:"", subsidy :"", advice:"冷蔵庫は温度調節ができます。設定を、強から中へ、中から弱へするとそれぞれ1割程度省エネができます。食品の傷みがやや速くなりますので、支障がないか確認しながら試してみてください。", lifestyle:"1", season:"wss"}; | AB78: ="$defMeasures['"&C78&"'] = [ '"&B$2&"'=>"""&B78&""", '"&D$2&"'=>"""&CLEAN(SUBSTITUTE(D78,"""","'"))&""", '"&L$2&"'=>"""&L78&""", '"&S$2&"'=>"""&CLEAN(SUBSTITUTE(S78,"""","'"))&"""];" -> $defMeasures['mRFtemplature'] = [ 'mid'=>"704", 'title'=>"冷蔵庫の温度設定を控えめにする", 'figNum'=>"2", 'advice'=>"冷蔵庫は温度調節ができます。設定を、強から中へ、中から弱へするとそれぞれ1割程度省エネができます。食品の傷みがやや速くなりますので、支障がないか確認しながら試してみてください。"]; | AD78: 冷ぞうこの設定を弱くする
B79: 801 | C79: mCRreplace | D79: エコカーに買い替える | E79: エコカーに買い替える | F79: consCR | G79: 車買い替え | H79: 車買い替え | I79: 2 | J79: 2 | L79: 21 | M79: 8 | N79: 1800000 | P79: 普及型 | Q79: エコカーの導入にあたっては、「減税」のメリットが得られます。 | R79: エコカーの導入にあたっては、「減税」のメリットが得られます。 | S79: ハイブリッド車や電気自動車以外にも、技術改善により、既存の燃料消費が半分程度で済む低燃費車が開発されて販売されています。購入時には燃費を考慮して選んで下さい。 | T79: ハイブリッド車や電気自動車以外にも、技術改善により、既存の燃料消費が半分程度で済む低燃費車が開発されて販売されています。購入時には燃費を考慮して選んで下さい。 | V79: wss | Z79: ="D6.scenario.defMeasures['"&C79&"'] = { "&B$2&":"""&B79&""", "&C$2&":"""&C79&""", "&D$2&":"""&CLEAN(SUBSTITUTE(D79,"""","'"))&""", "&I$2&":"""&I79&""", "&F$2&":"""&F79&""", "&G$2&":"""&CLEAN(SUBSTITUTE(G79,"""","'"))&""", "&K$2&":"""&K79&""", "&L$2&":"""&L79&""", "&M$2&":"""&M79&""", "&N$2&":"""&N79&""", "&O$2&":"""&O79&""", "&P$2&":"""&P79&""", "&Q$2&":"""&Q79&""", "&S$2&":"""&CLEAN(SUBSTITUTE(S79,"""","'"))&""", "&U$2&":"""&U79&""", "&V$2&":"""&V79&"""};" -> D6.scenario.defMeasures['mCRreplace'] = { mid:"801", name:"mCRreplace", title:"エコカーに買い替える", easyness:"2", refCons:"consCR", titleShort:"車買い替え", level:"", figNum:"21", lifeTime:"8", price:"1800000", roanShow:"", standardType:"普及型", subsidy :"エコカーの導入にあたっては、「減税」のメリットが得られます。", advice:"ハイブリッド車や電気自動車以外にも、技術改善により、既存の燃料消費が半分程度で済む低燃費車が開発されて販売されています。購入時には燃費を考慮して選んで下さい。", lifestyle:"", season:"wss"}; | AB79: ="$defMeasures['"&C79&"'] = [ '"&B$2&"'=>"""&B79&""", '"&D$2&"'=>"""&CLEAN(SUBSTITUTE(D79,"""","'"))&""", '"&L$2&"'=>"""&L79&""", '"&S$2&"'=>"""&CLEAN(SUBSTITUTE(S79,"""","'"))&"""];" -> $defMeasures['mCRreplace'] = [ 'mid'=>"801", 'title'=>"エコカーに買い替える", 'figNum'=>"21", 'advice'=>"ハイブリッド車や電気自動車以外にも、技術改善により、既存の燃料消費が半分程度で済む低燃費車が開発されて販売されています。購入時には燃費を考慮して選んで下さい。"]; | AD79: エコカーに買いかえる
B80: 802 | C80: mCRreplaceElec | D80: 電気自動車を導入する | E80: 電気自動車を導入する | F80: consCR | G80: 電気自動車 | H80: 電気自動車 | I80: 1 | J80: 1 | L80: 21 | M80: 7 | N80: 3000000 | Q80: 電気自動車の導入にあたっては、「CEV補助金」「減税」のメリットが得られます。 | S80: 電気自動車は、ガソリンの代わりに充電された電気を使い、エンジンの代わりにモーターを回して走ります。エンジンに比べて効率が高く、十分実用的な車として販売がされています。ただし充電スタンドはまだ少なく、充電に時間がかかるため、夜間に充電しておく必要があります。欧州や中国などでは、2040年ころまでにエンジン式の自動車から電気自動車に切り替える方針としています。 | T80: 電気自動車は、ガソリンの代わりに充電された電気を使い、エンジンの代わりにモーターを回して走ります。エンジンに比べて効率が高く、十分実用的な車として販売がされています。ただし充電スタンドはまだ少なく、充電に時間がかかるため、夜間に充電しておく必要があります。欧州や中国などでは、2040年ころまでにエンジン式の自動車から電気自動車に切り替える方針としています。 | V80: wss | Z80: ="D6.scenario.defMeasures['"&C80&"'] = { "&B$2&":"""&B80&""", "&C$2&":"""&C80&""", "&D$2&":"""&CLEAN(SUBSTITUTE(D80,"""","'"))&""", "&I$2&":"""&I80&""", "&F$2&":"""&F80&""", "&G$2&":"""&CLEAN(SUBSTITUTE(G80,"""","'"))&""", "&K$2&":"""&K80&""", "&L$2&":"""&L80&""", "&M$2&":"""&M80&""", "&N$2&":"""&N80&""", "&O$2&":"""&O80&""", "&P$2&":"""&P80&""", "&Q$2&":"""&Q80&""", "&S$2&":"""&CLEAN(SUBSTITUTE(S80,"""","'"))&""", "&U$2&":"""&U80&""", "&V$2&":"""&V80&"""};" -> D6.scenario.defMeasures['mCRreplaceElec'] = { mid:"802", name:"mCRreplaceElec", title:"電気自動車を導入する", easyness:"1", refCons:"consCR", titleShort:"電気自動車", level:"", figNum:"21", lifeTime:"7", price:"3000000", roanShow:"", standardType:"", subsidy :"電気自動車の導入にあたっては、「CEV補助金」「減税」のメリットが得られます。", advice:"電気自動車は、ガソリンの代わりに充電された電気を使い、エンジンの代わりにモーターを回して走ります。エンジンに比べて効率が高く、十分実用的な車として販売がされています。ただし充電スタンドはまだ少なく、充電に時間がかかるため、夜間に充電しておく必要があります。欧州や中国などでは、2040年ころまでにエンジン式の自動車から電気自動車に切り替える方針としています。", lifestyle:"", season:"wss"}; | AB80: ="$defMeasures['"&C80&"'] = [ '"&B$2&"'=>"""&B80&""", '"&D$2&"'=>"""&CLEAN(SUBSTITUTE(D80,"""","'"))&""", '"&L$2&"'=>"""&L80&""", '"&S$2&"'=>"""&CLEAN(SUBSTITUTE(S80,"""","'"))&"""];" -> $defMeasures['mCRreplaceElec'] = [ 'mid'=>"802", 'title'=>"電気自動車を導入する", 'figNum'=>"21", 'advice'=>"電気自動車は、ガソリンの代わりに充電された電気を使い、エンジンの代わりにモーターを回して走ります。エンジンに比べて効率が高く、十分実用的な車として販売がされています。ただし充電スタンドはまだ少なく、充電に時間がかかるため、夜間に充電しておく必要があります。欧州や中国などでは、2040年ころまでにエンジン式の自動車から電気自動車に切り替える方針としています。"]; | AD80: 電気自動車にする
B81: 803 | C81: mCRecoDrive | D81: アイドリングストップなどエコドライブに心がける | E81: アイドリングストップなどエコドライブに心がける | F81: consCRsum | G81: エコドライブ | H81: エコドライブ | I81: 3 | J81: 3 | L81: 21 | S81: アイドリングストップのほか、発進時にふんわりスタートすることにより、燃費を1割程度向上させることができます。 | T81: アイドリングストップのほか、発進時にふんわりスタートすることにより、燃費を1割程度向上させることができます。 | U81: 1 | V81: wss | Z81: ="D6.scenario.defMeasures['"&C81&"'] = { "&B$2&":"""&B81&""", "&C$2&":"""&C81&""", "&D$2&":"""&CLEAN(SUBSTITUTE(D81,"""","'"))&""", "&I$2&":"""&I81&""", "&F$2&":"""&F81&""", "&G$2&":"""&CLEAN(SUBSTITUTE(G81,"""","'"))&""", "&K$2&":"""&K81&""", "&L$2&":"""&L81&""", "&M$2&":"""&M81&""", "&N$2&":"""&N81&""", "&O$2&":"""&O81&""", "&P$2&":"""&P81&""", "&Q$2&":"""&Q81&""", "&S$2&":"""&CLEAN(SUBSTITUTE(S81,"""","'"))&""", "&U$2&":"""&U81&""", "&V$2&":"""&V81&"""};" -> D6.scenario.defMeasures['mCRecoDrive'] = { mid:"803", name:"mCRecoDrive", title:"アイドリングストップなどエコドライブに心がける", easyness:"3", refCons:"consCRsum", titleShort:"エコドライブ", level:"", figNum:"21", lifeTime:"", price:"", roanShow:"", standardType:"", subsidy :"", advice:"アイドリングストップのほか、発進時にふんわりスタートすることにより、燃費を1割程度向上させることができます。", lifestyle:"1", season:"wss"}; | AB81: ="$defMeasures['"&C81&"'] = [ '"&B$2&"'=>"""&B81&""", '"&D$2&"'=>"""&CLEAN(SUBSTITUTE(D81,"""","'"))&""", '"&L$2&"'=>"""&L81&""", '"&S$2&"'=>"""&CLEAN(SUBSTITUTE(S81,"""","'"))&"""];" -> $defMeasures['mCRecoDrive'] = [ 'mid'=>"803", 'title'=>"アイドリングストップなどエコドライブに心がける", 'figNum'=>"21", 'advice'=>"アイドリングストップのほか、発進時にふんわりスタートすることにより、燃費を1割程度向上させることができます。"]; | AD81: エコドライブにこころがける
B82: 804 | C82: mCRtrain | D82: 鉄道やバスなど公共交通機関を利用する | E82: 鉄道やバスなど公共交通機関を利用する | F82: consCRtrip | G82: 公共交通 | H82: 公共交通 | I82: 2 | J82: 2 | L82: 22 | S82: 2km程度の近所の場合で、気候がいいときには、車を使わずに自転車を使ったり、歩いたりしましょう。健康のためにもなります。 | T82: 2km程度の近所の場合で、気候がいいときには、車を使わずに自転車を使ったり、歩いたりしましょう。健康のためにもなります。 | U82: 1 | V82: wss | Z82: ="D6.scenario.defMeasures['"&C82&"'] = { "&B$2&":"""&B82&""", "&C$2&":"""&C82&""", "&D$2&":"""&CLEAN(SUBSTITUTE(D82,"""","'"))&""", "&I$2&":"""&I82&""", "&F$2&":"""&F82&""", "&G$2&":"""&CLEAN(SUBSTITUTE(G82,"""","'"))&""", "&K$2&":"""&K82&""", "&L$2&":"""&L82&""", "&M$2&":"""&M82&""", "&N$2&":"""&N82&""", "&O$2&":"""&O82&""", "&P$2&":"""&P82&""", "&Q$2&":"""&Q82&""", "&S$2&":"""&CLEAN(SUBSTITUTE(S82,"""","'"))&""", "&U$2&":"""&U82&""", "&V$2&":"""&V82&"""};" -> D6.scenario.defMeasures['mCRtrain'] = { mid:"804", name:"mCRtrain", title:"鉄道やバスなど公共交通機関を利用する", easyness:"2", refCons:"consCRtrip", titleShort:"公共交通", level:"", figNum:"22", lifeTime:"", price:"", roanShow:"", standardType:"", subsidy :"", advice:"2km程度の近所の場合で、気候がいいときには、車を使わずに自転車を使ったり、歩いたりしましょう。健康のためにもなります。", lifestyle:"1", season:"wss"}; | AB82: ="$defMeasures['"&C82&"'] = [ '"&B$2&"'=>"""&B82&""", '"&D$2&"'=>"""&CLEAN(SUBSTITUTE(D82,"""","'"))&""", '"&L$2&"'=>"""&L82&""", '"&S$2&"'=>"""&CLEAN(SUBSTITUTE(S82,"""","'"))&"""];" -> $defMeasures['mCRtrain'] = [ 'mid'=>"804", 'title'=>"鉄道やバスなど公共交通機関を利用する", 'figNum'=>"22", 'advice'=>"2km程度の近所の場合で、気候がいいときには、車を使わずに自転車を使ったり、歩いたりしましょう。健康のためにもなります。"]; | AD82: 鉄道やバスを使う
B83: 805 | C83: mCR20percent | D83: 車の利用を2割止める | E83: 車の利用を2割止める | F83: consCRtrip | G83: 車の利用2割減 | H83: 車の利用2割減 | I83: 1 | J83: 1 | L83: 22 | S83: 車の利用は多くのエネルギーを消費します。必要性の薄い用途には使わないなどの工夫が大切です。 | T83: 車の利用は多くのエネルギーを消費します。必要性の薄い用途には使わないなどの工夫が大切です。 | U83: 1 | V83: wss | Z83: ="D6.scenario.defMeasures['"&C83&"'] = { "&B$2&":"""&B83&""", "&C$2&":"""&C83&""", "&D$2&":"""&CLEAN(SUBSTITUTE(D83,"""","'"))&""", "&I$2&":"""&I83&""", "&F$2&":"""&F83&""", "&G$2&":"""&CLEAN(SUBSTITUTE(G83,"""","'"))&""", "&K$2&":"""&K83&""", "&L$2&":"""&L83&""", "&M$2&":"""&M83&""", "&N$2&":"""&N83&""", "&O$2&":"""&O83&""", "&P$2&":"""&P83&""", "&Q$2&":"""&Q83&""", "&S$2&":"""&CLEAN(SUBSTITUTE(S83,"""","'"))&""", "&U$2&":"""&U83&""", "&V$2&":"""&V83&"""};" -> D6.scenario.defMeasures['mCR20percent'] = { mid:"805", name:"mCR20percent", title:"車の利用を2割止める", easyness:"1", refCons:"consCRtrip", titleShort:"車の利用2割減", level:"", figNum:"22", lifeTime:"", price:"", roanShow:"", standardType:"", subsidy :"", advice:"車の利用は多くのエネルギーを消費します。必要性の薄い用途には使わないなどの工夫が大切です。", lifestyle:"1", season:"wss"}; | AB83: ="$defMeasures['"&C83&"'] = [ '"&B$2&"'=>"""&B83&""", '"&D$2&"'=>"""&CLEAN(SUBSTITUTE(D83,"""","'"))&""", '"&L$2&"'=>"""&L83&""", '"&S$2&"'=>"""&CLEAN(SUBSTITUTE(S83,"""","'"))&"""];" -> $defMeasures['mCR20percent'] = [ 'mid'=>"805", 'title'=>"車の利用を2割止める", 'figNum'=>"22", 'advice'=>"車の利用は多くのエネルギーを消費します。必要性の薄い用途には使わないなどの工夫が大切です。"]; | AD83: 全て使うなというのは無茶ですが、ほんとに必要なのか考えると、2割くらい工夫でどうにかなる分はあるのではないでしょうか。
